Workbook

Sheet 模型说明
A1: SP500风控模型 — 技术文档
A3: 1. 模型概述
A5: ● 是什么
A6: 一个基于多维度市场压力指标的风控仓位管理模型。它不预测市场方向，而是衡量当前市场环境的“操作难度”——即在当前条件下持有股票仓位的风险水平。当多个压力指标同时升高时，模型建议降低仓位；压力消退时恢复仓位。
A8: ● 设计哲学
A9: 模型的核心理念是“宁可踏空，不可被套”。它不试图择时（判断涨跌），而是在危险环境中主动降低暴露。代价是在牛市中因不满仓而跟不上基准（年化Alpha约-2%），收益是在熊市和危机中大幅减少损失（最大回撤从-56.2%压缩至-15.2%）。
A11: ● 不是什么
A12: • 不是择时模型：不会说“现在买”或“现在卖”，只调节仓位比例。
A13: • 不是预测模型：不预测未来收益率，只评估当前风险环境。
A14: • 不是交易策略：不包含个股选择、行业轮动、入场/出场时机等细节。
A15: • 不是实时系统：每周更新一次，下周一开盘执行，不做盘中调仓。
A17: ● 核心流程一句话
... A134: • 信号可视化：5张图表（SP500×风险信号、市场风险总览、纯评分、否决权评分、回撤深度） • _图表数据：信号可视化图表的源数据（8列×1,269行）

Sheet 模型评价
A1: 操作难度模型 — 风控有效性评价
A2: 评价视角：模型是否准确识别了不同操作难度的市场环境（非择时/收益评价）
A3: 数据范围 | B3: 评分与状态_周度 行275-1546 | 回测_周度 行262-1529
A4: 有效观测周数 | B4: =COUNTA(回测_周度!D262:D1529)
A6: 一、区分度分析 — 模型说“难”时，市场是否真的更难？
A7: 核心逻辑：如果模型的风险分级是准确的，那么被标为"高风险"的时期，市场应该确实波动更大、极端下跌更频繁。下表将1182周数据按6个风险等级分组，分别统计年化波动率、平均|周收益|、周跌>3%频率、最差单周等指标。如果这些指标从🟢简单到💀炼狱单调递增，说明模型的分类是有效的。"波动倍数"列以简单模式为基准=1.00x，显示各等级相对于最安全时期的波动放大程度。
A9: 风险状态 | B9: 周数 | C9: 占比 | D9: 年化波动率 | E9: 平均|周收益| | F9: 周跌>3%占比 | G9: 最差单周 | H9: 波动倍数vs简单
A10: 🟢 简单模式 | B10: =COUNTIF(评分与状态_周度!E278:E1545,评分与状态_周度!$A$7) | C10: =B10/$B$4 | D10: {=IFERROR(SQRT((B10*SUMPRODUCT((评分与状态_周度!E278:E1545=评分与状态_周度!$A$7)*回测_周度!C262:C1529*回测_周度!C262:C1529)-SUMPRODUCT((评分与状态_周度!E278:E1545=评分与状态_周度!$A$7)*回测_周度!C262:C1529)^2)/(B10*(B10-1))*52),"")} | E10: {=IFERROR(SUMPRODUCT((评分与状态_周度!E278:E1545=评分与状态_周度!$A$7)*ABS(回测_周度!C262:C1529))/B10,"")} | F10: =IFERROR(COUNTIFS(评分与状态_周度!E278:E1545,评分与状态_周度!$A$7,回测_周度!C262:C1529,"<-0.03")/B10,"") | G10: =IFERROR(_xlfn.MINIFS(回测_周度!C262:C1529,评分与状态_周度!E278:E1545,评分与状态_周度!$A$7),"") | H10: —
A11: 🟢 普通模式 | B11: =COUNTIF(评分与状态_周度!E278:E1545,评分与状态_周度!$A$8) | C11: =B11/$B$4 | D11: {=IFERROR(SQRT((B11*SUMPRODUCT((评分与状态_周度!E278:E1545=评分与状态_周度!$A$8)*回测_周度!C262:C1529*回测_周度!C262:C1529)-SUMPRODUCT((评分与状态_周度!E278:E1545=评分与状态_周度!$A$8)*回测_周度!C262:C1529)^2)/(B11*(B11-1))*52),"")} | E11: {=IFERROR(SUMPRODUCT((评分与状态_周度!E278:E1545=评分与状态_周度!$A$8)*ABS(回测_周度!C262:C1529))/B11,"")} | F11: =IFERROR(COUNTIFS(评分与状态_周度!E278:E1545,评分与状态_周度!$A$8,回测_周度!C262:C1529,"<-0.03")/B11,"") | G11: =IFERROR(_xlfn.MINIFS(回测_周度!C262:C1529,评分与状态_周度!E278:E1545,评分与状态_周度!$A$8),"") | H11: =IFERROR(D11/D$10,"")
A12: 🟡 困难模式 | B12: =COUNTIF(评分与状态_周度!E278:E1545,评分与状态_周度!$A$9) | C12: =B12/$B$4 | D12: {=IFERROR(SQRT((B12*SUMPRODUCT((评分与状态_周度!E278:E1545=评分与状态_周度!$A$9)*回测_周度!C262:C1529*回测_周度!C262:C1529)-SUMPRODUCT((评分与状态_周度!E278:E1545=评分与状态_周度!$A$9)*回测_周度!C262:C1529)^2)/(B12*(B12-1))*52),"")} | E12: {=IFERROR(SUMPRODUCT((评分与状态_周度!E278:E1545=评分与状态_周度!$A$9)*ABS(回测_周度!C262:C1529))/B12,"")} | F12: =IFERROR(COUNTIFS(评分与状态_周度!E278:E1545,评分与状态_周度!$A$9,回测_周度!C262:C1529,"<-0.03")/B12,"") | G12: =IFERROR(_xlfn.MINIFS(回测_周度!C262:C1529,评分与状态_周度!E278:E1545,评分与状态_周度!$A$9),"") | H12: =IFERROR(D12/D$10,"")
A13: 🟠 噩梦模式 | B13: =COUNTIF(评分与状态_周度!E278:E1545,评分与状态_周度!$A$10) | C13: =B13/$B$4 | D13: {=IFERROR(SQRT((B13*SUMPRODUCT((评分与状态_周度!E278:E1545=评分与状态_周度!$A$10)*回测_周度!C262:C1529*回测_周度!C262:C1529)-SUMPRODUCT((评分与状态_周度!E278:E1545=评分与状态_周度!$A$10)*回测_周度!C262:C1529)^2)/(B13*(B13-1))*52),"")} | E13: {=IFERROR(SUMPRODUCT((评分与状态_周度!E278:E1545=评分与状态_周度!$A$10)*ABS(回测_周度!C262:C1529))/B13,"")} | F13: =IFERROR(COUNTIFS(评分与状态_周度!E278:E1545,评分与状态_周度!$A$10,回测_周度!C262:C1529,"<-0.03")/B13,"") | G13: =IFERROR(_xlfn.MINIFS(回测_周度!C262:C1529,评分与状态_周度!E278:E1545,评分与状态_周度!$A$10),"") | H13: =IFERROR(D13/D$10,"")
A14: 🔴 地狱模式 | B14: =COUNTIF(评分与状态_周度!E278:E1545,评分与状态_周度!$A$11) | C14: =B14/$B$4 | D14: {=IFERROR(SQRT((B14*SUMPRODUCT((评分与状态_周度!E278:E1545=评分与状态_周度!$A$11)*回测_周度!C262:C1529*回测_周度!C262:C1529)-SUMPRODUCT((评分与状态_周度!E278:E1545=评分与状态_周度!$A$11)*回测_周度!C262:C1529)^2)/(B14*(B14-1))*52),"")} | E14: {=IFERROR(SUMPRODUCT((评分与状态_周度!E278:E1545=评分与状态_周度!$A$11)*ABS(回测_周度!C262:C1529))/B14,"")} | F14: =IFERROR(COUNTIFS(评分与状态_周度!E278:E1545,评分与状态_周度!$A$11,回测_周度!C262:C1529,"<-0.03")/B14,"") | G14: =IFERROR(_xlfn.MINIFS(回测_周度!C262:C1529,评分与状态_周度!E278:E1545,评分与状态_周度!$A$11),"") | H14: =IFERROR(D14/D$10,"")
A15: 💀 炼狱模式 | B15: =COUNTIF(评分与状态_周度!E278:E1545,评分与状态_周度!$A$12) | C15: =B15/$B$4 | D15: {=IFERROR(SQRT((B15*SUMPRODUCT((评分与状态_周度!E278:E1545=评分与状态_周度!$A$12)*回测_周度!C262:C1529*回测_周度!C262:C1529)-SUMPRODUCT((评分与状态_周度!E278:E1545=评分与状态_周度!$A$12)*回测_周度!C262:C1529)^2)/(B15*(B15-1))*52),"")} | E15: {=IFERROR(SUMPRODUCT((评分与状态_周度!E278:E1545=评分与状态_周度!$A$12)*ABS(回测_周度!C262:C1529))/B15,"")} | F15: =IFERROR(COUNTIFS(评分与状态_周度!E278:E1545,评分与状态_周度!$A$12,回测_周度!C262:C1529,"<-0.03")/B15,"") | G15: =IFERROR(_xlfn.MINIFS(回测_周度!C262:C1529,评分与状态_周度!E278:E1545,评分与状态_周度!$A$12),"") | H15: =IFERROR(D15/D$10,"")
A16: 全部 | B16: =SUM(B10:B15) | C16: =B16/$B$4 | D16: =STDEV(回测_周度!C262:C1529)*SQRT(52) | E16: {=AVERAGE(ABS(回测_周度!C262:C1529))} | F16: =COUNTIF(回测_周度!C262:C1529,"<-0.03")/B16 | G16: =MIN(回测_周度!C262:C1529)
A18: ✅ 单调性检验：波动率从简单模式的10.8%递增至炼狱模式的25.8%（2.38倍），周跌>3%频率从2.6%升至14.9%。模型准确区分了不同操作难度的市场环境。
A20: 二、误报分析 — 模型说“难”但市场其实很平静的情况有多少？
A21: 误报的定义：模型判定为"地狱模式"或"炼狱模式"（目标仓位仅15%-35%），但当周市场实际表现平稳（周收益绝对值<1.5%，即无明显方向性波动）。误报的代价是"踏空"——模型让你减仓了，但市场并没有出事，你错过了本可以满仓享受的温和收益。误报率越低越好，但需要与漏报率权衡：过度降低误报往往会增加漏报。
A23: 指标 | B23: 数值
A24: 高风险总周数（地狱+炼狱） | B24: =B14+B15
A25: 其中市场实际平稳的周数 | B25: {=SUMPRODUCT(((评分与状态_周度!E278:E1545=评分与状态_周度!$A$11)+(评分与状态_周度!E278:E1545=评分与状态_周度!$A$12))*(ABS(回测_周度!C262:C1529)<0.015))}
A26: 误报率（平稳周/高风险总周） | B26: =IFERROR(B25/B24,"")
A28: 误报的代价：高风险期平稳周的平均周收益 | B28: {=IFERROR(SUMPRODUCT(((评分与状态_周度!E278:E1545=评分与状态_周度!$A$11)+(评分与状态_周度!E278:E1545=评分与状态_周度!$A$12))*(ABS(回测_周度!C262:C1529)<0.015)*回测_周度!C262:C1529)/B25,"")} | C28: ← 踏空代价：这些周本可满仓享受的平均收益
A30: 三、漏报分析 — 市场真的出事时，模型是否提前预警了？
A31: 漏报的定义：市场出现了极端下跌（周跌>3%或>5%），但模型仍停留在低风险状态（🟢简单或🟢普通模式，仓位≥85%），未能提前预警。漏报的代价是"重仓挨打"——市场暴跌时你几乎满仓承受了全部损失。下方分两个阈值统计：>3%覆盖所有显著下跌（约占总周数的7%），>5%聚焦严重冲击事件。同时展示大跌在6个风险等级中的分布，理想情况下大跌应集中在高风险等级（说明模型在大跌时已经减仓）。
A33: 阈值：周跌幅 > 3%
A34: 指标 | B34: 数值
A35: 周跌>3%总次数 | B35: =COUNTIF(回测_周度!C262:C1529,"<-0.03")
A36: 其中模型处于低风险（简单+普通） | B36: =COUNTIFS(回测_周度!C262:C1529,"<-0.03",评分与状态_周度!E278:E1545,评分与状态_周度!$A$7)+COUNTIFS(回测_周度!C262:C1529,"<-0.03",评分与状态_周度!E278:E1545,评分与状态_周度!$A$8)
A37: 漏报率 | B37: =IFERROR(B36/B35,"") | C37: ← 越低越好：极端下跌时模型未预警的比例
A39: 阈值：周跌幅 > 5%（严重冲击）
A40: 指标 | B40: 数值
A41: 周跌>5%总次数 | B41: =COUNTIF(回测_周度!C262:C1529,"<-0.05")
A42: 其中模型处于低风险（简单+普通） | B42: =COUNTIFS(回测_周度!C262:C1529,"<-0.05",评分与状态_周度!E278:E1545,评分与状态_周度!$A$7)+COUNTIFS(回测_周度!C262:C1529,"<-0.05",评分与状态_周度!E278:E1545,评分与状态_周度!$A$8)
A43: 漏报率 | B43: =IFERROR(B42/B41,"")
A45: 大跌时各风险状态分布（周跌>3%）
A46: 风险状态 | B46: 大跌次数 | C46: 占比
A47: 🟢 简单模式 | B47: =COUNTIFS(回测_周度!C262:C1529,"<-0.03",评分与状态_周度!E278:E1545,评分与状态_周度!$A$7) | C47: =IFERROR(B47/$B$35,"")
A48: 🟢 普通模式 | B48: =COUNTIFS(回测_周度!C262:C1529,"<-0.03",评分与状态_周度!E278:E1545,评分与状态_周度!$A$8) | C48: =IFERROR(B48/$B$35,"")
A49: 🟡 困难模式 | B49: =COUNTIFS(回测_周度!C262:C1529,"<-0.03",评分与状态_周度!E278:E1545,评分与状态_周度!$A$9) | C49: =IFERROR(B49/$B$35,"")
A50: 🟠 噩梦模式 | B50: =COUNTIFS(回测_周度!C262:C1529,"<-0.03",评分与状态_周度!E278:E1545,评分与状态_周度!$A$10) | C50: =IFERROR(B50/$B$35,"")
A51: 🔴 地狱模式 | B51: =COUNTIFS(回测_周度!C262:C1529,"<-0.03",评分与状态_周度!E278:E1545,评分与状态_周度!$A$11) | C51: =IFERROR(B51/$B$35,"")
A52: 💀 炼狱模式 | B52: =COUNTIFS(回测_周度!C262:C1529,"<-0.03",评分与状态_周度!E278:E1545,评分与状态_周度!$A$12) | C52: =IFERROR(B52/$B$35,"")
A53: 合计 | B53: =SUM(B47:B52) | C53: =SUM(C47:C52)
A54: 未评分周（前期数据不足） | B54: =B35-B53 | C54: =IFERROR(B54/$B$35,"")
A56: ✅ 漏报控制：92次周跌>3%中，仅有14次（15.2%）发生在低风险状态；周跌>5%的严重冲击中，漏报率仅为11.1%。大跌更多集中在高风险状态（炼狱模式占比41.3%），模型对极端风险的识别能力强。
A58: 四、响应速度 — 环境恶化后，模型多快反应？
A59: 核心问题：模型升级风险等级后，未来市场是否真的变差了？如果升级后波动率确实升高，说明模型"反应及时"；如果升级后波动率反而不变或下降，说明模型可能"慢了半拍"，信号在风险高峰过后才发出。下表统计三类升级事件：低→中（从简单/普通跳到困难/噩梦）、低→高（直接跳到地狱/炼狱）、中→高（从困难/噩梦升到地狱/炼狱），分别比较升级前4周vs后4周的年化波动率变化。
A61: 升级类型 | B61: 事件数 | C61: 升级前4周波动率 | D61: 升级后4周波动率 | E61: 波动率变化 | F61: 升级后波动率升高率
A62: 低→中（简单/普通 → 困难/噩梦） | B62: 48 | C62: 0.123 | D62: 0.144 | E62: 0.021 | F62: 0.5625
A63: 低→高（简单/普通 → 地狱/炼狱） | B63: 7 | C63: 0.152 | D63: 0.205 | E63: 0.053 | F63: 0.4286
A64: 中→高（困难/噩梦 → 地狱/炼狱） | B64: 40 | C64: 0.158 | D64: 0.151 | E64: -0.007 | F64: 0.425
A65: 全部升级 | B65: 95 | C65: 0.14 | D65: 0.151 | E65: 0.011 | F65: 0.495
A67: ⚠️ 响应速度评价：低→中升级后波动率平均升高2.1%（56.3%升高率）；低→高升级后波动率升高5.3%，但仅有7次样本，统计显著性有限。中→高升级的后4周波动率反而略降（-0.7%），可能说明地狱/炼狱信号有时滞后于波动高峰。
A68: ℹ️ 以上数据通过计算引擎生成（逐行扫描状态变化，统计前后4周年化波动率），非单元格公式。
A70: 五、信号稳定性 — 信号是否可执行，还是频繁抖动？
A71: 实操问题：信号每周都在变，你跟还是不跟？如果模型频繁在不同风险等级间跳动（比如这周炼狱、下周普通、再下周又地狱），实际操作中很难执行——调仓有交易成本，而且频繁反转会让投资者失去信心。下表统计信号的"持续时长"（同一状态连续维持多少周）、方向反转频率、跨级跳变次数。理想的模型应该信号持续较长时间（>4周），而不是每1-2周就翻转一次。
A73: 基本统计
A74: 观测周数 | B74: 1182
A75: 状态切换总次数 | B75: 379
A76: 平均持续周数（每次信号） | B76: 3.1 | C76: 周
A77: 中位持续周数 | B77: 2 | C77: 周
A78: 升级次数 / 降级次数 | B78: 186 / 193
A80: 持续时长分布 | B80: 次数 | C80: 占比
A81: 1-2周（过短，执行困难） | B81: 259 | C81: 0.6816
A82: 3-4周 | B82: 65 | C82: 0.1711
A83: 5-8周 | B83: 30 | C83: 0.0789
A84: 9+周（稳定信号） | B84: 26 | C84: 0.0684
A86: 抽动分析
A87: 跨级跳变（一周跣2级以上） | B87: 54 | C87: 占全部切换的14.2%
A88: 方向反转（连续两周反向移动） | B88: 137 | C88: 占全部切换的36.1%
A90: ⚠️ 信号稳定性评价：平均持续3.1周、中位数2周，68.2%的信号仅维持1-2周，信号抽动明显。建议：① 考虑增加信号“缓冲期”（如连续2周确认后才切换）；② 或将评分平滑（如3周均线）减少高频跳变。
A91: ℹ️ 以上数据通过计算引擎生成（逐行扫描状态序列统计持续时间与跳变频率），非单元格公式。
A93: 六、领先预警效应 — 模型是提前预警还是事后确认？
A94: 终极检验：模型到底是"提前预警"还是"事后确认"？只有领先于市场的信号才有实际执行价值——如果信号总是在暴跌发生后才升级，那对投资者来说已经太迟了。本节从两个角度验证前瞻性：(1) 升级信号发出后，未来1-4周的市场波动是否高于正常水平？(2) 历史上每次大跌发生前，模型是否已经处于警戒状态？
A96: 6.1 前瞻波动率 — 升级信号后的市场波动是否高于基准？
A97: 方法：每次风险等级上调后，计算后续1/2/3/4周的平均|周收益|（波动幅度的代理变量），与全样本长期平均水平对比。"波动倍数">1说明升级后市场波动确实更大，模型具有前瞻性。"超越基准的比例"表示有多少比例的升级事件后波动率高于正常水平。分两组统计："全部风险上调"（任何等级升高，186次）和"升入高风险"（跳入地狱/炼狱模式的47次更极端事件）。
A99: 全部风险上调（186次） | B99: 后1周 | C99: 后2周 | D99: 后3周 | E99: 后4周
A100: 平均|周收益| | B100: 0.01717 | C100: 0.0174 | D100: 0.01752 | E100: 0.01772
A101: 全样本基准 | B101: 0.01685 | C101: 0.01685 | D101: 0.01685 | E101: 0.01684
A102: 波动倍数（vs基准） | B102: 1.02 | C102: 1.03 | D102: 1.04 | E102: 1.05
A103: 超越基准的比例 | B103: 0.366 | C103: 0.387 | D103: 0.382 | E103: 0.419
A105: 升入高风险（47次） | B105: 后1周 | C105: 后2周 | D105: 后3周 | E105: 后4周
A106: 平均|周收益| | B106: 0.01743 | C106: 0.01767 | D106: 0.01896 | E106: 0.01899
A107: 全样本基准 | B107: 0.01685 | C107: 0.01685 | D107: 0.01685 | E107: 0.01684
A108: 波动倍数（vs基准） | B108: 1.03 | C108: 1.05 | D108: 1.13 | E108: 1.13
A109: 超越基准的比例 | B109: 0.362 | C109: 0.426 | D109: 0.511 | E109: 0.489
A111: 6.2 大跌预警提前量 — 大跌前模型是否已处于高警觉？
A112: 方法：对历史上每一次大跌（周跌>3%或>5%），回看大跌前1/2/3/4周该时点的模型状态。如果模型当时已处于困难模式及以上（仓位≤70%），则计为"已预警"。命中率越高、越稳定（各窗口差异小），说明模型预警越持续、越可靠。"平均预警提前量"统计已预警的大跌中，模型在大跌前多少周就首次进入中风险以上状态（最远回看8周）。
A114: 周跌 > 3%（83次有效） | B114: 前1周 | C114: 前2周 | D114: 前3周 | E114: 前4周
A115: 已处于困难模式及以上的次数 | B115: 67 | C115: 62 | D115: 64 | E115: 62
A116: 预警命中率 | B116: 0.807 | C116: 0.747 | D116: 0.771 | E116: 0.747
A118: 周跌 > 5%（25次有效） | B118: 前1周 | C118: 前2周 | D118: 前3周 | E118: 前4周
A119: 已处于困难模式及以上的次数 | B119: 19 | C119: 17 | D119: 19 | E119: 17
A120: 预警命中率 | B120: 0.76 | C120: 0.68 | D120: 0.76 | E120: 0.68
A122: 平均预警提前量 | B122: 周跌>3% | C122: 周跌>5%
A123: 已预警的大跌中，平均提前周数 | B123: 6.8 | C123: 5.7
A124: 样本数（已预警的大跌次数） | B124: 69 | C124: 22
A126: ✅ 领先预警评价：
A127: • 前瞻波动率：升入高风险后3-4周波动率达基准的1.13倍，超半数事件波动超越基准（51.1%），信号具有前瞻性。
A128: • 大跌预警：83次周跌>3%中，80.7%提前1周已处于困难模式及以上，平均提前6.8周发出预警。模型是“领先指标”，而非事后确认。
...

Sheet 信号可视化
S2: 📊 SP500 × 操作难度信号
S3: “彩色色带 = 模型判定的风险等级。看色带和SP500走势的配合度：红色区间是否对应跌市，绿色区间是否对应涨市。”
S5: • 绿/蓝色带：简单/普通模式，市场平稳，可满仓操作
S6: • 黄/橙色带：困难/噩梦模式，波动加剧，应减仓
S7: • 红/暗红色带：地狱/炼狱模式，危机环境，仅保留底仓
S39: 📊 市场风险总览
S40: “蓝线和红线重叠 = 正常；红线飙升 = 否决权触发。”
S42: • 蓝线（纯评分）：5个特征的加权平均，反映市场“底噪”水平
S43: • 红线（否决权评分）：任一特征z>2时被拉高至该特征值，类似“紧急拉闸”
S44: • 粉色面积（回撤）：红线尖峰与回撤深度是否同步，是检验模型的核心视角
S46: 关注点：2008、2020、2025三次危机中红线是否领先于粉色回撤出现？
S67: 📊 纯综合评分
... S117: 理想情况：评分飙升→减仓→回撤来临时已轻仓。这是模型的核心价值。

Sheet 回测_周度
A1: 日期 | B1: 标普500 | C1: 标普周收益率 | D1: 滞后仓位 | E1: 策略收益 | F1: 策略NAV | G1: 买入持有NAV | H1: 策略滚动最高 | I1: 策略回撤 | J1: 持有滚动最高 | K1: 持有回撤
A2: =原始数据_周度!A2 | B2: =原始数据_周度!B2 | C2: ="" | D2: ="" | E2: =IF(OR(D2="",C2=""),"",D2*C2) | F2: ="" | G2: ="" | H2: =IF(F2="","",F2) | I2: =IF(OR(F2="",H2=""),"",F2/H2-1) | J2: =IF(G2="","",G2) | K2: =IF(OR(G2="",J2=""),"",G2/J2-1)
A3: =原始数据_周度!A3 | B3: =原始数据_周度!B3 | C3: =IFERROR(B3/B2-1,"") | D3: =IFERROR(评分与状态_周度!F19,"") | E3: =IF(OR(D3="",C3=""),"",D3*C3) | F3: =IF(E3="","",IF(F2="",1,F2*(1+E3))) | G3: =IF(E3="","",IF(G2="",1,G2*(1+C3))) | H3: =IF(F3="","",IF(H2="",F3,MAX(H2,F3))) | I3: =IF(OR(F3="",H3=""),"",F3/H3-1) | J3: =IF(G3="","",G3) | K3: =IF(OR(G3="",J3=""),"",G3/J3-1)
A4: =原始数据_周度!A4 | B4: =原始数据_周度!B4 | C4: =IFERROR(B4/B3-1,"") | D4: =IFERROR(评分与状态_周度!F20,"") | E4: =IF(OR(D4="",C4=""),"",D4*C4) | F4: =IF(E4="","",IF(F3="",1,F3*(1+E4))) | G4: =IF(E4="","",IF(G3="",1,G3*(1+C4))) | H4: =IF(F4="","",IF(H3="",F4,MAX(H3,F4))) | I4: =IF(OR(F4="",H4=""),"",F4/H4-1) | J4: =IF(G4="","",IF(J3="",G4,MAX(J3,G4))) | K4: =IF(OR(G4="",J4=""),"",G4/J4-1)
A5: =原始数据_周度!A5 | B5: =原始数据_周度!B5 | C5: =IFERROR(B5/B4-1,"") | D5: =IFERROR(评分与状态_周度!F21,"") | E5: =IF(OR(D5="",C5=""),"",D5*C5) | F5: =IF(E5="","",IF(F4="",1,F4*(1+E5))) | G5: =IF(E5="","",IF(G4="",1,G4*(1+C5))) | H5: =IF(F5="","",IF(H4="",F5,MAX(H4,F5))) | I5: =IF(OR(F5="",H5=""),"",F5/H5-1)
A6: =原始数据_周度!A6 | B6: =原始数据_周度!B6 | C6: =IFERROR(B6/B5-1,"") | D6: =IFERROR(评分与状态_周度!F22,"") | E6: =IF(OR(D6="",C6=""),"",D6*C6) | F6: =IF(E6="","",IF(F5="",1,F5*(1+E6))) | G6: =IF(E6="","",IF(G5="",1,G5*(1+C6))) | H6: =IF(F6="","",IF(H5="",F6,MAX(H5,F6))) | I6: =IF(OR(F6="",H6=""),"",F6/H6-1)
A7: =原始数据_周度!A7 | B7: =原始数据_周度!B7 | C7: =IFERROR(B7/B6-1,"") | D7: =IFERROR(评分与状态_周度!F23,"") | E7: =IF(OR(D7="",C7=""),"",D7*C7) | F7: =IF(E7="","",IF(F6="",1,F6*(1+E7))) | G7: =IF(E7="","",IF(G6="",1,G6*(1+C7))) | H7: =IF(F7="","",IF(H6="",F7,MAX(H6,F7))) | I7: =IF(OR(F7="",H7=""),"",F7/H7-1)
A8: =原始数据_周度!A8 | B8: =原始数据_周度!B8 | C8: =IFERROR(B8/B7-1,"") | D8: =IFERROR(评分与状态_周度!F24,"") | E8: =IF(OR(D8="",C8=""),"",D8*C8) | F8: =IF(E8="","",IF(F7="",1,F7*(1+E8))) | G8: =IF(E8="","",IF(G7="",1,G7*(1+C8))) | H8: =IF(F8="","",IF(H7="",F8,MAX(H7,F8))) | I8: =IF(OR(F8="",H8=""),"",F8/H8-1)
A9: =原始数据_周度!A9 | B9: =原始数据_周度!B9 | C9: =IFERROR(B9/B8-1,"") | D9: =IFERROR(评分与状态_周度!F25,"") | E9: =IF(OR(D9="",C9=""),"",D9*C9) | F9: =IF(E9="","",IF(F8="",1,F8*(1+E9))) | G9: =IF(E9="","",IF(G8="",1,G8*(1+C9))) | H9: =IF(F9="","",IF(H8="",F9,MAX(H8,F9))) | I9: =IF(OR(F9="",H9=""),"",F9/H9-1)
A10: =原始数据_周度!A10 | B10: =原始数据_周度!B10 | C10: =IFERROR(B10/B9-1,"") | D10: =IFERROR(评分与状态_周度!F26,"") | E10: =IF(OR(D10="",C10=""),"",D10*C10) | F10: =IF(E10="","",IF(F9="",1,F9*(1+E10))) | G10: =IF(E10="","",IF(G9="",1,G9*(1+C10))) | H10: =IF(F10="","",IF(H9="",F10,MAX(H9,F10))) | I10: =IF(OR(F10="",H10=""),"",F10/H10-1)
A11: =原始数据_周度!A11 | B11: =原始数据_周度!B11 | C11: =IFERROR(B11/B10-1,"") | D11: =IFERROR(评分与状态_周度!F27,"") | E11: =IF(OR(D11="",C11=""),"",D11*C11) | F11: =IF(E11="","",IF(F10="",1,F10*(1+E11))) | G11: =IF(E11="","",IF(G10="",1,G10*(1+C11))) | H11: =IF(F11="","",IF(H10="",F11,MAX(H10,F11))) | I11: =IF(OR(F11="",H11=""),"",F11/H11-1)
A12: =原始数据_周度!A12 | B12: =原始数据_周度!B12 | C12: =IFERROR(B12/B11-1,"") | D12: =IFERROR(评分与状态_周度!F28,"") | E12: =IF(OR(D12="",C12=""),"",D12*C12) | F12: =IF(E12="","",IF(F11="",1,F11*(1+E12))) | G12: =IF(E12="","",IF(G11="",1,G11*(1+C12))) | H12: =IF(F12="","",IF(H11="",F12,MAX(H11,F12))) | I12: =IF(OR(F12="",H12=""),"",F12/H12-1)
A13: =原始数据_周度!A13 | B13: =原始数据_周度!B13 | C13: =IFERROR(B13/B12-1,"") | D13: =IFERROR(评分与状态_周度!F29,"") | E13: =IF(OR(D13="",C13=""),"",D13*C13) | F13: =IF(E13="","",IF(F12="",1,F12*(1+E13))) | G13: =IF(E13="","",IF(G12="",1,G12*(1+C13))) | H13: =IF(F13="","",IF(H12="",F13,MAX(H12,F13))) | I13: =IF(OR(F13="",H13=""),"",F13/H13-1)
A14: =原始数据_周度!A14 | B14: =原始数据_周度!B14 | C14: =IFERROR(B14/B13-1,"") | D14: =IFERROR(评分与状态_周度!F30,"") | E14: =IF(OR(D14="",C14=""),"",D14*C14) | F14: =IF(E14="","",IF(F13="",1,F13*(1+E14))) | G14: =IF(E14="","",IF(G13="",1,G13*(1+C14))) | H14: =IF(F14="","",IF(H13="",F14,MAX(H13,F14))) | I14: =IF(OR(F14="",H14=""),"",F14/H14-1)
A15: =原始数据_周度!A15 | B15: =原始数据_周度!B15 | C15: =IFERROR(B15/B14-1,"") | D15: =IFERROR(评分与状态_周度!F31,"") | E15: =IF(OR(D15="",C15=""),"",D15*C15) | F15: =IF(E15="","",IF(F14="",1,F14*(1+E15))) | G15: =IF(E15="","",IF(G14="",1,G14*(1+C15))) | H15: =IF(F15="","",IF(H14="",F15,MAX(H14,F15))) | I15: =IF(OR(F15="",H15=""),"",F15/H15-1)
A16: =原始数据_周度!A16 | B16: =原始数据_周度!B16 | C16: =IFERROR(B16/B15-1,"") | D16: =IFERROR(评分与状态_周度!F32,"") | E16: =IF(OR(D16="",C16=""),"",D16*C16) | F16: =IF(E16="","",IF(F15="",1,F15*(1+E16))) | G16: =IF(E16="","",IF(G15="",1,G15*(1+C16))) | H16: =IF(F16="","",IF(H15="",F16,MAX(H15,F16))) | I16: =IF(OR(F16="",H16=""),"",F16/H16-1)
... A419: =原始数据_周度!A419 | B419: =原始数据_周度!B419 | C419: =IFERROR(B419/B418-1,"") | D419: =IFERROR(评分与状态_周度!F435,"") | E419: =IF(OR(D419="",C419=""),"",D419*C419) | F419: =IF(E419="","",IF(F418="",1,F418*(1+E419))) | G419: =IF(E419="","",IF(G418="",1,G418*(1+C419))) | H419: =IF(F419="","",IF(H418="",F419,MAX(H418,F419))) | I419: =IF(OR(F419="",H419=""),"",F419/H419-1)
A420: =原始数据_周度!A420 | B420: =原始数据_周度!B420 | C420: =IFERROR(B420/B419-1,"") | D420: =IFERROR(评分与状态_周度!F436,"") | E420: =IF(OR(D420="",C420=""),"",D420*C420) | F420: =IF(E420="","",IF(F419="",1,F419*(1+E420))) | G420: =IF(E420="","",IF(G419="",1,G419*(1+C420))) | H420: =IF(F420="","",IF(H419="",F420,MAX(H419,F420))) | I420: =IF(OR(F420="",H420=""),"",F420/H420-1) | J420: =IF(G420="","",IF(J419="",G420,MAX(J419,G420))) | K420: =IF(OR(G420="",J420=""),"",G420/J420-1)
A421: =原始数据_周度!A421 | B421: =原始数据_周度!B421 | C421: =IFERROR(B421/B420-1,"") | D421: =IFERROR(评分与状态_周度!F437,"") | E421: =IF(OR(D421="",C421=""),"",D421*C421) | F421: =IF(E421="","",IF(F420="",1,F420*(1+E421))) | G421: =IF(E421="","",IF(G420="",1,G420*(1+C421))) | H421: =IF(F421="","",IF(H420="",F421,MAX(H420,F421))) | I421: =IF(OR(F421="",H421=""),"",F421/H421-1) | J421: =IF(G421="","",IF(J420="",G421,MAX(J420,G421))) | K421: =IF(OR(G421="",J421=""),"",G421/J421-1)
A422: =原始数据_周度!A422 | B422: =原始数据_周度!B422 | C422: =IFERROR(B422/B421-1,"") | D422: =IFERROR(评分与状态_周度!F438,"") | E422: =IF(OR(D422="",C422=""),"",D422*C422) | F422: =IF(E422="","",IF(F421="",1,F421*(1+E422))) | G422: =IF(E422="","",IF(G421="",1,G421*(1+C422))) | H422: =IF(F422="","",IF(H421="",F422,MAX(H421,F422))) | I422: =IF(OR(F422="",H422=""),"",F422/H422-1) | J422: =IF(G422="","",IF(J421="",G422,MAX(J421,G422))) | K422: =IF(OR(G422="",J422=""),"",G422/J422-1)
A423: =原始数据_周度!A423 | B423: =原始数据_周度!B423 | C423: =IFERROR(B423/B422-1,"") | D423: =IFERROR(评分与状态_周度!F439,"") | E423: =IF(OR(D423="",C423=""),"",D423*C423) | F423: =IF(E423="","",IF(F422="",1,F422*(1+E423))) | G423: =IF(E423="","",IF(G422="",1,G422*(1+C423))) | H423: =IF(F423="","",IF(H422="",F423,MAX(H422,F423))) | I423: =IF(OR(F423="",H423=""),"",F423/H423-1) | J423: =IF(G423="","",IF(J422="",G423,MAX(J422,G423))) | K423: =IF(OR(G423="",J423=""),"",G423/J423-1)
A424: =原始数据_周度!A424 | B424: =原始数据_周度!B424 | C424: =IFERROR(B424/B423-1,"") | D424: =IFERROR(评分与状态_周度!F440,"") | E424: =IF(OR(D424="",C424=""),"",D424*C424) | F424: =IF(E424="","",IF(F423="",1,F423*(1+E424))) | G424: =IF(E424="","",IF(G423="",1,G423*(1+C424))) | H424: =IF(F424="","",IF(H423="",F424,MAX(H423,F424))) | I424: =IF(OR(F424="",H424=""),"",F424/H424-1) | J424: =IF(G424="","",IF(J423="",G424,MAX(J423,G424))) | K424: =IF(OR(G424="",J424=""),"",G424/J424-1)
A425: =原始数据_周度!A425 | B425: =原始数据_周度!B425 | C425: =IFERROR(B425/B424-1,"") | D425: =IFERROR(评分与状态_周度!F441,"") | E425: =IF(OR(D425="",C425=""),"",D425*C425) | F425: =IF(E425="","",IF(F424="",1,F424*(1+E425))) | G425: =IF(E425="","",IF(G424="",1,G424*(1+C425))) | H425: =IF(F425="","",IF(H424="",F425,MAX(H424,F425))) | I425: =IF(OR(F425="",H425=""),"",F425/H425-1) | J425: =IF(G425="","",IF(J424="",G425,MAX(J424,G425))) | K425: =IF(OR(G425="",J425=""),"",G425/J425-1)
A426: =原始数据_周度!A426 | B426: =原始数据_周度!B426 | C426: =IFERROR(B426/B425-1,"") | D426: =IFERROR(评分与状态_周度!F442,"") | E426: =IF(OR(D426="",C426=""),"",D426*C426) | F426: =IF(E426="","",IF(F425="",1,F425*(1+E426))) | G426: =IF(E426="","",IF(G425="",1,G425*(1+C426))) | H426: =IF(F426="","",IF(H425="",F426,MAX(H425,F426))) | I426: =IF(OR(F426="",H426=""),"",F426/H426-1) | J426: =IF(G426="","",IF(J425="",G426,MAX(J425,G426))) | K426: =IF(OR(G426="",J426=""),"",G426/J426-1)
A427: =原始数据_周度!A427 | B427: =原始数据_周度!B427 | C427: =IFERROR(B427/B426-1,"") | D427: =IFERROR(评分与状态_周度!F443,"") | E427: =IF(OR(D427="",C427=""),"",D427*C427) | F427: =IF(E427="","",IF(F426="",1,F426*(1+E427))) | G427: =IF(E427="","",IF(G426="",1,G426*(1+C427))) | H427: =IF(F427="","",IF(H426="",F427,MAX(H426,F427))) | I427: =IF(OR(F427="",H427=""),"",F427/H427-1) | J427: =IF(G427="","",IF(J426="",G427,MAX(J426,G427))) | K427: =IF(OR(G427="",J427=""),"",G427/J427-1)
A428: =原始数据_周度!A428 | B428: =原始数据_周度!B428 | C428: =IFERROR(B428/B427-1,"") | D428: =IFERROR(评分与状态_周度!F444,"") | E428: =IF(OR(D428="",C428=""),"",D428*C428) | F428: =IF(E428="","",IF(F427="",1,F427*(1+E428))) | G428: =IF(E428="","",IF(G427="",1,G427*(1+C428))) | H428: =IF(F428="","",IF(H427="",F428,MAX(H427,F428))) | I428: =IF(OR(F428="",H428=""),"",F428/H428-1) | J428: =IF(G428="","",IF(J427="",G428,MAX(J427,G428))) | K428: =IF(OR(G428="",J428=""),"",G428/J428-1)
A429: =原始数据_周度!A429 | B429: =原始数据_周度!B429 | C429: =IFERROR(B429/B428-1,"") | D429: =IFERROR(评分与状态_周度!F445,"") | E429: =IF(OR(D429="",C429=""),"",D429*C429) | F429: =IF(E429="","",IF(F428="",1,F428*(1+E429))) | G429: =IF(E429="","",IF(G428="",1,G428*(1+C429))) | H429: =IF(F429="","",IF(H428="",F429,MAX(H428,F429))) | I429: =IF(OR(F429="",H429=""),"",F429/H429-1) | J429: =IF(G429="","",IF(J428="",G429,MAX(J428,G429))) | K429: =IF(OR(G429="",J429=""),"",G429/J429-1)
A430: =原始数据_周度!A430 | B430: =原始数据_周度!B430 | C430: =IFERROR(B430/B429-1,"") | D430: =IFERROR(评分与状态_周度!F446,"") | E430: =IF(OR(D430="",C430=""),"",D430*C430) | F430: =IF(E430="","",IF(F429="",1,F429*(1+E430))) | G430: =IF(E430="","",IF(G429="",1,G429*(1+C430))) | H430: =IF(F430="","",IF(H429="",F430,MAX(H429,F430))) | I430: =IF(OR(F430="",H430=""),"",F430/H430-1) | J430: =IF(G430="","",IF(J429="",G430,MAX(J429,G430))) | K430: =IF(OR(G430="",J430=""),"",G430/J430-1)
A431: =原始数据_周度!A431 | B431: =原始数据_周度!B431 | C431: =IFERROR(B431/B430-1,"") | D431: =IFERROR(评分与状态_周度!F447,"") | E431: =IF(OR(D431="",C431=""),"",D431*C431) | F431: =IF(E431="","",IF(F430="",1,F430*(1+E431))) | G431: =IF(E431="","",IF(G430="",1,G430*(1+C431))) | H431: =IF(F431="","",IF(H430="",F431,MAX(H430,F431))) | I431: =IF(OR(F431="",H431=""),"",F431/H431-1) | J431: =IF(G431="","",IF(J430="",G431,MAX(J430,G431))) | K431: =IF(OR(G431="",J431=""),"",G431/J431-1)
... A1529: =原始数据_周度!A1529 | B1529: =原始数据_周度!B1529 | C1529: =IFERROR(B1529/B1528-1,"") | D1529: =IFERROR(评分与状态_周度!F1545,"") | E1529: =IF(OR(D1529="",C1529=""),"",D1529*C1529) | F1529: =IF(E1529="","",IF(F1528="",1,F1528*(1+E1529))) | G1529: =IF(E1529="","",IF(G1528="",1,G1528*(1+C1529))) | H1529: =IF(F1529="","",IF(H1528="",F1529,MAX(H1528,F1529))) | I1529: =IF(OR(F1529="",H1529=""),"",F1529/H1529-1) | J1529: =IF(G1529="","",IF(J1528="",G1529,MAX(J1528,G1529))) | K1529: =IF(OR(G1529="",J1529=""),"",G1529/J1529-1)

Sheet 评分与状态_周度
A1: 特征权重（可编辑）
A2: VIX_z分数 | B2: 高收益变化_z分数 | C2: 期限利差反转_z | D2: 标普趋势反转_z | E2: 均线斜率反转_z | F2: 盈利上修_z分数 | I2: 仓位缓冲参数
A3: 0.24 | B3: 0.24 | C3: 0.14 | D3: 0.14 | E3: 0.19 | F3: =SUM(A3:E3)+F3 | I3: 1
I4: 0.15
A5: 状态阈值与目标仓位（可编辑） | I5: 0.05
A6: 操作难度 | B6: 下限百分位 | C6: 上限百分位
A7: 🟢 简单模式 | B7: 0 | C7: 0.2
A8: 🟢 普通模式 | B8: 0.2 | C8: 0.4
A9: 🟡 困难模式 | B9: 0.4 | C9: 0.55
A10: 🟠 噩梦模式 | B10: 0.55 | C10: 0.7
A11: 🔴 地狱模式 | B11: 0.7 | C11: 0.85
A12: 💀 炼狱模式 | B12: 0.85 | C12: 1
A14: 否决权规则（可编辑）
A15: 单特征z-score否决阈值 | B15: 2 | C15: 任一特征z-score超过此值 → 直接判定为高风险，无视综合评分
A16: 超跌拐头减免（可编辑）
A17: 超跌阈值(偏离度) | B17: -0.1 | C17: 回看窗口(周) | D17: 8 | E17: 反弹确认(%)
A18: 日期 | B18: 综合评分 | C18: P20(滚动364周) | D18: P85(滚动364周) | E18: 风险状态 | G18: 否决权 | H18: 超跌拐头 | I18: 盈利上修仓位缓冲
A19: =特征计算_周度!A2 | B19: =IFERROR($A$3*特征计算_周度!B19+$B$3*特征计算_周度!C19+$C$3*特征计算_周度!D19+$D$3*特征计算_周度!E19+$E$3*特征计算_周度!F19+$F$3*特征计算_周度!H19,"") | C19: =IFERROR(PERCENTILE(OFFSET(B19,1-364,0,364,1),$C$7),"") | D19: =IFERROR(PERCENTILE(OFFSET(B19,1-364,0,364,1),$C$11),"") | E19: =_xlfn.LET(_xlpm.initState,IF(OR(B19="",C19=""),"",IF(OR(特征计算_周度!B2>$B$15,特征计算_周度!C2>$B$15,特征计算_周度!G2>$B$15,特征计算_周度!E2>$B$15,特征计算_周度!F2>$B$15),$A$12,IFERROR(IF(B19<PERCENTILE(OFFSET(B19,1-364,0,364,1),$C$7),$A$7,IF(B19<PERCENTILE(OFFSET(B19,1-364,0,364,1),$C$8),$A$8,IF(B19<PERCENTILE(OFFSET(B19,1-364,0,364,1),$C$9),$A$9,IF(B19<PERCENTILE(OFFSET(B19,1-364,0,364,1),$C$10),$A$10,IF(B19<PERCENTILE(OFFSET(B19,1-364,0,364,1),$C$11),$A$11,$A$12))))),""))),_xlpm.dev,原始数据_周度!G2,_xlpm.minDev,MIN(OFFSET(原始数据_周度!G2,1-$D$17,0,$D$17,1)),_xlpm.bounce,_xlpm.dev-_xlpm.minDev,_xlpm.oversold,AND(ISNUMBER(_xlpm.dev),ISNUMBER(_xlpm.minDev),_xlpm.minDev<=$B$17,_xlpm.bounce>=$F$17,OR(_xlpm.initState=$A$12,_xlpm.initState=$A$11,_xlpm.initState=$A$10)),_xlpm.pctOnly,IFERROR(IF(B19<PERCENTILE(OFFSET(B19,1-364,0,364,1),$C$7),$A$7,IF(B19<PERCENTILE(OFFSET(B19,1-364,0,364,1),$C$8),$A$8,IF(B19<PERCENTILE(OFFSET(B19,1-364,0,364,1),$C$9),$A$9,IF(B19<PERCENTILE(OFFSET(B19,1-364,0,364,1),$C$10),$A$10,IF(B19<PERCENTILE(OFFSET(B19,1-364,0,364,1),$C$11),$A$11,$A$12))))),""),IF(_xlpm.initState="","",IF(_xlpm.oversold,_xlpm.pctOnly,_xlpm.initState))) | G19: =IF(OR(B19="",C19=""),"",IF(OR(特征计算_周度!B2>$B$15,特征计算_周度!C2>$B$15,特征计算_周度!G2>$B$15,特征计算_周度!E2>$B$15,特征计算_周度!F2>$B$15),IF(特征计算_周度!B2>$B$15,"VIX ","")&IF(特征计算_周度!C2>$B$15,"HY ","")&IF(特征计算_周度!G2>$B$15,"Sahm ","")&IF(特征计算_周度!E2>$B$15,"趋势 ","")&IF(特征计算_周度!F2>$B$15,"斜率",""),"—")) | H19: =IF(OR(B19="",C19=""),"",_xlfn.LET(_xlpm.dev,原始数据_周度!G2,_xlpm.minDev,MIN(OFFSET(原始数据_周度!G2,1-$D$17,0,$D$17,1)),_xlpm.bounce,_xlpm.dev-_xlpm.minDev,IF(AND(ISNUMBER(_xlpm.dev),ISNUMBER(_xlpm.minDev),_xlpm.minDev<=$B$17,_xlpm.bounce>=$F$17),"✅ 触发","—"))) | I19: =IFERROR(IF(特征计算_周度!H19>$I$3,MIN($I$4,MAX(-$I$5,(特征计算_周度!H19-$I$3)*$I$4)),0),"")
A20: =特征计算_周度!A3 | B20: =IFERROR($A$3*特征计算_周度!B20+$B$3*特征计算_周度!C20+$C$3*特征计算_周度!D20+$D$3*特征计算_周度!E20+$E$3*特征计算_周度!F20+$F$3*特征计算_周度!H20,"") | C20: =IFERROR(PERCENTILE(OFFSET(B20,1-364,0,364,1),$C$7),"") | D20: =IFERROR(PERCENTILE(OFFSET(B20,1-364,0,364,1),$C$11),"") | E20: =_xlfn.LET(_xlpm.initState,IF(OR(B20="",C20=""),"",IF(OR(特征计算_周度!B3>$B$15,特征计算_周度!C3>$B$15,特征计算_周度!G3>$B$15,特征计算_周度!E3>$B$15,特征计算_周度!F3>$B$15),$A$12,IFERROR(IF(B20<PERCENTILE(OFFSET(B20,1-364,0,364,1),$C$7),$A$7,IF(B20<PERCENTILE(OFFSET(B20,1-364,0,364,1),$C$8),$A$8,IF(B20<PERCENTILE(OFFSET(B20,1-364,0,364,1),$C$9),$A$9,IF(B20<PERCENTILE(OFFSET(B20,1-364,0,364,1),$C$10),$A$10,IF(B20<PERCENTILE(OFFSET(B20,1-364,0,364,1),$C$11),$A$11,$A$12))))),""))),_xlpm.dev,原始数据_周度!G3,_xlpm.minDev,MIN(OFFSET(原始数据_周度!G3,1-$D$17,0,$D$17,1)),_xlpm.bounce,_xlpm.dev-_xlpm.minDev,_xlpm.oversold,AND(ISNUMBER(_xlpm.dev),ISNUMBER(_xlpm.minDev),_xlpm.minDev<=$B$17,_xlpm.bounce>=$F$17,OR(_xlpm.initState=$A$12,_xlpm.initState=$A$11,_xlpm.initState=$A$10)),_xlpm.pctOnly,IFERROR(IF(B20<PERCENTILE(OFFSET(B20,1-364,0,364,1),$C$7),$A$7,IF(B20<PERCENTILE(OFFSET(B20,1-364,0,364,1),$C$8),$A$8,IF(B20<PERCENTILE(OFFSET(B20,1-364,0,364,1),$C$9),$A$9,IF(B20<PERCENTILE(OFFSET(B20,1-364,0,364,1),$C$10),$A$10,IF(B20<PERCENTILE(OFFSET(B20,1-364,0,364,1),$C$11),$A$11,$A$12))))),""),IF(_xlpm.initState="","",IF(_xlpm.oversold,_xlpm.pctOnly,_xlpm.initState))) | G20: =IF(OR(B20="",C20=""),"",IF(OR(特征计算_周度!B3>$B$15,特征计算_周度!C3>$B$15,特征计算_周度!G3>$B$15,特征计算_周度!E3>$B$15,特征计算_周度!F3>$B$15),IF(特征计算_周度!B3>$B$15,"VIX ","")&IF(特征计算_周度!C3>$B$15,"HY ","")&IF(特征计算_周度!G3>$B$15,"Sahm ","")&IF(特征计算_周度!E3>$B$15,"趋势 ","")&IF(特征计算_周度!F3>$B$15,"斜率",""),"—")) | H20: =IF(OR(B20="",C20=""),"",_xlfn.LET(_xlpm.dev,原始数据_周度!G3,_xlpm.minDev,MIN(OFFSET(原始数据_周度!G3,1-$D$17,0,$D$17,1)),_xlpm.bounce,_xlpm.dev-_xlpm.minDev,IF(AND(ISNUMBER(_xlpm.dev),ISNUMBER(_xlpm.minDev),_xlpm.minDev<=$B$17,_xlpm.bounce>=$F$17),"✅ 触发","—"))) | I20: =IFERROR(IF(特征计算_周度!H20>$I$3,MIN($I$4,MAX(-$I$5,(特征计算_周度!H20-$I$3)*$I$4)),0),"")
A21: =特征计算_周度!A4 | B21: =IFERROR($A$3*特征计算_周度!B21+$B$3*特征计算_周度!C21+$C$3*特征计算_周度!D21+$D$3*特征计算_周度!E21+$E$3*特征计算_周度!F21+$F$3*特征计算_周度!H21,"") | C21: =IFERROR(PERCENTILE(OFFSET(B21,1-364,0,364,1),$C$7),"") | D21: =IFERROR(PERCENTILE(OFFSET(B21,1-364,0,364,1),$C$11),"") | E21: =_xlfn.LET(_xlpm.initState,IF(OR(B21="",C21=""),"",IF(OR(特征计算_周度!B4>$B$15,特征计算_周度!C4>$B$15,特征计算_周度!G4>$B$15,特征计算_周度!E4>$B$15,特征计算_周度!F4>$B$15),$A$12,IFERROR(IF(B21<PERCENTILE(OFFSET(B21,1-364,0,364,1),$C$7),$A$7,IF(B21<PERCENTILE(OFFSET(B21,1-364,0,364,1),$C$8),$A$8,IF(B21<PERCENTILE(OFFSET(B21,1-364,0,364,1),$C$9),$A$9,IF(B21<PERCENTILE(OFFSET(B21,1-364,0,364,1),$C$10),$A$10,IF(B21<PERCENTILE(OFFSET(B21,1-364,0,364,1),$C$11),$A$11,$A$12))))),""))),_xlpm.dev,原始数据_周度!G4,_xlpm.minDev,MIN(OFFSET(原始数据_周度!G4,1-$D$17,0,$D$17,1)),_xlpm.bounce,_xlpm.dev-_xlpm.minDev,_xlpm.oversold,AND(ISNUMBER(_xlpm.dev),ISNUMBER(_xlpm.minDev),_xlpm.minDev<=$B$17,_xlpm.bounce>=$F$17,OR(_xlpm.initState=$A$12,_xlpm.initState=$A$11,_xlpm.initState=$A$10)),_xlpm.pctOnly,IFERROR(IF(B21<PERCENTILE(OFFSET(B21,1-364,0,364,1),$C$7),$A$7,IF(B21<PERCENTILE(OFFSET(B21,1-364,0,364,1),$C$8),$A$8,IF(B21<PERCENTILE(OFFSET(B21,1-364,0,364,1),$C$9),$A$9,IF(B21<PERCENTILE(OFFSET(B21,1-364,0,364,1),$C$10),$A$10,IF(B21<PERCENTILE(OFFSET(B21,1-364,0,364,1),$C$11),$A$11,$A$12))))),""),IF(_xlpm.initState="","",IF(_xlpm.oversold,_xlpm.pctOnly,_xlpm.initState))) | G21: =IF(OR(B21="",C21=""),"",IF(OR(特征计算_周度!B4>$B$15,特征计算_周度!C4>$B$15,特征计算_周度!G4>$B$15,特征计算_周度!E4>$B$15,特征计算_周度!F4>$B$15),IF(特征计算_周度!B4>$B$15,"VIX ","")&IF(特征计算_周度!C4>$B$15,"HY ","")&IF(特征计算_周度!G4>$B$15,"Sahm ","")&IF(特征计算_周度!E4>$B$15,"趋势 ","")&IF(特征计算_周度!F4>$B$15,"斜率",""),"—")) | H21: =IF(OR(B21="",C21=""),"",_xlfn.LET(_xlpm.dev,原始数据_周度!G4,_xlpm.minDev,MIN(OFFSET(原始数据_周度!G4,1-$D$17,0,$D$17,1)),_xlpm.bounce,_xlpm.dev-_xlpm.minDev,IF(AND(ISNUMBER(_xlpm.dev),ISNUMBER(_xlpm.minDev),_xlpm.minDev<=$B$17,_xlpm.bounce>=$F$17),"✅ 触发","—"))) | I21: =IFERROR(IF(特征计算_周度!H21>$I$3,MIN($I$4,MAX(-$I$5,(特征计算_周度!H21-$I$3)*$I$4)),0),"")
A22: =特征计算_周度!A5 | B22: =IFERROR($A$3*特征计算_周度!B22+$B$3*特征计算_周度!C22+$C$3*特征计算_周度!D22+$D$3*特征计算_周度!E22+$E$3*特征计算_周度!F22+$F$3*特征计算_周度!H22,"") | C22: =IFERROR(PERCENTILE(OFFSET(B22,1-364,0,364,1),$C$7),"") | D22: =IFERROR(PERCENTILE(OFFSET(B22,1-364,0,364,1),$C$11),"") | E22: =_xlfn.LET(_xlpm.initState,IF(OR(B22="",C22=""),"",IF(OR(特征计算_周度!B5>$B$15,特征计算_周度!C5>$B$15,特征计算_周度!G5>$B$15,特征计算_周度!E5>$B$15,特征计算_周度!F5>$B$15),$A$12,IFERROR(IF(B22<PERCENTILE(OFFSET(B22,1-364,0,364,1),$C$7),$A$7,IF(B22<PERCENTILE(OFFSET(B22,1-364,0,364,1),$C$8),$A$8,IF(B22<PERCENTILE(OFFSET(B22,1-364,0,364,1),$C$9),$A$9,IF(B22<PERCENTILE(OFFSET(B22,1-364,0,364,1),$C$10),$A$10,IF(B22<PERCENTILE(OFFSET(B22,1-364,0,364,1),$C$11),$A$11,$A$12))))),""))),_xlpm.dev,原始数据_周度!G5,_xlpm.minDev,MIN(OFFSET(原始数据_周度!G5,1-$D$17,0,$D$17,1)),_xlpm.bounce,_xlpm.dev-_xlpm.minDev,_xlpm.oversold,AND(ISNUMBER(_xlpm.dev),ISNUMBER(_xlpm.minDev),_xlpm.minDev<=$B$17,_xlpm.bounce>=$F$17,OR(_xlpm.initState=$A$12,_xlpm.initState=$A$11,_xlpm.initState=$A$10)),_xlpm.pctOnly,IFERROR(IF(B22<PERCENTILE(OFFSET(B22,1-364,0,364,1),$C$7),$A$7,IF(B22<PERCENTILE(OFFSET(B22,1-364,0,364,1),$C$8),$A$8,IF(B22<PERCENTILE(OFFSET(B22,1-364,0,364,1),$C$9),$A$9,IF(B22<PERCENTILE(OFFSET(B22,1-364,0,364,1),$C$10),$A$10,IF(B22<PERCENTILE(OFFSET(B22,1-364,0,364,1),$C$11),$A$11,$A$12))))),""),IF(_xlpm.initState="","",IF(_xlpm.oversold,_xlpm.pctOnly,_xlpm.initState))) | G22: =IF(OR(B22="",C22=""),"",IF(OR(特征计算_周度!B5>$B$15,特征计算_周度!C5>$B$15,特征计算_周度!G5>$B$15,特征计算_周度!E5>$B$15,特征计算_周度!F5>$B$15),IF(特征计算_周度!B5>$B$15,"VIX ","")&IF(特征计算_周度!C5>$B$15,"HY ","")&IF(特征计算_周度!G5>$B$15,"Sahm ","")&IF(特征计算_周度!E5>$B$15,"趋势 ","")&IF(特征计算_周度!F5>$B$15,"斜率",""),"—")) | H22: =IF(OR(B22="",C22=""),"",_xlfn.LET(_xlpm.dev,原始数据_周度!G5,_xlpm.minDev,MIN(OFFSET(原始数据_周度!G5,1-$D$17,0,$D$17,1)),_xlpm.bounce,_xlpm.dev-_xlpm.minDev,IF(AND(ISNUMBER(_xlpm.dev),ISNUMBER(_xlpm.minDev),_xlpm.minDev<=$B$17,_xlpm.bounce>=$F$17),"✅ 触发","—"))) | I22: =IFERROR(IF(特征计算_周度!H22>$I$3,MIN($I$4,MAX(-$I$5,(特征计算_周度!H22-$I$3)*$I$4)),0),"")
A23: =特征计算_周度!A6 | B23: =IFERROR($A$3*特征计算_周度!B23+$B$3*特征计算_周度!C23+$C$3*特征计算_周度!D23+$D$3*特征计算_周度!E23+$E$3*特征计算_周度!F23+$F$3*特征计算_周度!H23,"") | C23: =IFERROR(PERCENTILE(OFFSET(B23,1-364,0,364,1),$C$7),"") | D23: =IFERROR(PERCENTILE(OFFSET(B23,1-364,0,364,1),$C$11),"") | E23: =_xlfn.LET(_xlpm.initState,IF(OR(B23="",C23=""),"",IF(OR(特征计算_周度!B6>$B$15,特征计算_周度!C6>$B$15,特征计算_周度!G6>$B$15,特征计算_周度!E6>$B$15,特征计算_周度!F6>$B$15),$A$12,IFERROR(IF(B23<PERCENTILE(OFFSET(B23,1-364,0,364,1),$C$7),$A$7,IF(B23<PERCENTILE(OFFSET(B23,1-364,0,364,1),$C$8),$A$8,IF(B23<PERCENTILE(OFFSET(B23,1-364,0,364,1),$C$9),$A$9,IF(B23<PERCENTILE(OFFSET(B23,1-364,0,364,1),$C$10),$A$10,IF(B23<PERCENTILE(OFFSET(B23,1-364,0,364,1),$C$11),$A$11,$A$12))))),""))),_xlpm.dev,原始数据_周度!G6,_xlpm.minDev,MIN(OFFSET(原始数据_周度!G6,1-$D$17,0,$D$17,1)),_xlpm.bounce,_xlpm.dev-_xlpm.minDev,_xlpm.oversold,AND(ISNUMBER(_xlpm.dev),ISNUMBER(_xlpm.minDev),_xlpm.minDev<=$B$17,_xlpm.bounce>=$F$17,OR(_xlpm.initState=$A$12,_xlpm.initState=$A$11,_xlpm.initState=$A$10)),_xlpm.pctOnly,IFERROR(IF(B23<PERCENTILE(OFFSET(B23,1-364,0,364,1),$C$7),$A$7,IF(B23<PERCENTILE(OFFSET(B23,1-364,0,364,1),$C$8),$A$8,IF(B23<PERCENTILE(OFFSET(B23,1-364,0,364,1),$C$9),$A$9,IF(B23<PERCENTILE(OFFSET(B23,1-364,0,364,1),$C$10),$A$10,IF(B23<PERCENTILE(OFFSET(B23,1-364,0,364,1),$C$11),$A$11,$A$12))))),""),IF(_xlpm.initState="","",IF(_xlpm.oversold,_xlpm.pctOnly,_xlpm.initState))) | G23: =IF(OR(B23="",C23=""),"",IF(OR(特征计算_周度!B6>$B$15,特征计算_周度!C6>$B$15,特征计算_周度!G6>$B$15,特征计算_周度!E6>$B$15,特征计算_周度!F6>$B$15),IF(特征计算_周度!B6>$B$15,"VIX ","")&IF(特征计算_周度!C6>$B$15,"HY ","")&IF(特征计算_周度!G6>$B$15,"Sahm ","")&IF(特征计算_周度!E6>$B$15,"趋势 ","")&IF(特征计算_周度!F6>$B$15,"斜率",""),"—")) | H23: =IF(OR(B23="",C23=""),"",_xlfn.LET(_xlpm.dev,原始数据_周度!G6,_xlpm.minDev,MIN(OFFSET(原始数据_周度!G6,1-$D$17,0,$D$17,1)),_xlpm.bounce,_xlpm.dev-_xlpm.minDev,IF(AND(ISNUMBER(_xlpm.dev),ISNUMBER(_xlpm.minDev),_xlpm.minDev<=$B$17,_xlpm.bounce>=$F$17),"✅ 触发","—"))) | I23: =IFERROR(IF(特征计算_周度!H23>$I$3,MIN($I$4,MAX(-$I$5,(特征计算_周度!H23-$I$3)*$I$4)),0),"")
A24: =特征计算_周度!A7 | B24: =IFERROR($A$3*特征计算_周度!B24+$B$3*特征计算_周度!C24+$C$3*特征计算_周度!D24+$D$3*特征计算_周度!E24+$E$3*特征计算_周度!F24+$F$3*特征计算_周度!H24,"") | C24: =IFERROR(PERCENTILE(OFFSET(B24,1-364,0,364,1),$C$7),"") | D24: =IFERROR(PERCENTILE(OFFSET(B24,1-364,0,364,1),$C$11),"") | E24: =_xlfn.LET(_xlpm.initState,IF(OR(B24="",C24=""),"",IF(OR(特征计算_周度!B7>$B$15,特征计算_周度!C7>$B$15,特征计算_周度!G7>$B$15,特征计算_周度!E7>$B$15,特征计算_周度!F7>$B$15),$A$12,IFERROR(IF(B24<PERCENTILE(OFFSET(B24,1-364,0,364,1),$C$7),$A$7,IF(B24<PERCENTILE(OFFSET(B24,1-364,0,364,1),$C$8),$A$8,IF(B24<PERCENTILE(OFFSET(B24,1-364,0,364,1),$C$9),$A$9,IF(B24<PERCENTILE(OFFSET(B24,1-364,0,364,1),$C$10),$A$10,IF(B24<PERCENTILE(OFFSET(B24,1-364,0,364,1),$C$11),$A$11,$A$12))))),""))),_xlpm.dev,原始数据_周度!G7,_xlpm.minDev,MIN(OFFSET(原始数据_周度!G7,1-$D$17,0,$D$17,1)),_xlpm.bounce,_xlpm.dev-_xlpm.minDev,_xlpm.oversold,AND(ISNUMBER(_xlpm.dev),ISNUMBER(_xlpm.minDev),_xlpm.minDev<=$B$17,_xlpm.bounce>=$F$17,OR(_xlpm.initState=$A$12,_xlpm.initState=$A$11,_xlpm.initState=$A$10)),_xlpm.pctOnly,IFERROR(IF(B24<PERCENTILE(OFFSET(B24,1-364,0,364,1),$C$7),$A$7,IF(B24<PERCENTILE(OFFSET(B24,1-364,0,364,1),$C$8),$A$8,IF(B24<PERCENTILE(OFFSET(B24,1-364,0,364,1),$C$9),$A$9,IF(B24<PERCENTILE(OFFSET(B24,1-364,0,364,1),$C$10),$A$10,IF(B24<PERCENTILE(OFFSET(B24,1-364,0,364,1),$C$11),$A$11,$A$12))))),""),IF(_xlpm.initState="","",IF(_xlpm.oversold,_xlpm.pctOnly,_xlpm.initState))) | G24: =IF(OR(B24="",C24=""),"",IF(OR(特征计算_周度!B7>$B$15,特征计算_周度!C7>$B$15,特征计算_周度!G7>$B$15,特征计算_周度!E7>$B$15,特征计算_周度!F7>$B$15),IF(特征计算_周度!B7>$B$15,"VIX ","")&IF(特征计算_周度!C7>$B$15,"HY ","")&IF(特征计算_周度!G7>$B$15,"Sahm ","")&IF(特征计算_周度!E7>$B$15,"趋势 ","")&IF(特征计算_周度!F7>$B$15,"斜率",""),"—")) | H24: =IF(OR(B24="",C24=""),"",_xlfn.LET(_xlpm.dev,原始数据_周度!G7,_xlpm.minDev,MIN(OFFSET(原始数据_周度!G7,1-$D$17,0,$D$17,1)),_xlpm.bounce,_xlpm.dev-_xlpm.minDev,IF(AND(ISNUMBER(_xlpm.dev),ISNUMBER(_xlpm.minDev),_xlpm.minDev<=$B$17,_xlpm.bounce>=$F$17),"✅ 触发","—"))) | I24: =IFERROR(IF(特征计算_周度!H24>$I$3,MIN($I$4,MAX(-$I$5,(特征计算_周度!H24-$I$3)*$I$4)),0),"")
A25: =特征计算_周度!A8 | B25: =IFERROR($A$3*特征计算_周度!B25+$B$3*特征计算_周度!C25+$C$3*特征计算_周度!D25+$D$3*特征计算_周度!E25+$E$3*特征计算_周度!F25+$F$3*特征计算_周度!H25,"") | C25: =IFERROR(PERCENTILE(OFFSET(B25,1-364,0,364,1),$C$7),"") | D25: =IFERROR(PERCENTILE(OFFSET(B25,1-364,0,364,1),$C$11),"") | E25: =_xlfn.LET(_xlpm.initState,IF(OR(B25="",C25=""),"",IF(OR(特征计算_周度!B8>$B$15,特征计算_周度!C8>$B$15,特征计算_周度!G8>$B$15,特征计算_周度!E8>$B$15,特征计算_周度!F8>$B$15),$A$12,IFERROR(IF(B25<PERCENTILE(OFFSET(B25,1-364,0,364,1),$C$7),$A$7,IF(B25<PERCENTILE(OFFSET(B25,1-364,0,364,1),$C$8),$A$8,IF(B25<PERCENTILE(OFFSET(B25,1-364,0,364,1),$C$9),$A$9,IF(B25<PERCENTILE(OFFSET(B25,1-364,0,364,1),$C$10),$A$10,IF(B25<PERCENTILE(OFFSET(B25,1-364,0,364,1),$C$11),$A$11,$A$12))))),""))),_xlpm.dev,原始数据_周度!G8,_xlpm.minDev,MIN(OFFSET(原始数据_周度!G8,1-$D$17,0,$D$17,1)),_xlpm.bounce,_xlpm.dev-_xlpm.minDev,_xlpm.oversold,AND(ISNUMBER(_xlpm.dev),ISNUMBER(_xlpm.minDev),_xlpm.minDev<=$B$17,_xlpm.bounce>=$F$17,OR(_xlpm.initState=$A$12,_xlpm.initState=$A$11,_xlpm.initState=$A$10)),_xlpm.pctOnly,IFERROR(IF(B25<PERCENTILE(OFFSET(B25,1-364,0,364,1),$C$7),$A$7,IF(B25<PERCENTILE(OFFSET(B25,1-364,0,364,1),$C$8),$A$8,IF(B25<PERCENTILE(OFFSET(B25,1-364,0,364,1),$C$9),$A$9,IF(B25<PERCENTILE(OFFSET(B25,1-364,0,364,1),$C$10),$A$10,IF(B25<PERCENTILE(OFFSET(B25,1-364,0,364,1),$C$11),$A$11,$A$12))))),""),IF(_xlpm.initState="","",IF(_xlpm.oversold,_xlpm.pctOnly,_xlpm.initState))) | G25: =IF(OR(B25="",C25=""),"",IF(OR(特征计算_周度!B8>$B$15,特征计算_周度!C8>$B$15,特征计算_周度!G8>$B$15,特征计算_周度!E8>$B$15,特征计算_周度!F8>$B$15),IF(特征计算_周度!B8>$B$15,"VIX ","")&IF(特征计算_周度!C8>$B$15,"HY ","")&IF(特征计算_周度!G8>$B$15,"Sahm ","")&IF(特征计算_周度!E8>$B$15,"趋势 ","")&IF(特征计算_周度!F8>$B$15,"斜率",""),"—")) | H25: =IF(OR(B25="",C25=""),"",_xlfn.LET(_xlpm.dev,原始数据_周度!G8,_xlpm.minDev,MIN(OFFSET(原始数据_周度!G8,1-$D$17,0,$D$17,1)),_xlpm.bounce,_xlpm.dev-_xlpm.minDev,IF(AND(ISNUMBER(_xlpm.dev),ISNUMBER(_xlpm.minDev),_xlpm.minDev<=$B$17,_xlpm.bounce>=$F$17),"✅ 触发","—"))) | I25: =IFERROR(IF(特征计算_周度!H25>$I$3,MIN($I$4,MAX(-$I$5,(特征计算_周度!H25-$I$3)*$I$4)),0),"")
A26: =特征计算_周度!A9 | B26: =IFERROR($A$3*特征计算_周度!B26+$B$3*特征计算_周度!C26+$C$3*特征计算_周度!D26+$D$3*特征计算_周度!E26+$E$3*特征计算_周度!F26+$F$3*特征计算_周度!H26,"") | C26: =IFERROR(PERCENTILE(OFFSET(B26,1-364,0,364,1),$C$7),"") | D26: =IFERROR(PERCENTILE(OFFSET(B26,1-364,0,364,1),$C$11),"") | E26: =_xlfn.LET(_xlpm.initState,IF(OR(B26="",C26=""),"",IF(OR(特征计算_周度!B9>$B$15,特征计算_周度!C9>$B$15,特征计算_周度!G9>$B$15,特征计算_周度!E9>$B$15,特征计算_周度!F9>$B$15),$A$12,IFERROR(IF(B26<PERCENTILE(OFFSET(B26,1-364,0,364,1),$C$7),$A$7,IF(B26<PERCENTILE(OFFSET(B26,1-364,0,364,1),$C$8),$A$8,IF(B26<PERCENTILE(OFFSET(B26,1-364,0,364,1),$C$9),$A$9,IF(B26<PERCENTILE(OFFSET(B26,1-364,0,364,1),$C$10),$A$10,IF(B26<PERCENTILE(OFFSET(B26,1-364,0,364,1),$C$11),$A$11,$A$12))))),""))),_xlpm.dev,原始数据_周度!G9,_xlpm.minDev,MIN(OFFSET(原始数据_周度!G9,1-$D$17,0,$D$17,1)),_xlpm.bounce,_xlpm.dev-_xlpm.minDev,_xlpm.oversold,AND(ISNUMBER(_xlpm.dev),ISNUMBER(_xlpm.minDev),_xlpm.minDev<=$B$17,_xlpm.bounce>=$F$17,OR(_xlpm.initState=$A$12,_xlpm.initState=$A$11,_xlpm.initState=$A$10)),_xlpm.pctOnly,IFERROR(IF(B26<PERCENTILE(OFFSET(B26,1-364,0,364,1),$C$7),$A$7,IF(B26<PERCENTILE(OFFSET(B26,1-364,0,364,1),$C$8),$A$8,IF(B26<PERCENTILE(OFFSET(B26,1-364,0,364,1),$C$9),$A$9,IF(B26<PERCENTILE(OFFSET(B26,1-364,0,364,1),$C$10),$A$10,IF(B26<PERCENTILE(OFFSET(B26,1-364,0,364,1),$C$11),$A$11,$A$12))))),""),IF(_xlpm.initState="","",IF(_xlpm.oversold,_xlpm.pctOnly,_xlpm.initState))) | G26: =IF(OR(B26="",C26=""),"",IF(OR(特征计算_周度!B9>$B$15,特征计算_周度!C9>$B$15,特征计算_周度!G9>$B$15,特征计算_周度!E9>$B$15,特征计算_周度!F9>$B$15),IF(特征计算_周度!B9>$B$15,"VIX ","")&IF(特征计算_周度!C9>$B$15,"HY ","")&IF(特征计算_周度!G9>$B$15,"Sahm ","")&IF(特征计算_周度!E9>$B$15,"趋势 ","")&IF(特征计算_周度!F9>$B$15,"斜率",""),"—")) | H26: =IF(OR(B26="",C26=""),"",_xlfn.LET(_xlpm.dev,原始数据_周度!G9,_xlpm.minDev,MIN(OFFSET(原始数据_周度!G9,1-$D$17,0,$D$17,1)),_xlpm.bounce,_xlpm.dev-_xlpm.minDev,IF(AND(ISNUMBER(_xlpm.dev),ISNUMBER(_xlpm.minDev),_xlpm.minDev<=$B$17,_xlpm.bounce>=$F$17),"✅ 触发","—"))) | I26: =IFERROR(IF(特征计算_周度!H26>$I$3,MIN($I$4,MAX(-$I$5,(特征计算_周度!H26-$I$3)*$I$4)),0),"")
A27: =特征计算_周度!A10 | B27: =IFERROR($A$3*特征计算_周度!B27+$B$3*特征计算_周度!C27+$C$3*特征计算_周度!D27+$D$3*特征计算_周度!E27+$E$3*特征计算_周度!F27+$F$3*特征计算_周度!H27,"") | C27: =IFERROR(PERCENTILE(OFFSET(B27,1-364,0,364,1),$C$7),"") | D27: =IFERROR(PERCENTILE(OFFSET(B27,1-364,0,364,1),$C$11),"") | E27: =_xlfn.LET(_xlpm.initState,IF(OR(B27="",C27=""),"",IF(OR(特征计算_周度!B10>$B$15,特征计算_周度!C10>$B$15,特征计算_周度!G10>$B$15,特征计算_周度!E10>$B$15,特征计算_周度!F10>$B$15),$A$12,IFERROR(IF(B27<PERCENTILE(OFFSET(B27,1-364,0,364,1),$C$7),$A$7,IF(B27<PERCENTILE(OFFSET(B27,1-364,0,364,1),$C$8),$A$8,IF(B27<PERCENTILE(OFFSET(B27,1-364,0,364,1),$C$9),$A$9,IF(B27<PERCENTILE(OFFSET(B27,1-364,0,364,1),$C$10),$A$10,IF(B27<PERCENTILE(OFFSET(B27,1-364,0,364,1),$C$11),$A$11,$A$12))))),""))),_xlpm.dev,原始数据_周度!G10,_xlpm.minDev,MIN(OFFSET(原始数据_周度!G10,1-$D$17,0,$D$17,1)),_xlpm.bounce,_xlpm.dev-_xlpm.minDev,_xlpm.oversold,AND(ISNUMBER(_xlpm.dev),ISNUMBER(_xlpm.minDev),_xlpm.minDev<=$B$17,_xlpm.bounce>=$F$17,OR(_xlpm.initState=$A$12,_xlpm.initState=$A$11,_xlpm.initState=$A$10)),_xlpm.pctOnly,IFERROR(IF(B27<PERCENTILE(OFFSET(B27,1-364,0,364,1),$C$7),$A$7,IF(B27<PERCENTILE(OFFSET(B27,1-364,0,364,1),$C$8),$A$8,IF(B27<PERCENTILE(OFFSET(B27,1-364,0,364,1),$C$9),$A$9,IF(B27<PERCENTILE(OFFSET(B27,1-364,0,364,1),$C$10),$A$10,IF(B27<PERCENTILE(OFFSET(B27,1-364,0,364,1),$C$11),$A$11,$A$12))))),""),IF(_xlpm.initState="","",IF(_xlpm.oversold,_xlpm.pctOnly,_xlpm.initState))) | G27: =IF(OR(B27="",C27=""),"",IF(OR(特征计算_周度!B10>$B$15,特征计算_周度!C10>$B$15,特征计算_周度!G10>$B$15,特征计算_周度!E10>$B$15,特征计算_周度!F10>$B$15),IF(特征计算_周度!B10>$B$15,"VIX ","")&IF(特征计算_周度!C10>$B$15,"HY ","")&IF(特征计算_周度!G10>$B$15,"Sahm ","")&IF(特征计算_周度!E10>$B$15,"趋势 ","")&IF(特征计算_周度!F10>$B$15,"斜率",""),"—")) | H27: =IF(OR(B27="",C27=""),"",_xlfn.LET(_xlpm.dev,原始数据_周度!G10,_xlpm.minDev,MIN(OFFSET(原始数据_周度!G10,1-$D$17,0,$D$17,1)),_xlpm.bounce,_xlpm.dev-_xlpm.minDev,IF(AND(ISNUMBER(_xlpm.dev),ISNUMBER(_xlpm.minDev),_xlpm.minDev<=$B$17,_xlpm.bounce>=$F$17),"✅ 触发","—"))) | I27: =IFERROR(IF(特征计算_周度!H27>$I$3,MIN($I$4,MAX(-$I$5,(特征计算_周度!H27-$I$3)*$I$4)),0),"")
A28: =特征计算_周度!A11 | B28: =IFERROR($A$3*特征计算_周度!B28+$B$3*特征计算_周度!C28+$C$3*特征计算_周度!D28+$D$3*特征计算_周度!E28+$E$3*特征计算_周度!F28+$F$3*特征计算_周度!H28,"") | C28: =IFERROR(PERCENTILE(OFFSET(B28,1-364,0,364,1),$C$7),"") | D28: =IFERROR(PERCENTILE(OFFSET(B28,1-364,0,364,1),$C$11),"") | E28: =_xlfn.LET(_xlpm.initState,IF(OR(B28="",C28=""),"",IF(OR(特征计算_周度!B11>$B$15,特征计算_周度!C11>$B$15,特征计算_周度!G11>$B$15,特征计算_周度!E11>$B$15,特征计算_周度!F11>$B$15),$A$12,IFERROR(IF(B28<PERCENTILE(OFFSET(B28,1-364,0,364,1),$C$7),$A$7,IF(B28<PERCENTILE(OFFSET(B28,1-364,0,364,1),$C$8),$A$8,IF(B28<PERCENTILE(OFFSET(B28,1-364,0,364,1),$C$9),$A$9,IF(B28<PERCENTILE(OFFSET(B28,1-364,0,364,1),$C$10),$A$10,IF(B28<PERCENTILE(OFFSET(B28,1-364,0,364,1),$C$11),$A$11,$A$12))))),""))),_xlpm.dev,原始数据_周度!G11,_xlpm.minDev,MIN(OFFSET(原始数据_周度!G11,1-$D$17,0,$D$17,1)),_xlpm.bounce,_xlpm.dev-_xlpm.minDev,_xlpm.oversold,AND(ISNUMBER(_xlpm.dev),ISNUMBER(_xlpm.minDev),_xlpm.minDev<=$B$17,_xlpm.bounce>=$F$17,OR(_xlpm.initState=$A$12,_xlpm.initState=$A$11,_xlpm.initState=$A$10)),_xlpm.pctOnly,IFERROR(IF(B28<PERCENTILE(OFFSET(B28,1-364,0,364,1),$C$7),$A$7,IF(B28<PERCENTILE(OFFSET(B28,1-364,0,364,1),$C$8),$A$8,IF(B28<PERCENTILE(OFFSET(B28,1-364,0,364,1),$C$9),$A$9,IF(B28<PERCENTILE(OFFSET(B28,1-364,0,364,1),$C$10),$A$10,IF(B28<PERCENTILE(OFFSET(B28,1-364,0,364,1),$C$11),$A$11,$A$12))))),""),IF(_xlpm.initState="","",IF(_xlpm.oversold,_xlpm.pctOnly,_xlpm.initState))) | G28: =IF(OR(B28="",C28=""),"",IF(OR(特征计算_周度!B11>$B$15,特征计算_周度!C11>$B$15,特征计算_周度!G11>$B$15,特征计算_周度!E11>$B$15,特征计算_周度!F11>$B$15),IF(特征计算_周度!B11>$B$15,"VIX ","")&IF(特征计算_周度!C11>$B$15,"HY ","")&IF(特征计算_周度!G11>$B$15,"Sahm ","")&IF(特征计算_周度!E11>$B$15,"趋势 ","")&IF(特征计算_周度!F11>$B$15,"斜率",""),"—")) | H28: =IF(OR(B28="",C28=""),"",_xlfn.LET(_xlpm.dev,原始数据_周度!G11,_xlpm.minDev,MIN(OFFSET(原始数据_周度!G11,1-$D$17,0,$D$17,1)),_xlpm.bounce,_xlpm.dev-_xlpm.minDev,IF(AND(ISNUMBER(_xlpm.dev),ISNUMBER(_xlpm.minDev),_xlpm.minDev<=$B$17,_xlpm.bounce>=$F$17),"✅ 触发","—"))) | I28: =IFERROR(IF(特征计算_周度!H28>$I$3,MIN($I$4,MAX(-$I$5,(特征计算_周度!H28-$I$3)*$I$4)),0),"")
A29: =特征计算_周度!A12 | B29: =IFERROR($A$3*特征计算_周度!B29+$B$3*特征计算_周度!C29+$C$3*特征计算_周度!D29+$D$3*特征计算_周度!E29+$E$3*特征计算_周度!F29+$F$3*特征计算_周度!H29,"") | C29: =IFERROR(PERCENTILE(OFFSET(B29,1-364,0,364,1),$C$7),"") | D29: =IFERROR(PERCENTILE(OFFSET(B29,1-364,0,364,1),$C$11),"") | E29: =_xlfn.LET(_xlpm.initState,IF(OR(B29="",C29=""),"",IF(OR(特征计算_周度!B12>$B$15,特征计算_周度!C12>$B$15,特征计算_周度!G12>$B$15,特征计算_周度!E12>$B$15,特征计算_周度!F12>$B$15),$A$12,IFERROR(IF(B29<PERCENTILE(OFFSET(B29,1-364,0,364,1),$C$7),$A$7,IF(B29<PERCENTILE(OFFSET(B29,1-364,0,364,1),$C$8),$A$8,IF(B29<PERCENTILE(OFFSET(B29,1-364,0,364,1),$C$9),$A$9,IF(B29<PERCENTILE(OFFSET(B29,1-364,0,364,1),$C$10),$A$10,IF(B29<PERCENTILE(OFFSET(B29,1-364,0,364,1),$C$11),$A$11,$A$12))))),""))),_xlpm.dev,原始数据_周度!G12,_xlpm.minDev,MIN(OFFSET(原始数据_周度!G12,1-$D$17,0,$D$17,1)),_xlpm.bounce,_xlpm.dev-_xlpm.minDev,_xlpm.oversold,AND(ISNUMBER(_xlpm.dev),ISNUMBER(_xlpm.minDev),_xlpm.minDev<=$B$17,_xlpm.bounce>=$F$17,OR(_xlpm.initState=$A$12,_xlpm.initState=$A$11,_xlpm.initState=$A$10)),_xlpm.pctOnly,IFERROR(IF(B29<PERCENTILE(OFFSET(B29,1-364,0,364,1),$C$7),$A$7,IF(B29<PERCENTILE(OFFSET(B29,1-364,0,364,1),$C$8),$A$8,IF(B29<PERCENTILE(OFFSET(B29,1-364,0,364,1),$C$9),$A$9,IF(B29<PERCENTILE(OFFSET(B29,1-364,0,364,1),$C$10),$A$10,IF(B29<PERCENTILE(OFFSET(B29,1-364,0,364,1),$C$11),$A$11,$A$12))))),""),IF(_xlpm.initState="","",IF(_xlpm.oversold,_xlpm.pctOnly,_xlpm.initState))) | G29: =IF(OR(B29="",C29=""),"",IF(OR(特征计算_周度!B12>$B$15,特征计算_周度!C12>$B$15,特征计算_周度!G12>$B$15,特征计算_周度!E12>$B$15,特征计算_周度!F12>$B$15),IF(特征计算_周度!B12>$B$15,"VIX ","")&IF(特征计算_周度!C12>$B$15,"HY ","")&IF(特征计算_周度!G12>$B$15,"Sahm ","")&IF(特征计算_周度!E12>$B$15,"趋势 ","")&IF(特征计算_周度!F12>$B$15,"斜率",""),"—")) | H29: =IF(OR(B29="",C29=""),"",_xlfn.LET(_xlpm.dev,原始数据_周度!G12,_xlpm.minDev,MIN(OFFSET(原始数据_周度!G12,1-$D$17,0,$D$17,1)),_xlpm.bounce,_xlpm.dev-_xlpm.minDev,IF(AND(ISNUMBER(_xlpm.dev),ISNUMBER(_xlpm.minDev),_xlpm.minDev<=$B$17,_xlpm.bounce>=$F$17),"✅ 触发","—"))) | I29: =IFERROR(IF(特征计算_周度!H29>$I$3,MIN($I$4,MAX(-$I$5,(特征计算_周度!H29-$I$3)*$I$4)),0),"")
A30: =特征计算_周度!A13 | B30: =IFERROR($A$3*特征计算_周度!B30+$B$3*特征计算_周度!C30+$C$3*特征计算_周度!D30+$D$3*特征计算_周度!E30+$E$3*特征计算_周度!F30+$F$3*特征计算_周度!H30,"") | C30: =IFERROR(PERCENTILE(OFFSET(B30,1-364,0,364,1),$C$7),"") | D30: =IFERROR(PERCENTILE(OFFSET(B30,1-364,0,364,1),$C$11),"") | E30: =_xlfn.LET(_xlpm.initState,IF(OR(B30="",C30=""),"",IF(OR(特征计算_周度!B13>$B$15,特征计算_周度!C13>$B$15,特征计算_周度!G13>$B$15,特征计算_周度!E13>$B$15,特征计算_周度!F13>$B$15),$A$12,IFERROR(IF(B30<PERCENTILE(OFFSET(B30,1-364,0,364,1),$C$7),$A$7,IF(B30<PERCENTILE(OFFSET(B30,1-364,0,364,1),$C$8),$A$8,IF(B30<PERCENTILE(OFFSET(B30,1-364,0,364,1),$C$9),$A$9,IF(B30<PERCENTILE(OFFSET(B30,1-364,0,364,1),$C$10),$A$10,IF(B30<PERCENTILE(OFFSET(B30,1-364,0,364,1),$C$11),$A$11,$A$12))))),""))),_xlpm.dev,原始数据_周度!G13,_xlpm.minDev,MIN(OFFSET(原始数据_周度!G13,1-$D$17,0,$D$17,1)),_xlpm.bounce,_xlpm.dev-_xlpm.minDev,_xlpm.oversold,AND(ISNUMBER(_xlpm.dev),ISNUMBER(_xlpm.minDev),_xlpm.minDev<=$B$17,_xlpm.bounce>=$F$17,OR(_xlpm.initState=$A$12,_xlpm.initState=$A$11,_xlpm.initState=$A$10)),_xlpm.pctOnly,IFERROR(IF(B30<PERCENTILE(OFFSET(B30,1-364,0,364,1),$C$7),$A$7,IF(B30<PERCENTILE(OFFSET(B30,1-364,0,364,1),$C$8),$A$8,IF(B30<PERCENTILE(OFFSET(B30,1-364,0,364,1),$C$9),$A$9,IF(B30<PERCENTILE(OFFSET(B30,1-364,0,364,1),$C$10),$A$10,IF(B30<PERCENTILE(OFFSET(B30,1-364,0,364,1),$C$11),$A$11,$A$12))))),""),IF(_xlpm.initState="","",IF(_xlpm.oversold,_xlpm.pctOnly,_xlpm.initState))) | G30: =IF(OR(B30="",C30=""),"",IF(OR(特征计算_周度!B13>$B$15,特征计算_周度!C13>$B$15,特征计算_周度!G13>$B$15,特征计算_周度!E13>$B$15,特征计算_周度!F13>$B$15),IF(特征计算_周度!B13>$B$15,"VIX ","")&IF(特征计算_周度!C13>$B$15,"HY ","")&IF(特征计算_周度!G13>$B$15,"Sahm ","")&IF(特征计算_周度!E13>$B$15,"趋势 ","")&IF(特征计算_周度!F13>$B$15,"斜率",""),"—")) | H30: =IF(OR(B30="",C30=""),"",_xlfn.LET(_xlpm.dev,原始数据_周度!G13,_xlpm.minDev,MIN(OFFSET(原始数据_周度!G13,1-$D$17,0,$D$17,1)),_xlpm.bounce,_xlpm.dev-_xlpm.minDev,IF(AND(ISNUMBER(_xlpm.dev),ISNUMBER(_xlpm.minDev),_xlpm.minDev<=$B$17,_xlpm.bounce>=$F$17),"✅ 触发","—"))) | I30: =IFERROR(IF(特征计算_周度!H30>$I$3,MIN($I$4,MAX(-$I$5,(特征计算_周度!H30-$I$3)*$I$4)),0),"")
... A1546: =特征计算_周度!A1529 | B1546: =IFERROR($A$3*特征计算_周度!B1546+$B$3*特征计算_周度!C1546+$C$3*特征计算_周度!D1546+$D$3*特征计算_周度!E1546+$E$3*特征计算_周度!F1546+$F$3*特征计算_周度!H1546,"") | C1546: =IFERROR(PERCENTILE(OFFSET(B1546,1-364,0,364,1),$C$7),"") | D1546: =IFERROR(PERCENTILE(OFFSET(B1546,1-364,0,364,1),$C$11),"") | E1546: =_xlfn.LET(_xlpm.initState,IF(OR(B1546="",C1546=""),"",IF(OR(特征计算_周度!B1529>$B$15,特征计算_周度!C1529>$B$15,特征计算_周度!G1529>$B$15,特征计算_周度!E1529>$B$15,特征计算_周度!F1529>$B$15),$A$12,IFERROR(IF(B1546<PERCENTILE(OFFSET(B1546,1-364,0,364,1),$C$7),$A$7,IF(B1546<PERCENTILE(OFFSET(B1546,1-364,0,364,1),$C$8),$A$8,IF(B1546<PERCENTILE(OFFSET(B1546,1-364,0,364,1),$C$9),$A$9,IF(B1546<PERCENTILE(OFFSET(B1546,1-364,0,364,1),$C$10),$A$10,IF(B1546<PERCENTILE(OFFSET(B1546,1-364,0,364,1),$C$11),$A$11,$A$12))))),""))),_xlpm.dev,原始数据_周度!G1529,_xlpm.minDev,MIN(OFFSET(原始数据_周度!G1529,1-$D$17,0,$D$17,1)),_xlpm.bounce,_xlpm.dev-_xlpm.minDev,_xlpm.oversold,AND(ISNUMBER(_xlpm.dev),ISNUMBER(_xlpm.minDev),_xlpm.minDev<=$B$17,_xlpm.bounce>=$F$17,OR(_xlpm.initState=$A$12,_xlpm.initState=$A$11,_xlpm.initState=$A$10)),_xlpm.pctOnly,IFERROR(IF(B1546<PERCENTILE(OFFSET(B1546,1-364,0,364,1),$C$7),$A$7,IF(B1546<PERCENTILE(OFFSET(B1546,1-364,0,364,1),$C$8),$A$8,IF(B1546<PERCENTILE(OFFSET(B1546,1-364,0,364,1),$C$9),$A$9,IF(B1546<PERCENTILE(OFFSET(B1546,1-364,0,364,1),$C$10),$A$10,IF(B1546<PERCENTILE(OFFSET(B1546,1-364,0,364,1),$C$11),$A$11,$A$12))))),""),IF(_xlpm.initState="","",IF(_xlpm.oversold,_xlpm.pctOnly,_xlpm.initState))) | G1546: =IF(OR(B1546="",C1546=""),"",IF(OR(特征计算_周度!B1529>$B$15,特征计算_周度!C1529>$B$15,特征计算_周度!G1529>$B$15,特征计算_周度!E1529>$B$15,特征计算_周度!F1529>$B$15),IF(特征计算_周度!B1529>$B$15,"VIX ","")&IF(特征计算_周度!C1529>$B$15,"HY ","")&IF(特征计算_周度!G1529>$B$15,"Sahm ","")&IF(特征计算_周度!E1529>$B$15,"趋势 ","")&IF(特征计算_周度!F1529>$B$15,"斜率",""),"—")) | H1546: =IF(OR(B1546="",C1546=""),"",_xlfn.LET(_xlpm.dev,原始数据_周度!G1529,_xlpm.minDev,MIN(OFFSET(原始数据_周度!G1529,1-$D$17,0,$D$17,1)),_xlpm.bounce,_xlpm.dev-_xlpm.minDev,IF(AND(ISNUMBER(_xlpm.dev),ISNUMBER(_xlpm.minDev),_xlpm.minDev<=$B$17,_xlpm.bounce>=$F$17),"✅ 触发","—"))) | I1546: =IFERROR(IF(特征计算_周度!H1546>$I$3,MIN($I$4,MAX(-$I$5,(特征计算_周度!H1546-$I$3)*$I$4)),0),"")

Sheet 市场状态总览
A1: 市场状态总览
A3: 日期 | B3: 纯综合评分 | C3: 综合评分带否决权 | D3: SP500 | E3: SP500回撤
A4: =原始数据_周度!A2 | B4: =IF(特征计算_周度!B2="","",0.25*IF(特征计算_周度!B2="",0,特征计算_周度!B2)+0.25*IF(特征计算_周度!C2="",0,特征计算_周度!C2)+0.15*IF(特征计算_周度!D2="",0,特征计算_周度!D2)+0.15*IF(特征计算_周度!E2="",0,特征计算_周度!E2)+0.2*IF(特征计算_周度!F2="",0,特征计算_周度!F2)) | C4: =IF(B4="","",IF(OR(IF(特征计算_周度!B2="",FALSE,特征计算_周度!B2>2),IF(特征计算_周度!C2="",FALSE,特征计算_周度!C2>2),IF(特征计算_周度!G2="",FALSE,特征计算_周度!G2>2),IF(特征计算_周度!E2="",FALSE,特征计算_周度!E2>2),IF(特征计算_周度!F2="",FALSE,特征计算_周度!F2>2)),MAX(B4,MAX(IF(特征计算_周度!B2="",0,特征计算_周度!B2),IF(特征计算_周度!C2="",0,特征计算_周度!C2),IF(特征计算_周度!G2="",0,特征计算_周度!G2),IF(特征计算_周度!E2="",0,特征计算_周度!E2),IF(特征计算_周度!F2="",0,特征计算_周度!F2))),B4)) | D4: =原始数据_周度!B2 | E4: =IF(D4="","",D4/MAX(D$4:D4)-1)
A5: =原始数据_周度!A3 | B5: =IF(特征计算_周度!B3="","",0.25*IF(特征计算_周度!B3="",0,特征计算_周度!B3)+0.25*IF(特征计算_周度!C3="",0,特征计算_周度!C3)+0.15*IF(特征计算_周度!D3="",0,特征计算_周度!D3)+0.15*IF(特征计算_周度!E3="",0,特征计算_周度!E3)+0.2*IF(特征计算_周度!F3="",0,特征计算_周度!F3)) | C5: =IF(B5="","",IF(OR(IF(特征计算_周度!B3="",FALSE,特征计算_周度!B3>2),IF(特征计算_周度!C3="",FALSE,特征计算_周度!C3>2),IF(特征计算_周度!G3="",FALSE,特征计算_周度!G3>2),IF(特征计算_周度!E3="",FALSE,特征计算_周度!E3>2),IF(特征计算_周度!F3="",FALSE,特征计算_周度!F3>2)),MAX(B5,MAX(IF(特征计算_周度!B3="",0,特征计算_周度!B3),IF(特征计算_周度!C3="",0,特征计算_周度!C3),IF(特征计算_周度!G3="",0,特征计算_周度!G3),IF(特征计算_周度!E3="",0,特征计算_周度!E3),IF(特征计算_周度!F3="",0,特征计算_周度!F3))),B5)) | D5: =原始数据_周度!B3 | E5: =IF(D5="","",D5/MAX(D$4:D5)-1)
A6: =原始数据_周度!A4 | B6: =IF(特征计算_周度!B4="","",0.25*IF(特征计算_周度!B4="",0,特征计算_周度!B4)+0.25*IF(特征计算_周度!C4="",0,特征计算_周度!C4)+0.15*IF(特征计算_周度!D4="",0,特征计算_周度!D4)+0.15*IF(特征计算_周度!E4="",0,特征计算_周度!E4)+0.2*IF(特征计算_周度!F4="",0,特征计算_周度!F4)) | C6: =IF(B6="","",IF(OR(IF(特征计算_周度!B4="",FALSE,特征计算_周度!B4>2),IF(特征计算_周度!C4="",FALSE,特征计算_周度!C4>2),IF(特征计算_周度!G4="",FALSE,特征计算_周度!G4>2),IF(特征计算_周度!E4="",FALSE,特征计算_周度!E4>2),IF(特征计算_周度!F4="",FALSE,特征计算_周度!F4>2)),MAX(B6,MAX(IF(特征计算_周度!B4="",0,特征计算_周度!B4),IF(特征计算_周度!C4="",0,特征计算_周度!C4),IF(特征计算_周度!G4="",0,特征计算_周度!G4),IF(特征计算_周度!E4="",0,特征计算_周度!E4),IF(特征计算_周度!F4="",0,特征计算_周度!F4))),B6)) | D6: =原始数据_周度!B4 | E6: =IF(D6="","",D6/MAX(D$4:D6)-1)
A7: =原始数据_周度!A5 | B7: =IF(特征计算_周度!B5="","",0.25*IF(特征计算_周度!B5="",0,特征计算_周度!B5)+0.25*IF(特征计算_周度!C5="",0,特征计算_周度!C5)+0.15*IF(特征计算_周度!D5="",0,特征计算_周度!D5)+0.15*IF(特征计算_周度!E5="",0,特征计算_周度!E5)+0.2*IF(特征计算_周度!F5="",0,特征计算_周度!F5)) | C7: =IF(B7="","",IF(OR(IF(特征计算_周度!B5="",FALSE,特征计算_周度!B5>2),IF(特征计算_周度!C5="",FALSE,特征计算_周度!C5>2),IF(特征计算_周度!G5="",FALSE,特征计算_周度!G5>2),IF(特征计算_周度!E5="",FALSE,特征计算_周度!E5>2),IF(特征计算_周度!F5="",FALSE,特征计算_周度!F5>2)),MAX(B7,MAX(IF(特征计算_周度!B5="",0,特征计算_周度!B5),IF(特征计算_周度!C5="",0,特征计算_周度!C5),IF(特征计算_周度!G5="",0,特征计算_周度!G5),IF(特征计算_周度!E5="",0,特征计算_周度!E5),IF(特征计算_周度!F5="",0,特征计算_周度!F5))),B7)) | D7: =原始数据_周度!B5 | E7: =IF(D7="","",D7/MAX(D$4:D7)-1)
A8: =原始数据_周度!A6 | B8: =IF(特征计算_周度!B6="","",0.25*IF(特征计算_周度!B6="",0,特征计算_周度!B6)+0.25*IF(特征计算_周度!C6="",0,特征计算_周度!C6)+0.15*IF(特征计算_周度!D6="",0,特征计算_周度!D6)+0.15*IF(特征计算_周度!E6="",0,特征计算_周度!E6)+0.2*IF(特征计算_周度!F6="",0,特征计算_周度!F6)) | C8: =IF(B8="","",IF(OR(IF(特征计算_周度!B6="",FALSE,特征计算_周度!B6>2),IF(特征计算_周度!C6="",FALSE,特征计算_周度!C6>2),IF(特征计算_周度!G6="",FALSE,特征计算_周度!G6>2),IF(特征计算_周度!E6="",FALSE,特征计算_周度!E6>2),IF(特征计算_周度!F6="",FALSE,特征计算_周度!F6>2)),MAX(B8,MAX(IF(特征计算_周度!B6="",0,特征计算_周度!B6),IF(特征计算_周度!C6="",0,特征计算_周度!C6),IF(特征计算_周度!G6="",0,特征计算_周度!G6),IF(特征计算_周度!E6="",0,特征计算_周度!E6),IF(特征计算_周度!F6="",0,特征计算_周度!F6))),B8)) | D8: =原始数据_周度!B6 | E8: =IF(D8="","",D8/MAX(D$4:D8)-1)
A9: =原始数据_周度!A7 | B9: =IF(特征计算_周度!B7="","",0.25*IF(特征计算_周度!B7="",0,特征计算_周度!B7)+0.25*IF(特征计算_周度!C7="",0,特征计算_周度!C7)+0.15*IF(特征计算_周度!D7="",0,特征计算_周度!D7)+0.15*IF(特征计算_周度!E7="",0,特征计算_周度!E7)+0.2*IF(特征计算_周度!F7="",0,特征计算_周度!F7)) | C9: =IF(B9="","",IF(OR(IF(特征计算_周度!B7="",FALSE,特征计算_周度!B7>2),IF(特征计算_周度!C7="",FALSE,特征计算_周度!C7>2),IF(特征计算_周度!G7="",FALSE,特征计算_周度!G7>2),IF(特征计算_周度!E7="",FALSE,特征计算_周度!E7>2),IF(特征计算_周度!F7="",FALSE,特征计算_周度!F7>2)),MAX(B9,MAX(IF(特征计算_周度!B7="",0,特征计算_周度!B7),IF(特征计算_周度!C7="",0,特征计算_周度!C7),IF(特征计算_周度!G7="",0,特征计算_周度!G7),IF(特征计算_周度!E7="",0,特征计算_周度!E7),IF(特征计算_周度!F7="",0,特征计算_周度!F7))),B9)) | D9: =原始数据_周度!B7 | E9: =IF(D9="","",D9/MAX(D$4:D9)-1)
A10: =原始数据_周度!A8 | B10: =IF(特征计算_周度!B8="","",0.25*IF(特征计算_周度!B8="",0,特征计算_周度!B8)+0.25*IF(特征计算_周度!C8="",0,特征计算_周度!C8)+0.15*IF(特征计算_周度!D8="",0,特征计算_周度!D8)+0.15*IF(特征计算_周度!E8="",0,特征计算_周度!E8)+0.2*IF(特征计算_周度!F8="",0,特征计算_周度!F8)) | C10: =IF(B10="","",IF(OR(IF(特征计算_周度!B8="",FALSE,特征计算_周度!B8>2),IF(特征计算_周度!C8="",FALSE,特征计算_周度!C8>2),IF(特征计算_周度!G8="",FALSE,特征计算_周度!G8>2),IF(特征计算_周度!E8="",FALSE,特征计算_周度!E8>2),IF(特征计算_周度!F8="",FALSE,特征计算_周度!F8>2)),MAX(B10,MAX(IF(特征计算_周度!B8="",0,特征计算_周度!B8),IF(特征计算_周度!C8="",0,特征计算_周度!C8),IF(特征计算_周度!G8="",0,特征计算_周度!G8),IF(特征计算_周度!E8="",0,特征计算_周度!E8),IF(特征计算_周度!F8="",0,特征计算_周度!F8))),B10)) | D10: =原始数据_周度!B8 | E10: =IF(D10="","",D10/MAX(D$4:D10)-1)
A11: =原始数据_周度!A9 | B11: =IF(特征计算_周度!B9="","",0.25*IF(特征计算_周度!B9="",0,特征计算_周度!B9)+0.25*IF(特征计算_周度!C9="",0,特征计算_周度!C9)+0.15*IF(特征计算_周度!D9="",0,特征计算_周度!D9)+0.15*IF(特征计算_周度!E9="",0,特征计算_周度!E9)+0.2*IF(特征计算_周度!F9="",0,特征计算_周度!F9)) | C11: =IF(B11="","",IF(OR(IF(特征计算_周度!B9="",FALSE,特征计算_周度!B9>2),IF(特征计算_周度!C9="",FALSE,特征计算_周度!C9>2),IF(特征计算_周度!G9="",FALSE,特征计算_周度!G9>2),IF(特征计算_周度!E9="",FALSE,特征计算_周度!E9>2),IF(特征计算_周度!F9="",FALSE,特征计算_周度!F9>2)),MAX(B11,MAX(IF(特征计算_周度!B9="",0,特征计算_周度!B9),IF(特征计算_周度!C9="",0,特征计算_周度!C9),IF(特征计算_周度!G9="",0,特征计算_周度!G9),IF(特征计算_周度!E9="",0,特征计算_周度!E9),IF(特征计算_周度!F9="",0,特征计算_周度!F9))),B11)) | D11: =原始数据_周度!B9 | E11: =IF(D11="","",D11/MAX(D$4:D11)-1)
A12: =原始数据_周度!A10 | B12: =IF(特征计算_周度!B10="","",0.25*IF(特征计算_周度!B10="",0,特征计算_周度!B10)+0.25*IF(特征计算_周度!C10="",0,特征计算_周度!C10)+0.15*IF(特征计算_周度!D10="",0,特征计算_周度!D10)+0.15*IF(特征计算_周度!E10="",0,特征计算_周度!E10)+0.2*IF(特征计算_周度!F10="",0,特征计算_周度!F10)) | C12: =IF(B12="","",IF(OR(IF(特征计算_周度!B10="",FALSE,特征计算_周度!B10>2),IF(特征计算_周度!C10="",FALSE,特征计算_周度!C10>2),IF(特征计算_周度!G10="",FALSE,特征计算_周度!G10>2),IF(特征计算_周度!E10="",FALSE,特征计算_周度!E10>2),IF(特征计算_周度!F10="",FALSE,特征计算_周度!F10>2)),MAX(B12,MAX(IF(特征计算_周度!B10="",0,特征计算_周度!B10),IF(特征计算_周度!C10="",0,特征计算_周度!C10),IF(特征计算_周度!G10="",0,特征计算_周度!G10),IF(特征计算_周度!E10="",0,特征计算_周度!E10),IF(特征计算_周度!F10="",0,特征计算_周度!F10))),B12)) | D12: =原始数据_周度!B10 | E12: =IF(D12="","",D12/MAX(D$4:D12)-1)
A13: =原始数据_周度!A11 | B13: =IF(特征计算_周度!B11="","",0.25*IF(特征计算_周度!B11="",0,特征计算_周度!B11)+0.25*IF(特征计算_周度!C11="",0,特征计算_周度!C11)+0.15*IF(特征计算_周度!D11="",0,特征计算_周度!D11)+0.15*IF(特征计算_周度!E11="",0,特征计算_周度!E11)+0.2*IF(特征计算_周度!F11="",0,特征计算_周度!F11)) | C13: =IF(B13="","",IF(OR(IF(特征计算_周度!B11="",FALSE,特征计算_周度!B11>2),IF(特征计算_周度!C11="",FALSE,特征计算_周度!C11>2),IF(特征计算_周度!G11="",FALSE,特征计算_周度!G11>2),IF(特征计算_周度!E11="",FALSE,特征计算_周度!E11>2),IF(特征计算_周度!F11="",FALSE,特征计算_周度!F11>2)),MAX(B13,MAX(IF(特征计算_周度!B11="",0,特征计算_周度!B11),IF(特征计算_周度!C11="",0,特征计算_周度!C11),IF(特征计算_周度!G11="",0,特征计算_周度!G11),IF(特征计算_周度!E11="",0,特征计算_周度!E11),IF(特征计算_周度!F11="",0,特征计算_周度!F11))),B13)) | D13: =原始数据_周度!B11 | E13: =IF(D13="","",D13/MAX(D$4:D13)-1)
A14: =原始数据_周度!A12 | B14: =IF(特征计算_周度!B12="","",0.25*IF(特征计算_周度!B12="",0,特征计算_周度!B12)+0.25*IF(特征计算_周度!C12="",0,特征计算_周度!C12)+0.15*IF(特征计算_周度!D12="",0,特征计算_周度!D12)+0.15*IF(特征计算_周度!E12="",0,特征计算_周度!E12)+0.2*IF(特征计算_周度!F12="",0,特征计算_周度!F12)) | C14: =IF(B14="","",IF(OR(IF(特征计算_周度!B12="",FALSE,特征计算_周度!B12>2),IF(特征计算_周度!C12="",FALSE,特征计算_周度!C12>2),IF(特征计算_周度!G12="",FALSE,特征计算_周度!G12>2),IF(特征计算_周度!E12="",FALSE,特征计算_周度!E12>2),IF(特征计算_周度!F12="",FALSE,特征计算_周度!F12>2)),MAX(B14,MAX(IF(特征计算_周度!B12="",0,特征计算_周度!B12),IF(特征计算_周度!C12="",0,特征计算_周度!C12),IF(特征计算_周度!G12="",0,特征计算_周度!G12),IF(特征计算_周度!E12="",0,特征计算_周度!E12),IF(特征计算_周度!F12="",0,特征计算_周度!F12))),B14)) | D14: =原始数据_周度!B12 | E14: =IF(D14="","",D14/MAX(D$4:D14)-1)
A15: =原始数据_周度!A13 | B15: =IF(特征计算_周度!B13="","",0.25*IF(特征计算_周度!B13="",0,特征计算_周度!B13)+0.25*IF(特征计算_周度!C13="",0,特征计算_周度!C13)+0.15*IF(特征计算_周度!D13="",0,特征计算_周度!D13)+0.15*IF(特征计算_周度!E13="",0,特征计算_周度!E13)+0.2*IF(特征计算_周度!F13="",0,特征计算_周度!F13)) | C15: =IF(B15="","",IF(OR(IF(特征计算_周度!B13="",FALSE,特征计算_周度!B13>2),IF(特征计算_周度!C13="",FALSE,特征计算_周度!C13>2),IF(特征计算_周度!G13="",FALSE,特征计算_周度!G13>2),IF(特征计算_周度!E13="",FALSE,特征计算_周度!E13>2),IF(特征计算_周度!F13="",FALSE,特征计算_周度!F13>2)),MAX(B15,MAX(IF(特征计算_周度!B13="",0,特征计算_周度!B13),IF(特征计算_周度!C13="",0,特征计算_周度!C13),IF(特征计算_周度!G13="",0,特征计算_周度!G13),IF(特征计算_周度!E13="",0,特征计算_周度!E13),IF(特征计算_周度!F13="",0,特征计算_周度!F13))),B15)) | D15: =原始数据_周度!B13 | E15: =IF(D15="","",D15/MAX(D$4:D15)-1)
... A1531: =原始数据_周度!A1529 | B1531: =IF(特征计算_周度!B1529="","",0.25*IF(特征计算_周度!B1529="",0,特征计算_周度!B1529)+0.25*IF(特征计算_周度!C1529="",0,特征计算_周度!C1529)+0.15*IF(特征计算_周度!D1529="",0,特征计算_周度!D1529)+0.15*IF(特征计算_周度!E1529="",0,特征计算_周度!E1529)+0.2*IF(特征计算_周度!F1529="",0,特征计算_周度!F1529)) | C1531: =IF(B1531="","",IF(OR(IF(特征计算_周度!B1529="",FALSE,特征计算_周度!B1529>2),IF(特征计算_周度!C1529="",FALSE,特征计算_周度!C1529>2),IF(特征计算_周度!G1529="",FALSE,特征计算_周度!G1529>2),IF(特征计算_周度!E1529="",FALSE,特征计算_周度!E1529>2),IF(特征计算_周度!F1529="",FALSE,特征计算_周度!F1529>2)),MAX(B1531,MAX(IF(特征计算_周度!B1529="",0,特征计算_周度!B1529),IF(特征计算_周度!C1529="",0,特征计算_周度!C1529),IF(特征计算_周度!G1529="",0,特征计算_周度!G1529),IF(特征计算_周度!E1529="",0,特征计算_周度!E1529),IF(特征计算_周度!F1529="",0,特征计算_周度!F1529))),B1531)) | D1531: =原始数据_周度!B1529 | E1531: =IF(D1531="","",D1531/MAX(D$4:D1531)-1)

Sheet 特征计算_周度
A1: 日期 | B1: VIX_z分数 | C1: 高收益变化_z分数 | D1: 期限利差反转_z | E1: 标普趋势反转_z | F1: 均线斜率反转_z | G1: Sahm_z(否决权用) | H1: 盈利上修_z分数
A2: =原始数据_周度!A2 | B2: ="" | C2: ="" | D2: ="" | E2: ="" | F2: ="" | G2: ="" | H2: =""
A3: =原始数据_周度!A3 | B3: ="" | C3: ="" | D3: ="" | E3: ="" | F3: ="" | G3: ="" | H3: =""
A4: =原始数据_周度!A4 | B4: ="" | C4: ="" | D4: ="" | E4: ="" | F4: ="" | G4: ="" | H4: =""
A5: =原始数据_周度!A5 | B5: ="" | C5: ="" | D5: ="" | E5: ="" | F5: ="" | G5: ="" | H5: =""
A6: =原始数据_周度!A6 | B6: ="" | C6: ="" | D6: ="" | E6: ="" | F6: ="" | G6: ="" | H6: =""
A7: =原始数据_周度!A7 | B7: ="" | C7: ="" | D7: ="" | E7: ="" | F7: ="" | G7: ="" | H7: =""
A8: =原始数据_周度!A8 | B8: ="" | C8: ="" | D8: ="" | E8: ="" | F8: ="" | G8: ="" | H8: =""
A9: =原始数据_周度!A9 | B9: ="" | C9: ="" | D9: ="" | E9: ="" | F9: ="" | G9: ="" | H9: =""
A10: =原始数据_周度!A10 | B10: ="" | C10: ="" | D10: ="" | E10: ="" | F10: ="" | G10: ="" | H10: =""
A11: =原始数据_周度!A11 | B11: ="" | C11: ="" | D11: ="" | E11: ="" | F11: ="" | G11: ="" | H11: =""
A12: =原始数据_周度!A12 | B12: ="" | C12: ="" | D12: ="" | E12: ="" | F12: ="" | G12: ="" | H12: =""
A13: =原始数据_周度!A13 | B13: ="" | C13: ="" | D13: ="" | E13: ="" | F13: ="" | G13: ="" | H13: =""
... A53: =原始数据_周度!A53 | B53: ="" | C53: ="" | D53: ="" | E53: ="" | F53: ="" | G53: ="" | H53: =""
A54: =原始数据_周度!A54 | B54: ="" | C54: ="" | D54: ="" | E54: ="" | F54: ="" | G54: ="" | H54: =IFERROR((原始数据_周度!J54-AVERAGE($J$2:J54))/STDEV($J$2:J54),"")
A55: =原始数据_周度!A55 | B55: ="" | C55: ="" | D55: ="" | E55: ="" | F55: ="" | G55: ="" | H55: =IFERROR((原始数据_周度!J55-AVERAGE($J$2:J55))/STDEV($J$2:J55),"")
A56: =原始数据_周度!A56 | B56: ="" | C56: ="" | D56: ="" | E56: ="" | F56: ="" | G56: ="" | H56: =IFERROR((原始数据_周度!J56-AVERAGE($J$2:J56))/STDEV($J$2:J56),"")
A57: =原始数据_周度!A57 | B57: ="" | C57: ="" | D57: ="" | E57: ="" | F57: ="" | G57: ="" | H57: =IFERROR((原始数据_周度!J57-AVERAGE($J$2:J57))/STDEV($J$2:J57),"")
A58: =原始数据_周度!A58 | B58: ="" | C58: ="" | D58: ="" | E58: ="" | F58: ="" | G58: ="" | H58: =IFERROR((原始数据_周度!J58-AVERAGE($J$2:J58))/STDEV($J$2:J58),"")
A59: =原始数据_周度!A59 | B59: ="" | C59: ="" | D59: ="" | E59: ="" | F59: ="" | G59: ="" | H59: =IFERROR((原始数据_周度!J59-AVERAGE($J$2:J59))/STDEV($J$2:J59),"")
A60: =原始数据_周度!A60 | B60: ="" | C60: ="" | D60: ="" | E60: ="" | F60: ="" | G60: ="" | H60: =IFERROR((原始数据_周度!J60-AVERAGE($J$2:J60))/STDEV($J$2:J60),"")
A61: =原始数据_周度!A61 | B61: ="" | C61: ="" | D61: ="" | E61: ="" | F61: ="" | G61: ="" | H61: =IFERROR((原始数据_周度!J61-AVERAGE($J$2:J61))/STDEV($J$2:J61),"")
A62: =原始数据_周度!A62 | B62: ="" | C62: ="" | D62: ="" | E62: ="" | F62: ="" | G62: ="" | H62: =IFERROR((原始数据_周度!J62-AVERAGE($J$2:J62))/STDEV($J$2:J62),"")
A63: =原始数据_周度!A63 | B63: ="" | C63: ="" | D63: ="" | E63: ="" | F63: ="" | G63: ="" | H63: =IFERROR((原始数据_周度!J63-AVERAGE($J$2:J63))/STDEV($J$2:J63),"")
A64: =原始数据_周度!A64 | B64: ="" | C64: ="" | D64: ="" | E64: ="" | F64: ="" | G64: ="" | H64: =IFERROR((原始数据_周度!J64-AVERAGE($J$2:J64))/STDEV($J$2:J64),"")
A65: =原始数据_周度!A65 | B65: ="" | C65: ="" | D65: ="" | E65: ="" | F65: ="" | G65: ="" | H65: =IFERROR((原始数据_周度!J65-AVERAGE($J$2:J65))/STDEV($J$2:J65),"")
... A156: =原始数据_周度!A156 | B156: ="" | C156: ="" | D156: ="" | E156: ="" | F156: ="" | G156: ="" | H156: =IFERROR((原始数据_周度!J156-AVERAGE($J$2:J156))/STDEV($J$2:J156),"")
A157: =原始数据_周度!A157 | B157: =IFERROR((原始数据_周度!C157-AVERAGE(原始数据_周度!C2:C157))/STDEV(原始数据_周度!C2:C157),"") | C157: ="" | D157: =IFERROR(-1*(原始数据_周度!E157-AVERAGE(原始数据_周度!E2:E157))/STDEV(原始数据_周度!E2:E157),"") | E157: ="" | F157: ="" | G157: =IFERROR((原始数据_周度!I157-AVERAGE(原始数据_周度!I2:I157))/STDEV(原始数据_周度!I2:I157),"") | H157: =IFERROR((原始数据_周度!J157-AVERAGE($J$2:J157))/STDEV($J$2:J157),"")
A158: =原始数据_周度!A158 | B158: =IFERROR((原始数据_周度!C158-AVERAGE(原始数据_周度!C3:C158))/STDEV(原始数据_周度!C3:C158),"") | C158: ="" | D158: =IFERROR(-1*(原始数据_周度!E158-AVERAGE(原始数据_周度!E3:E158))/STDEV(原始数据_周度!E3:E158),"") | E158: ="" | F158: ="" | G158: =IFERROR((原始数据_周度!I158-AVERAGE(原始数据_周度!I3:I158))/STDEV(原始数据_周度!I3:I158),"") | H158: =IFERROR((原始数据_周度!J158-AVERAGE($J$2:J158))/STDEV($J$2:J158),"")
A159: =原始数据_周度!A159 | B159: =IFERROR((原始数据_周度!C159-AVERAGE(原始数据_周度!C4:C159))/STDEV(原始数据_周度!C4:C159),"") | C159: ="" | D159: =IFERROR(-1*(原始数据_周度!E159-AVERAGE(原始数据_周度!E4:E159))/STDEV(原始数据_周度!E4:E159),"") | E159: ="" | F159: ="" | G159: =IFERROR((原始数据_周度!I159-AVERAGE(原始数据_周度!I4:I159))/STDEV(原始数据_周度!I4:I159),"") | H159: =IFERROR((原始数据_周度!J159-AVERAGE($J$2:J159))/STDEV($J$2:J159),"")
A160: =原始数据_周度!A160 | B160: =IFERROR((原始数据_周度!C160-AVERAGE(原始数据_周度!C5:C160))/STDEV(原始数据_周度!C5:C160),"") | C160: ="" | D160: =IFERROR(-1*(原始数据_周度!E160-AVERAGE(原始数据_周度!E5:E160))/STDEV(原始数据_周度!E5:E160),"") | E160: ="" | F160: ="" | G160: =IFERROR((原始数据_周度!I160-AVERAGE(原始数据_周度!I5:I160))/STDEV(原始数据_周度!I5:I160),"") | H160: =IFERROR((原始数据_周度!J160-AVERAGE($J$2:J160))/STDEV($J$2:J160),"")
A161: =原始数据_周度!A161 | B161: =IFERROR((原始数据_周度!C161-AVERAGE(原始数据_周度!C6:C161))/STDEV(原始数据_周度!C6:C161),"") | C161: ="" | D161: =IFERROR(-1*(原始数据_周度!E161-AVERAGE(原始数据_周度!E6:E161))/STDEV(原始数据_周度!E6:E161),"") | E161: ="" | F161: ="" | G161: =IFERROR((原始数据_周度!I161-AVERAGE(原始数据_周度!I6:I161))/STDEV(原始数据_周度!I6:I161),"") | H161: =IFERROR((原始数据_周度!J161-AVERAGE($J$2:J161))/STDEV($J$2:J161),"")
A162: =原始数据_周度!A162 | B162: =IFERROR((原始数据_周度!C162-AVERAGE(原始数据_周度!C7:C162))/STDEV(原始数据_周度!C7:C162),"") | C162: ="" | D162: =IFERROR(-1*(原始数据_周度!E162-AVERAGE(原始数据_周度!E7:E162))/STDEV(原始数据_周度!E7:E162),"") | E162: ="" | F162: ="" | G162: =IFERROR((原始数据_周度!I162-AVERAGE(原始数据_周度!I7:I162))/STDEV(原始数据_周度!I7:I162),"") | H162: =IFERROR((原始数据_周度!J162-AVERAGE($J$2:J162))/STDEV($J$2:J162),"")
A163: =原始数据_周度!A163 | B163: =IFERROR((原始数据_周度!C163-AVERAGE(原始数据_周度!C8:C163))/STDEV(原始数据_周度!C8:C163),"") | C163: ="" | D163: =IFERROR(-1*(原始数据_周度!E163-AVERAGE(原始数据_周度!E8:E163))/STDEV(原始数据_周度!E8:E163),"") | E163: ="" | F163: ="" | G163: =IFERROR((原始数据_周度!I163-AVERAGE(原始数据_周度!I8:I163))/STDEV(原始数据_周度!I8:I163),"") | H163: =IFERROR((原始数据_周度!J163-AVERAGE($J$2:J163))/STDEV($J$2:J163),"")
A164: =原始数据_周度!A164 | B164: =IFERROR((原始数据_周度!C164-AVERAGE(原始数据_周度!C9:C164))/STDEV(原始数据_周度!C9:C164),"") | C164: ="" | D164: =IFERROR(-1*(原始数据_周度!E164-AVERAGE(原始数据_周度!E9:E164))/STDEV(原始数据_周度!E9:E164),"") | E164: ="" | F164: ="" | G164: =IFERROR((原始数据_周度!I164-AVERAGE(原始数据_周度!I9:I164))/STDEV(原始数据_周度!I9:I164),"") | H164: =IFERROR((原始数据_周度!J164-AVERAGE($J$2:J164))/STDEV($J$2:J164),"")
A165: =原始数据_周度!A165 | B165: =IFERROR((原始数据_周度!C165-AVERAGE(原始数据_周度!C10:C165))/STDEV(原始数据_周度!C10:C165),"") | C165: ="" | D165: =IFERROR(-1*(原始数据_周度!E165-AVERAGE(原始数据_周度!E10:E165))/STDEV(原始数据_周度!E10:E165),"") | E165: ="" | F165: ="" | G165: =IFERROR((原始数据_周度!I165-AVERAGE(原始数据_周度!I10:I165))/STDEV(原始数据_周度!I10:I165),"") | H165: =IFERROR((原始数据_周度!J165-AVERAGE($J$2:J165))/STDEV($J$2:J165),"")
A166: =原始数据_周度!A166 | B166: =IFERROR((原始数据_周度!C166-AVERAGE(原始数据_周度!C11:C166))/STDEV(原始数据_周度!C11:C166),"") | C166: ="" | D166: =IFERROR(-1*(原始数据_周度!E166-AVERAGE(原始数据_周度!E11:E166))/STDEV(原始数据_周度!E11:E166),"") | E166: ="" | F166: ="" | G166: =IFERROR((原始数据_周度!I166-AVERAGE(原始数据_周度!I11:I166))/STDEV(原始数据_周度!I11:I166),"") | H166: =IFERROR((原始数据_周度!J166-AVERAGE($J$2:J166))/STDEV($J$2:J166),"")
A167: =原始数据_周度!A167 | B167: =IFERROR((原始数据_周度!C167-AVERAGE(原始数据_周度!C12:C167))/STDEV(原始数据_周度!C12:C167),"") | C167: ="" | D167: =IFERROR(-1*(原始数据_周度!E167-AVERAGE(原始数据_周度!E12:E167))/STDEV(原始数据_周度!E12:E167),"") | E167: ="" | F167: ="" | G167: =IFERROR((原始数据_周度!I167-AVERAGE(原始数据_周度!I12:I167))/STDEV(原始数据_周度!I12:I167),"") | H167: =IFERROR((原始数据_周度!J167-AVERAGE($J$2:J167))/STDEV($J$2:J167),"")
A168: =原始数据_周度!A168 | B168: =IFERROR((原始数据_周度!C168-AVERAGE(原始数据_周度!C13:C168))/STDEV(原始数据_周度!C13:C168),"") | C168: ="" | D168: =IFERROR(-1*(原始数据_周度!E168-AVERAGE(原始数据_周度!E13:E168))/STDEV(原始数据_周度!E13:E168),"") | E168: ="" | F168: ="" | G168: =IFERROR((原始数据_周度!I168-AVERAGE(原始数据_周度!I13:I168))/STDEV(原始数据_周度!I13:I168),"") | H168: =IFERROR((原始数据_周度!J168-AVERAGE($J$2:J168))/STDEV($J$2:J168),"")
A169: =原始数据_周度!A169 | B169: =IFERROR((原始数据_周度!C169-AVERAGE(原始数据_周度!C14:C169))/STDEV(原始数据_周度!C14:C169),"") | C169: ="" | D169: =IFERROR(-1*(原始数据_周度!E169-AVERAGE(原始数据_周度!E14:E169))/STDEV(原始数据_周度!E14:E169),"") | E169: ="" | F169: ="" | G169: =IFERROR((原始数据_周度!I169-AVERAGE(原始数据_周度!I14:I169))/STDEV(原始数据_周度!I14:I169),"") | H169: =IFERROR((原始数据_周度!J169-AVERAGE($J$2:J169))/STDEV($J$2:J169),"")
A170: =原始数据_周度!A170 | B170: =IFERROR((原始数据_周度!C170-AVERAGE(原始数据_周度!C15:C170))/STDEV(原始数据_周度!C15:C170),"") | C170: =IFERROR((原始数据_周度!F170-AVERAGE(原始数据_周度!F15:'原始数据_周度'!F170))/STDEV(原始数据_周度!F15:'原始数据_周度'!F170),"") | D170: =IFERROR(-1*(原始数据_周度!E170-AVERAGE(原始数据_周度!E15:E170))/STDEV(原始数据_周度!E15:E170),"") | E170: ="" | F170: ="" | G170: =IFERROR((原始数据_周度!I170-AVERAGE(原始数据_周度!I15:I170))/STDEV(原始数据_周度!I15:I170),"") | H170: =IFERROR((原始数据_周度!J170-AVERAGE($J$2:J170))/STDEV($J$2:J170),"")
A171: =原始数据_周度!A171 | B171: =IFERROR((原始数据_周度!C171-AVERAGE(原始数据_周度!C16:C171))/STDEV(原始数据_周度!C16:C171),"") | C171: =IFERROR((原始数据_周度!F171-AVERAGE(原始数据_周度!F16:'原始数据_周度'!F171))/STDEV(原始数据_周度!F16:'原始数据_周度'!F171),"") | D171: =IFERROR(-1*(原始数据_周度!E171-AVERAGE(原始数据_周度!E16:E171))/STDEV(原始数据_周度!E16:E171),"") | E171: ="" | F171: ="" | G171: =IFERROR((原始数据_周度!I171-AVERAGE(原始数据_周度!I16:I171))/STDEV(原始数据_周度!I16:I171),"") | H171: =IFERROR((原始数据_周度!J171-AVERAGE($J$2:J171))/STDEV($J$2:J171),"")
A172: =原始数据_周度!A172 | B172: =IFERROR((原始数据_周度!C172-AVERAGE(原始数据_周度!C17:C172))/STDEV(原始数据_周度!C17:C172),"") | C172: =IFERROR((原始数据_周度!F172-AVERAGE(原始数据_周度!F17:'原始数据_周度'!F172))/STDEV(原始数据_周度!F17:'原始数据_周度'!F172),"") | D172: =IFERROR(-1*(原始数据_周度!E172-AVERAGE(原始数据_周度!E17:E172))/STDEV(原始数据_周度!E17:E172),"") | E172: ="" | F172: ="" | G172: =IFERROR((原始数据_周度!I172-AVERAGE(原始数据_周度!I17:I172))/STDEV(原始数据_周度!I17:I172),"") | H172: =IFERROR((原始数据_周度!J172-AVERAGE($J$2:J172))/STDEV($J$2:J172),"")
A173: =原始数据_周度!A173 | B173: =IFERROR((原始数据_周度!C173-AVERAGE(原始数据_周度!C18:C173))/STDEV(原始数据_周度!C18:C173),"") | C173: =IFERROR((原始数据_周度!F173-AVERAGE(原始数据_周度!F18:'原始数据_周度'!F173))/STDEV(原始数据_周度!F18:'原始数据_周度'!F173),"") | D173: =IFERROR(-1*(原始数据_周度!E173-AVERAGE(原始数据_周度!E18:E173))/STDEV(原始数据_周度!E18:E173),"") | E173: ="" | F173: ="" | G173: =IFERROR((原始数据_周度!I173-AVERAGE(原始数据_周度!I18:I173))/STDEV(原始数据_周度!I18:I173),"") | H173: =IFERROR((原始数据_周度!J173-AVERAGE($J$2:J173))/STDEV($J$2:J173),"")
A174: =原始数据_周度!A174 | B174: =IFERROR((原始数据_周度!C174-AVERAGE(原始数据_周度!C19:C174))/STDEV(原始数据_周度!C19:C174),"") | C174: =IFERROR((原始数据_周度!F174-AVERAGE(原始数据_周度!F19:'原始数据_周度'!F174))/STDEV(原始数据_周度!F19:'原始数据_周度'!F174),"") | D174: =IFERROR(-1*(原始数据_周度!E174-AVERAGE(原始数据_周度!E19:E174))/STDEV(原始数据_周度!E19:E174),"") | E174: ="" | F174: ="" | G174: =IFERROR((原始数据_周度!I174-AVERAGE(原始数据_周度!I19:I174))/STDEV(原始数据_周度!I19:I174),"") | H174: =IFERROR((原始数据_周度!J174-AVERAGE($J$2:J174))/STDEV($J$2:J174),"")
A175: =原始数据_周度!A175 | B175: =IFERROR((原始数据_周度!C175-AVERAGE(原始数据_周度!C20:C175))/STDEV(原始数据_周度!C20:C175),"") | C175: =IFERROR((原始数据_周度!F175-AVERAGE(原始数据_周度!F20:'原始数据_周度'!F175))/STDEV(原始数据_周度!F20:'原始数据_周度'!F175),"") | D175: =IFERROR(-1*(原始数据_周度!E175-AVERAGE(原始数据_周度!E20:E175))/STDEV(原始数据_周度!E20:E175),"") | E175: ="" | F175: ="" | G175: =IFERROR((原始数据_周度!I175-AVERAGE(原始数据_周度!I20:I175))/STDEV(原始数据_周度!I20:I175),"") | H175: =IFERROR((原始数据_周度!J175-AVERAGE($J$2:J175))/STDEV($J$2:J175),"")
A176: =原始数据_周度!A176 | B176: =IFERROR((原始数据_周度!C176-AVERAGE(原始数据_周度!C21:C176))/STDEV(原始数据_周度!C21:C176),"") | C176: =IFERROR((原始数据_周度!F176-AVERAGE(原始数据_周度!F21:'原始数据_周度'!F176))/STDEV(原始数据_周度!F21:'原始数据_周度'!F176),"") | D176: =IFERROR(-1*(原始数据_周度!E176-AVERAGE(原始数据_周度!E21:E176))/STDEV(原始数据_周度!E21:E176),"") | E176: ="" | F176: ="" | G176: =IFERROR((原始数据_周度!I176-AVERAGE(原始数据_周度!I21:I176))/STDEV(原始数据_周度!I21:I176),"") | H176: =IFERROR((原始数据_周度!J176-AVERAGE($J$2:J176))/STDEV($J$2:J176),"")
A177: =原始数据_周度!A177 | B177: =IFERROR((原始数据_周度!C177-AVERAGE(原始数据_周度!C22:C177))/STDEV(原始数据_周度!C22:C177),"") | C177: =IFERROR((原始数据_周度!F177-AVERAGE(原始数据_周度!F22:'原始数据_周度'!F177))/STDEV(原始数据_周度!F22:'原始数据_周度'!F177),"") | D177: =IFERROR(-1*(原始数据_周度!E177-AVERAGE(原始数据_周度!E22:E177))/STDEV(原始数据_周度!E22:E177),"") | E177: ="" | F177: ="" | G177: =IFERROR((原始数据_周度!I177-AVERAGE(原始数据_周度!I22:I177))/STDEV(原始数据_周度!I22:I177),"") | H177: =IFERROR((原始数据_周度!J177-AVERAGE($J$2:J177))/STDEV($J$2:J177),"")
A178: =原始数据_周度!A178 | B178: =IFERROR((原始数据_周度!C178-AVERAGE(原始数据_周度!C23:C178))/STDEV(原始数据_周度!C23:C178),"") | C178: =IFERROR((原始数据_周度!F178-AVERAGE(原始数据_周度!F23:'原始数据_周度'!F178))/STDEV(原始数据_周度!F23:'原始数据_周度'!F178),"") | D178: =IFERROR(-1*(原始数据_周度!E178-AVERAGE(原始数据_周度!E23:E178))/STDEV(原始数据_周度!E23:E178),"") | E178: ="" | F178: ="" | G178: =IFERROR((原始数据_周度!I178-AVERAGE(原始数据_周度!I23:I178))/STDEV(原始数据_周度!I23:I178),"") | H178: =IFERROR((原始数据_周度!J178-AVERAGE($J$2:J178))/STDEV($J$2:J178),"")
A179: =原始数据_周度!A179 | B179: =IFERROR((原始数据_周度!C179-AVERAGE(原始数据_周度!C24:C179))/STDEV(原始数据_周度!C24:C179),"") | C179: =IFERROR((原始数据_周度!F179-AVERAGE(原始数据_周度!F24:'原始数据_周度'!F179))/STDEV(原始数据_周度!F24:'原始数据_周度'!F179),"") | D179: =IFERROR(-1*(原始数据_周度!E179-AVERAGE(原始数据_周度!E24:E179))/STDEV(原始数据_周度!E24:E179),"") | E179: ="" | F179: ="" | G179: =IFERROR((原始数据_周度!I179-AVERAGE(原始数据_周度!I24:I179))/STDEV(原始数据_周度!I24:I179),"") | H179: =IFERROR((原始数据_周度!J179-AVERAGE($J$2:J179))/STDEV($J$2:J179),"")
A180: =原始数据_周度!A180 | B180: =IFERROR((原始数据_周度!C180-AVERAGE(原始数据_周度!C25:C180))/STDEV(原始数据_周度!C25:C180),"") | C180: =IFERROR((原始数据_周度!F180-AVERAGE(原始数据_周度!F25:'原始数据_周度'!F180))/STDEV(原始数据_周度!F25:'原始数据_周度'!F180),"") | D180: =IFERROR(-1*(原始数据_周度!E180-AVERAGE(原始数据_周度!E25:E180))/STDEV(原始数据_周度!E25:E180),"") | E180: ="" | F180: ="" | G180: =IFERROR((原始数据_周度!I180-AVERAGE(原始数据_周度!I25:I180))/STDEV(原始数据_周度!I25:I180),"") | H180: =IFERROR((原始数据_周度!J180-AVERAGE($J$2:J180))/STDEV($J$2:J180),"")
A181: =原始数据_周度!A181 | B181: =IFERROR((原始数据_周度!C181-AVERAGE(原始数据_周度!C26:C181))/STDEV(原始数据_周度!C26:C181),"") | C181: =IFERROR((原始数据_周度!F181-AVERAGE(原始数据_周度!F26:'原始数据_周度'!F181))/STDEV(原始数据_周度!F26:'原始数据_周度'!F181),"") | D181: =IFERROR(-1*(原始数据_周度!E181-AVERAGE(原始数据_周度!E26:E181))/STDEV(原始数据_周度!E26:E181),"") | E181: ="" | F181: ="" | G181: =IFERROR((原始数据_周度!I181-AVERAGE(原始数据_周度!I26:I181))/STDEV(原始数据_周度!I26:I181),"") | H181: =IFERROR((原始数据_周度!J181-AVERAGE($J$2:J181))/STDEV($J$2:J181),"")
... A207: =原始数据_周度!A207 | B207: =IFERROR((原始数据_周度!C207-AVERAGE(原始数据_周度!C52:C207))/STDEV(原始数据_周度!C52:C207),"") | C207: =IFERROR((原始数据_周度!F207-AVERAGE(原始数据_周度!F52:'原始数据_周度'!F207))/STDEV(原始数据_周度!F52:'原始数据_周度'!F207),"") | D207: =IFERROR(-1*(原始数据_周度!E207-AVERAGE(原始数据_周度!E52:E207))/STDEV(原始数据_周度!E52:E207),"") | E207: ="" | F207: ="" | G207: =IFERROR((原始数据_周度!I207-AVERAGE(原始数据_周度!I52:I207))/STDEV(原始数据_周度!I52:I207),"") | H207: =IFERROR((原始数据_周度!J207-AVERAGE($J$2:J207))/STDEV($J$2:J207),"")
A208: =原始数据_周度!A208 | B208: =IFERROR((原始数据_周度!C208-AVERAGE(原始数据_周度!C53:C208))/STDEV(原始数据_周度!C53:C208),"") | C208: =IFERROR((原始数据_周度!F208-AVERAGE(原始数据_周度!F53:'原始数据_周度'!F208))/STDEV(原始数据_周度!F53:'原始数据_周度'!F208),"") | D208: =IFERROR(-1*(原始数据_周度!E208-AVERAGE(原始数据_周度!E53:E208))/STDEV(原始数据_周度!E53:E208),"") | E208: =IFERROR(-1*(原始数据_周度!G208-AVERAGE(原始数据_周度!G53:G208))/STDEV(原始数据_周度!G53:G208),"") | F208: ="" | G208: =IFERROR((原始数据_周度!I208-AVERAGE(原始数据_周度!I53:I208))/STDEV(原始数据_周度!I53:I208),"") | H208: =IFERROR((原始数据_周度!J208-AVERAGE($J$2:J208))/STDEV($J$2:J208),"")
A209: =原始数据_周度!A209 | B209: =IFERROR((原始数据_周度!C209-AVERAGE(原始数据_周度!C54:C209))/STDEV(原始数据_周度!C54:C209),"") | C209: =IFERROR((原始数据_周度!F209-AVERAGE(原始数据_周度!F54:'原始数据_周度'!F209))/STDEV(原始数据_周度!F54:'原始数据_周度'!F209),"") | D209: =IFERROR(-1*(原始数据_周度!E209-AVERAGE(原始数据_周度!E54:E209))/STDEV(原始数据_周度!E54:E209),"") | E209: =IFERROR(-1*(原始数据_周度!G209-AVERAGE(原始数据_周度!G54:G209))/STDEV(原始数据_周度!G54:G209),"") | F209: ="" | G209: =IFERROR((原始数据_周度!I209-AVERAGE(原始数据_周度!I54:I209))/STDEV(原始数据_周度!I54:I209),"") | H209: =IFERROR((原始数据_周度!J209-AVERAGE($J$2:J209))/STDEV($J$2:J209),"")
A210: =原始数据_周度!A210 | B210: =IFERROR((原始数据_周度!C210-AVERAGE(原始数据_周度!C55:C210))/STDEV(原始数据_周度!C55:C210),"") | C210: =IFERROR((原始数据_周度!F210-AVERAGE(原始数据_周度!F55:'原始数据_周度'!F210))/STDEV(原始数据_周度!F55:'原始数据_周度'!F210),"") | D210: =IFERROR(-1*(原始数据_周度!E210-AVERAGE(原始数据_周度!E55:E210))/STDEV(原始数据_周度!E55:E210),"") | E210: =IFERROR(-1*(原始数据_周度!G210-AVERAGE(原始数据_周度!G55:G210))/STDEV(原始数据_周度!G55:G210),"") | F210: =IFERROR(-1*(原始数据_周度!H210-AVERAGE(原始数据_周度!H55:H210))/STDEV(原始数据_周度!H55:H210),"") | G210: =IFERROR((原始数据_周度!I210-AVERAGE(原始数据_周度!I55:I210))/STDEV(原始数据_周度!I55:I210),"") | H210: =IFERROR((原始数据_周度!J210-AVERAGE($J$2:J210))/STDEV($J$2:J210),"")
A211: =原始数据_周度!A211 | B211: =IFERROR((原始数据_周度!C211-AVERAGE(原始数据_周度!C56:C211))/STDEV(原始数据_周度!C56:C211),"") | C211: =IFERROR((原始数据_周度!F211-AVERAGE(原始数据_周度!F56:'原始数据_周度'!F211))/STDEV(原始数据_周度!F56:'原始数据_周度'!F211),"") | D211: =IFERROR(-1*(原始数据_周度!E211-AVERAGE(原始数据_周度!E56:E211))/STDEV(原始数据_周度!E56:E211),"") | E211: =IFERROR(-1*(原始数据_周度!G211-AVERAGE(原始数据_周度!G56:G211))/STDEV(原始数据_周度!G56:G211),"") | F211: =IFERROR(-1*(原始数据_周度!H211-AVERAGE(原始数据_周度!H56:H211))/STDEV(原始数据_周度!H56:H211),"") | G211: =IFERROR((原始数据_周度!I211-AVERAGE(原始数据_周度!I56:I211))/STDEV(原始数据_周度!I56:I211),"") | H211: =IFERROR((原始数据_周度!J211-AVERAGE($J$2:J211))/STDEV($J$2:J211),"")
A212: =原始数据_周度!A212 | B212: =IFERROR((原始数据_周度!C212-AVERAGE(原始数据_周度!C57:C212))/STDEV(原始数据_周度!C57:C212),"") | C212: =IFERROR((原始数据_周度!F212-AVERAGE(原始数据_周度!F57:'原始数据_周度'!F212))/STDEV(原始数据_周度!F57:'原始数据_周度'!F212),"") | D212: =IFERROR(-1*(原始数据_周度!E212-AVERAGE(原始数据_周度!E57:E212))/STDEV(原始数据_周度!E57:E212),"") | E212: =IFERROR(-1*(原始数据_周度!G212-AVERAGE(原始数据_周度!G57:G212))/STDEV(原始数据_周度!G57:G212),"") | F212: =IFERROR(-1*(原始数据_周度!H212-AVERAGE(原始数据_周度!H57:H212))/STDEV(原始数据_周度!H57:H212),"") | G212: =IFERROR((原始数据_周度!I212-AVERAGE(原始数据_周度!I57:I212))/STDEV(原始数据_周度!I57:I212),"") | H212: =IFERROR((原始数据_周度!J212-AVERAGE($J$2:J212))/STDEV($J$2:J212),"")
A213: =原始数据_周度!A213 | B213: =IFERROR((原始数据_周度!C213-AVERAGE(原始数据_周度!C58:C213))/STDEV(原始数据_周度!C58:C213),"") | C213: =IFERROR((原始数据_周度!F213-AVERAGE(原始数据_周度!F58:'原始数据_周度'!F213))/STDEV(原始数据_周度!F58:'原始数据_周度'!F213),"") | D213: =IFERROR(-1*(原始数据_周度!E213-AVERAGE(原始数据_周度!E58:E213))/STDEV(原始数据_周度!E58:E213),"") | E213: =IFERROR(-1*(原始数据_周度!G213-AVERAGE(原始数据_周度!G58:G213))/STDEV(原始数据_周度!G58:G213),"") | F213: =IFERROR(-1*(原始数据_周度!H213-AVERAGE(原始数据_周度!H58:H213))/STDEV(原始数据_周度!H58:H213),"") | G213: =IFERROR((原始数据_周度!I213-AVERAGE(原始数据_周度!I58:I213))/STDEV(原始数据_周度!I58:I213),"") | H213: =IFERROR((原始数据_周度!J213-AVERAGE($J$2:J213))/STDEV($J$2:J213),"")
A214: =原始数据_周度!A214 | B214: =IFERROR((原始数据_周度!C214-AVERAGE(原始数据_周度!C59:C214))/STDEV(原始数据_周度!C59:C214),"") | C214: =IFERROR((原始数据_周度!F214-AVERAGE(原始数据_周度!F59:'原始数据_周度'!F214))/STDEV(原始数据_周度!F59:'原始数据_周度'!F214),"") | D214: =IFERROR(-1*(原始数据_周度!E214-AVERAGE(原始数据_周度!E59:E214))/STDEV(原始数据_周度!E59:E214),"") | E214: =IFERROR(-1*(原始数据_周度!G214-AVERAGE(原始数据_周度!G59:G214))/STDEV(原始数据_周度!G59:G214),"") | F214: =IFERROR(-1*(原始数据_周度!H214-AVERAGE(原始数据_周度!H59:H214))/STDEV(原始数据_周度!H59:H214),"") | G214: =IFERROR((原始数据_周度!I214-AVERAGE(原始数据_周度!I59:I214))/STDEV(原始数据_周度!I59:I214),"") | H214: =IFERROR((原始数据_周度!J214-AVERAGE($J$2:J214))/STDEV($J$2:J214),"")
A215: =原始数据_周度!A215 | B215: =IFERROR((原始数据_周度!C215-AVERAGE(原始数据_周度!C60:C215))/STDEV(原始数据_周度!C60:C215),"") | C215: =IFERROR((原始数据_周度!F215-AVERAGE(原始数据_周度!F60:'原始数据_周度'!F215))/STDEV(原始数据_周度!F60:'原始数据_周度'!F215),"") | D215: =IFERROR(-1*(原始数据_周度!E215-AVERAGE(原始数据_周度!E60:E215))/STDEV(原始数据_周度!E60:E215),"") | E215: =IFERROR(-1*(原始数据_周度!G215-AVERAGE(原始数据_周度!G60:G215))/STDEV(原始数据_周度!G60:G215),"") | F215: =IFERROR(-1*(原始数据_周度!H215-AVERAGE(原始数据_周度!H60:H215))/STDEV(原始数据_周度!H60:H215),"") | G215: =IFERROR((原始数据_周度!I215-AVERAGE(原始数据_周度!I60:I215))/STDEV(原始数据_周度!I60:I215),"") | H215: =IFERROR((原始数据_周度!J215-AVERAGE($J$2:J215))/STDEV($J$2:J215),"")
A216: =原始数据_周度!A216 | B216: =IFERROR((原始数据_周度!C216-AVERAGE(原始数据_周度!C61:C216))/STDEV(原始数据_周度!C61:C216),"") | C216: =IFERROR((原始数据_周度!F216-AVERAGE(原始数据_周度!F61:'原始数据_周度'!F216))/STDEV(原始数据_周度!F61:'原始数据_周度'!F216),"") | D216: =IFERROR(-1*(原始数据_周度!E216-AVERAGE(原始数据_周度!E61:E216))/STDEV(原始数据_周度!E61:E216),"") | E216: =IFERROR(-1*(原始数据_周度!G216-AVERAGE(原始数据_周度!G61:G216))/STDEV(原始数据_周度!G61:G216),"") | F216: =IFERROR(-1*(原始数据_周度!H216-AVERAGE(原始数据_周度!H61:H216))/STDEV(原始数据_周度!H61:H216),"") | G216: =IFERROR((原始数据_周度!I216-AVERAGE(原始数据_周度!I61:I216))/STDEV(原始数据_周度!I61:I216),"") | H216: =IFERROR((原始数据_周度!J216-AVERAGE($J$2:J216))/STDEV($J$2:J216),"")
A217: =原始数据_周度!A217 | B217: =IFERROR((原始数据_周度!C217-AVERAGE(原始数据_周度!C62:C217))/STDEV(原始数据_周度!C62:C217),"") | C217: =IFERROR((原始数据_周度!F217-AVERAGE(原始数据_周度!F62:'原始数据_周度'!F217))/STDEV(原始数据_周度!F62:'原始数据_周度'!F217),"") | D217: =IFERROR(-1*(原始数据_周度!E217-AVERAGE(原始数据_周度!E62:E217))/STDEV(原始数据_周度!E62:E217),"") | E217: =IFERROR(-1*(原始数据_周度!G217-AVERAGE(原始数据_周度!G62:G217))/STDEV(原始数据_周度!G62:G217),"") | F217: =IFERROR(-1*(原始数据_周度!H217-AVERAGE(原始数据_周度!H62:H217))/STDEV(原始数据_周度!H62:H217),"") | G217: =IFERROR((原始数据_周度!I217-AVERAGE(原始数据_周度!I62:I217))/STDEV(原始数据_周度!I62:I217),"") | H217: =IFERROR((原始数据_周度!J217-AVERAGE($J$2:J217))/STDEV($J$2:J217),"")
A218: =原始数据_周度!A218 | B218: =IFERROR((原始数据_周度!C218-AVERAGE(原始数据_周度!C63:C218))/STDEV(原始数据_周度!C63:C218),"") | C218: =IFERROR((原始数据_周度!F218-AVERAGE(原始数据_周度!F63:'原始数据_周度'!F218))/STDEV(原始数据_周度!F63:'原始数据_周度'!F218),"") | D218: =IFERROR(-1*(原始数据_周度!E218-AVERAGE(原始数据_周度!E63:E218))/STDEV(原始数据_周度!E63:E218),"") | E218: =IFERROR(-1*(原始数据_周度!G218-AVERAGE(原始数据_周度!G63:G218))/STDEV(原始数据_周度!G63:G218),"") | F218: =IFERROR(-1*(原始数据_周度!H218-AVERAGE(原始数据_周度!H63:H218))/STDEV(原始数据_周度!H63:H218),"") | G218: =IFERROR((原始数据_周度!I218-AVERAGE(原始数据_周度!I63:I218))/STDEV(原始数据_周度!I63:I218),"") | H218: =IFERROR((原始数据_周度!J218-AVERAGE($J$2:J218))/STDEV($J$2:J218),"")
A219: =原始数据_周度!A219 | B219: =IFERROR((原始数据_周度!C219-AVERAGE(原始数据_周度!C64:C219))/STDEV(原始数据_周度!C64:C219),"") | C219: =IFERROR((原始数据_周度!F219-AVERAGE(原始数据_周度!F64:'原始数据_周度'!F219))/STDEV(原始数据_周度!F64:'原始数据_周度'!F219),"") | D219: =IFERROR(-1*(原始数据_周度!E219-AVERAGE(原始数据_周度!E64:E219))/STDEV(原始数据_周度!E64:E219),"") | E219: =IFERROR(-1*(原始数据_周度!G219-AVERAGE(原始数据_周度!G64:G219))/STDEV(原始数据_周度!G64:G219),"") | F219: =IFERROR(-1*(原始数据_周度!H219-AVERAGE(原始数据_周度!H64:H219))/STDEV(原始数据_周度!H64:H219),"") | G219: =IFERROR((原始数据_周度!I219-AVERAGE(原始数据_周度!I64:I219))/STDEV(原始数据_周度!I64:I219),"") | H219: =IFERROR((原始数据_周度!J219-AVERAGE($J$2:J219))/STDEV($J$2:J219),"")
A220: =原始数据_周度!A220 | B220: =IFERROR((原始数据_周度!C220-AVERAGE(原始数据_周度!C65:C220))/STDEV(原始数据_周度!C65:C220),"") | C220: =IFERROR((原始数据_周度!F220-AVERAGE(原始数据_周度!F65:'原始数据_周度'!F220))/STDEV(原始数据_周度!F65:'原始数据_周度'!F220),"") | D220: =IFERROR(-1*(原始数据_周度!E220-AVERAGE(原始数据_周度!E65:E220))/STDEV(原始数据_周度!E65:E220),"") | E220: =IFERROR(-1*(原始数据_周度!G220-AVERAGE(原始数据_周度!G65:G220))/STDEV(原始数据_周度!G65:G220),"") | F220: =IFERROR(-1*(原始数据_周度!H220-AVERAGE(原始数据_周度!H65:H220))/STDEV(原始数据_周度!H65:H220),"") | G220: =IFERROR((原始数据_周度!I220-AVERAGE(原始数据_周度!I65:I220))/STDEV(原始数据_周度!I65:I220),"") | H220: =IFERROR((原始数据_周度!J220-AVERAGE($J$2:J220))/STDEV($J$2:J220),"")
A221: =原始数据_周度!A221 | B221: =IFERROR((原始数据_周度!C221-AVERAGE(原始数据_周度!C66:C221))/STDEV(原始数据_周度!C66:C221),"") | C221: =IFERROR((原始数据_周度!F221-AVERAGE(原始数据_周度!F66:'原始数据_周度'!F221))/STDEV(原始数据_周度!F66:'原始数据_周度'!F221),"") | D221: =IFERROR(-1*(原始数据_周度!E221-AVERAGE(原始数据_周度!E66:E221))/STDEV(原始数据_周度!E66:E221),"") | E221: =IFERROR(-1*(原始数据_周度!G221-AVERAGE(原始数据_周度!G66:G221))/STDEV(原始数据_周度!G66:G221),"") | F221: =IFERROR(-1*(原始数据_周度!H221-AVERAGE(原始数据_周度!H66:H221))/STDEV(原始数据_周度!H66:H221),"") | G221: =IFERROR((原始数据_周度!I221-AVERAGE(原始数据_周度!I66:I221))/STDEV(原始数据_周度!I66:I221),"") | H221: =IFERROR((原始数据_周度!J221-AVERAGE($J$2:J221))/STDEV($J$2:J221),"")
... A419: =原始数据_周度!A419 | B419: =IFERROR((原始数据_周度!C419-AVERAGE(原始数据_周度!C264:C419))/STDEV(原始数据_周度!C264:C419),"") | C419: =IFERROR((原始数据_周度!F419-AVERAGE(原始数据_周度!F264:'原始数据_周度'!F419))/STDEV(原始数据_周度!F264:'原始数据_周度'!F419),"") | D419: =IFERROR(-1*(原始数据_周度!E419-AVERAGE(原始数据_周度!E264:E419))/STDEV(原始数据_周度!E264:E419),"") | E419: =IFERROR(-1*(原始数据_周度!G419-AVERAGE(原始数据_周度!G264:G419))/STDEV(原始数据_周度!G264:G419),"") | F419: =IFERROR(-1*(原始数据_周度!H419-AVERAGE(原始数据_周度!H264:H419))/STDEV(原始数据_周度!H264:H419),"") | G419: =IFERROR((原始数据_周度!I419-AVERAGE(原始数据_周度!I264:I419))/STDEV(原始数据_周度!I264:I419),"") | H419: =IFERROR((原始数据_周度!J419-AVERAGE($J$2:J419))/STDEV($J$2:J419),"")
A420: =原始数据_周度!A420 | B420: =IFERROR((原始数据_周度!C420-AVERAGE(原始数据_周度!C265:C420))/STDEV(原始数据_周度!C265:C420),"") | C420: =IFERROR((原始数据_周度!F420-AVERAGE(原始数据_周度!F265:F420))/STDEV(原始数据_周度!F265:F420),"") | D420: =IFERROR(-1*(原始数据_周度!E420-AVERAGE(原始数据_周度!E265:E420))/STDEV(原始数据_周度!E265:E420),"") | E420: =IFERROR(-1*(原始数据_周度!G420-AVERAGE(原始数据_周度!G265:G420))/STDEV(原始数据_周度!G265:G420),"") | F420: =IFERROR(-1*(原始数据_周度!H420-AVERAGE(原始数据_周度!H265:H420))/STDEV(原始数据_周度!H265:H420),"") | G420: =IFERROR((原始数据_周度!I420-AVERAGE(原始数据_周度!I265:I420))/STDEV(原始数据_周度!I265:I420),"") | H420: =IFERROR((原始数据_周度!J420-AVERAGE($J$2:J420))/STDEV($J$2:J420),"")
A421: =原始数据_周度!A421 | B421: =IFERROR((原始数据_周度!C421-AVERAGE(原始数据_周度!C266:C421))/STDEV(原始数据_周度!C266:C421),"") | C421: =IFERROR((原始数据_周度!F421-AVERAGE(原始数据_周度!F266:F421))/STDEV(原始数据_周度!F266:F421),"") | D421: =IFERROR(-1*(原始数据_周度!E421-AVERAGE(原始数据_周度!E266:E421))/STDEV(原始数据_周度!E266:E421),"") | E421: =IFERROR(-1*(原始数据_周度!G421-AVERAGE(原始数据_周度!G266:G421))/STDEV(原始数据_周度!G266:G421),"") | F421: =IFERROR(-1*(原始数据_周度!H421-AVERAGE(原始数据_周度!H266:H421))/STDEV(原始数据_周度!H266:H421),"") | G421: =IFERROR((原始数据_周度!I421-AVERAGE(原始数据_周度!I266:I421))/STDEV(原始数据_周度!I266:I421),"") | H421: =IFERROR((原始数据_周度!J421-AVERAGE($J$2:J421))/STDEV($J$2:J421),"")
A422: =原始数据_周度!A422 | B422: =IFERROR((原始数据_周度!C422-AVERAGE(原始数据_周度!C267:C422))/STDEV(原始数据_周度!C267:C422),"") | C422: =IFERROR((原始数据_周度!F422-AVERAGE(原始数据_周度!F267:F422))/STDEV(原始数据_周度!F267:F422),"") | D422: =IFERROR(-1*(原始数据_周度!E422-AVERAGE(原始数据_周度!E267:E422))/STDEV(原始数据_周度!E267:E422),"") | E422: =IFERROR(-1*(原始数据_周度!G422-AVERAGE(原始数据_周度!G267:G422))/STDEV(原始数据_周度!G267:G422),"") | F422: =IFERROR(-1*(原始数据_周度!H422-AVERAGE(原始数据_周度!H267:H422))/STDEV(原始数据_周度!H267:H422),"") | G422: =IFERROR((原始数据_周度!I422-AVERAGE(原始数据_周度!I267:I422))/STDEV(原始数据_周度!I267:I422),"") | H422: =IFERROR((原始数据_周度!J422-AVERAGE($J$2:J422))/STDEV($J$2:J422),"")
A423: =原始数据_周度!A423 | B423: =IFERROR((原始数据_周度!C423-AVERAGE(原始数据_周度!C268:C423))/STDEV(原始数据_周度!C268:C423),"") | C423: =IFERROR((原始数据_周度!F423-AVERAGE(原始数据_周度!F268:F423))/STDEV(原始数据_周度!F268:F423),"") | D423: =IFERROR(-1*(原始数据_周度!E423-AVERAGE(原始数据_周度!E268:E423))/STDEV(原始数据_周度!E268:E423),"") | E423: =IFERROR(-1*(原始数据_周度!G423-AVERAGE(原始数据_周度!G268:G423))/STDEV(原始数据_周度!G268:G423),"") | F423: =IFERROR(-1*(原始数据_周度!H423-AVERAGE(原始数据_周度!H268:H423))/STDEV(原始数据_周度!H268:H423),"") | G423: =IFERROR((原始数据_周度!I423-AVERAGE(原始数据_周度!I268:I423))/STDEV(原始数据_周度!I268:I423),"") | H423: =IFERROR((原始数据_周度!J423-AVERAGE($J$2:J423))/STDEV($J$2:J423),"")
A424: =原始数据_周度!A424 | B424: =IFERROR((原始数据_周度!C424-AVERAGE(原始数据_周度!C269:C424))/STDEV(原始数据_周度!C269:C424),"") | C424: =IFERROR((原始数据_周度!F424-AVERAGE(原始数据_周度!F269:F424))/STDEV(原始数据_周度!F269:F424),"") | D424: =IFERROR(-1*(原始数据_周度!E424-AVERAGE(原始数据_周度!E269:E424))/STDEV(原始数据_周度!E269:E424),"") | E424: =IFERROR(-1*(原始数据_周度!G424-AVERAGE(原始数据_周度!G269:G424))/STDEV(原始数据_周度!G269:G424),"") | F424: =IFERROR(-1*(原始数据_周度!H424-AVERAGE(原始数据_周度!H269:H424))/STDEV(原始数据_周度!H269:H424),"") | G424: =IFERROR((原始数据_周度!I424-AVERAGE(原始数据_周度!I269:I424))/STDEV(原始数据_周度!I269:I424),"") | H424: =IFERROR((原始数据_周度!J424-AVERAGE($J$2:J424))/STDEV($J$2:J424),"")
A425: =原始数据_周度!A425 | B425: =IFERROR((原始数据_周度!C425-AVERAGE(原始数据_周度!C270:C425))/STDEV(原始数据_周度!C270:C425),"") | C425: =IFERROR((原始数据_周度!F425-AVERAGE(原始数据_周度!F270:F425))/STDEV(原始数据_周度!F270:F425),"") | D425: =IFERROR(-1*(原始数据_周度!E425-AVERAGE(原始数据_周度!E270:E425))/STDEV(原始数据_周度!E270:E425),"") | E425: =IFERROR(-1*(原始数据_周度!G425-AVERAGE(原始数据_周度!G270:G425))/STDEV(原始数据_周度!G270:G425),"") | F425: =IFERROR(-1*(原始数据_周度!H425-AVERAGE(原始数据_周度!H270:H425))/STDEV(原始数据_周度!H270:H425),"") | G425: =IFERROR((原始数据_周度!I425-AVERAGE(原始数据_周度!I270:I425))/STDEV(原始数据_周度!I270:I425),"") | H425: =IFERROR((原始数据_周度!J425-AVERAGE($J$2:J425))/STDEV($J$2:J425),"")
A426: =原始数据_周度!A426 | B426: =IFERROR((原始数据_周度!C426-AVERAGE(原始数据_周度!C271:C426))/STDEV(原始数据_周度!C271:C426),"") | C426: =IFERROR((原始数据_周度!F426-AVERAGE(原始数据_周度!F271:F426))/STDEV(原始数据_周度!F271:F426),"") | D426: =IFERROR(-1*(原始数据_周度!E426-AVERAGE(原始数据_周度!E271:E426))/STDEV(原始数据_周度!E271:E426),"") | E426: =IFERROR(-1*(原始数据_周度!G426-AVERAGE(原始数据_周度!G271:G426))/STDEV(原始数据_周度!G271:G426),"") | F426: =IFERROR(-1*(原始数据_周度!H426-AVERAGE(原始数据_周度!H271:H426))/STDEV(原始数据_周度!H271:H426),"") | G426: =IFERROR((原始数据_周度!I426-AVERAGE(原始数据_周度!I271:I426))/STDEV(原始数据_周度!I271:I426),"") | H426: =IFERROR((原始数据_周度!J426-AVERAGE($J$2:J426))/STDEV($J$2:J426),"")
A427: =原始数据_周度!A427 | B427: =IFERROR((原始数据_周度!C427-AVERAGE(原始数据_周度!C272:C427))/STDEV(原始数据_周度!C272:C427),"") | C427: =IFERROR((原始数据_周度!F427-AVERAGE(原始数据_周度!F272:F427))/STDEV(原始数据_周度!F272:F427),"") | D427: =IFERROR(-1*(原始数据_周度!E427-AVERAGE(原始数据_周度!E272:E427))/STDEV(原始数据_周度!E272:E427),"") | E427: =IFERROR(-1*(原始数据_周度!G427-AVERAGE(原始数据_周度!G272:G427))/STDEV(原始数据_周度!G272:G427),"") | F427: =IFERROR(-1*(原始数据_周度!H427-AVERAGE(原始数据_周度!H272:H427))/STDEV(原始数据_周度!H272:H427),"") | G427: =IFERROR((原始数据_周度!I427-AVERAGE(原始数据_周度!I272:I427))/STDEV(原始数据_周度!I272:I427),"") | H427: =IFERROR((原始数据_周度!J427-AVERAGE($J$2:J427))/STDEV($J$2:J427),"")
A428: =原始数据_周度!A428 | B428: =IFERROR((原始数据_周度!C428-AVERAGE(原始数据_周度!C273:C428))/STDEV(原始数据_周度!C273:C428),"") | C428: =IFERROR((原始数据_周度!F428-AVERAGE(原始数据_周度!F273:F428))/STDEV(原始数据_周度!F273:F428),"") | D428: =IFERROR(-1*(原始数据_周度!E428-AVERAGE(原始数据_周度!E273:E428))/STDEV(原始数据_周度!E273:E428),"") | E428: =IFERROR(-1*(原始数据_周度!G428-AVERAGE(原始数据_周度!G273:G428))/STDEV(原始数据_周度!G273:G428),"") | F428: =IFERROR(-1*(原始数据_周度!H428-AVERAGE(原始数据_周度!H273:H428))/STDEV(原始数据_周度!H273:H428),"") | G428: =IFERROR((原始数据_周度!I428-AVERAGE(原始数据_周度!I273:I428))/STDEV(原始数据_周度!I273:I428),"") | H428: =IFERROR((原始数据_周度!J428-AVERAGE($J$2:J428))/STDEV($J$2:J428),"")
A429: =原始数据_周度!A429 | B429: =IFERROR((原始数据_周度!C429-AVERAGE(原始数据_周度!C274:C429))/STDEV(原始数据_周度!C274:C429),"") | C429: =IFERROR((原始数据_周度!F429-AVERAGE(原始数据_周度!F274:F429))/STDEV(原始数据_周度!F274:F429),"") | D429: =IFERROR(-1*(原始数据_周度!E429-AVERAGE(原始数据_周度!E274:E429))/STDEV(原始数据_周度!E274:E429),"") | E429: =IFERROR(-1*(原始数据_周度!G429-AVERAGE(原始数据_周度!G274:G429))/STDEV(原始数据_周度!G274:G429),"") | F429: =IFERROR(-1*(原始数据_周度!H429-AVERAGE(原始数据_周度!H274:H429))/STDEV(原始数据_周度!H274:H429),"") | G429: =IFERROR((原始数据_周度!I429-AVERAGE(原始数据_周度!I274:I429))/STDEV(原始数据_周度!I274:I429),"") | H429: =IFERROR((原始数据_周度!J429-AVERAGE($J$2:J429))/STDEV($J$2:J429),"")
A430: =原始数据_周度!A430 | B430: =IFERROR((原始数据_周度!C430-AVERAGE(原始数据_周度!C275:C430))/STDEV(原始数据_周度!C275:C430),"") | C430: =IFERROR((原始数据_周度!F430-AVERAGE(原始数据_周度!F275:F430))/STDEV(原始数据_周度!F275:F430),"") | D430: =IFERROR(-1*(原始数据_周度!E430-AVERAGE(原始数据_周度!E275:E430))/STDEV(原始数据_周度!E275:E430),"") | E430: =IFERROR(-1*(原始数据_周度!G430-AVERAGE(原始数据_周度!G275:G430))/STDEV(原始数据_周度!G275:G430),"") | F430: =IFERROR(-1*(原始数据_周度!H430-AVERAGE(原始数据_周度!H275:H430))/STDEV(原始数据_周度!H275:H430),"") | G430: =IFERROR((原始数据_周度!I430-AVERAGE(原始数据_周度!I275:I430))/STDEV(原始数据_周度!I275:I430),"") | H430: =IFERROR((原始数据_周度!J430-AVERAGE($J$2:J430))/STDEV($J$2:J430),"")
A431: =原始数据_周度!A431 | B431: =IFERROR((原始数据_周度!C431-AVERAGE(原始数据_周度!C276:C431))/STDEV(原始数据_周度!C276:C431),"") | C431: =IFERROR((原始数据_周度!F431-AVERAGE(原始数据_周度!F276:F431))/STDEV(原始数据_周度!F276:F431),"") | D431: =IFERROR(-1*(原始数据_周度!E431-AVERAGE(原始数据_周度!E276:E431))/STDEV(原始数据_周度!E276:E431),"") | E431: =IFERROR(-1*(原始数据_周度!G431-AVERAGE(原始数据_周度!G276:G431))/STDEV(原始数据_周度!G276:G431),"") | F431: =IFERROR(-1*(原始数据_周度!H431-AVERAGE(原始数据_周度!H276:H431))/STDEV(原始数据_周度!H276:H431),"") | G431: =IFERROR((原始数据_周度!I431-AVERAGE(原始数据_周度!I276:I431))/STDEV(原始数据_周度!I276:I431),"") | H431: =IFERROR((原始数据_周度!J431-AVERAGE($J$2:J431))/STDEV($J$2:J431),"")
... A1529: =原始数据_周度!A1529 | B1529: =IFERROR((原始数据_周度!C1529-AVERAGE(原始数据_周度!C1374:C1529))/STDEV(原始数据_周度!C1374:C1529),"") | C1529: =IFERROR((原始数据_周度!F1529-AVERAGE(原始数据_周度!F1374:F1529))/STDEV(原始数据_周度!F1374:F1529),"") | D1529: =IFERROR(-1*(原始数据_周度!E1529-AVERAGE(原始数据_周度!E1374:E1529))/STDEV(原始数据_周度!E1374:E1529),"") | E1529: =IFERROR(-1*(原始数据_周度!G1529-AVERAGE(原始数据_周度!G1374:G1529))/STDEV(原始数据_周度!G1374:G1529),"") | F1529: =IFERROR(-1*(原始数据_周度!H1529-AVERAGE(原始数据_周度!H1374:H1529))/STDEV(原始数据_周度!H1374:H1529),"") | G1529: =IFERROR((原始数据_周度!I1529-AVERAGE(原始数据_周度!I1374:I1529))/STDEV(原始数据_周度!I1374:I1529),"") | H1529: =IFERROR((原始数据_周度!J1529-AVERAGE($J$2:J1529))/STDEV($J$2:J1529),"")

Sheet 原始数据_周度
A1: 日期 | B1: 标普500 | C1: VIX | D1: 高收益利差(%) | E1: 10Y-2Y期限利差(%) | F1: 高收益利差13周变化(辅助) | G1: 标普偏离40周均线(辅助) | H1: 200日均线13周斜率(辅助) | I1: Sahm Rule(否决权用) | J1: 盈利上修代理指标(%)
A2: 35433 | B2: =IF(VLOOKUP(A2,SP500相关数据!$B$11:$C$24727,2,TRUE)<>"",VLOOKUP(A2,SP500相关数据!$B$11:$C$24727,2,TRUE),IF(VLOOKUP(A2-1,SP500相关数据!$B$11:$C$24727,2,TRUE)<>"",VLOOKUP(A2-1,SP500相关数据!$B$11:$C$24727,2,TRUE),VLOOKUP(A2-2,SP500相关数据!$B$11:$C$24727,2,TRUE))) | C2: =IFERROR(IF(VLOOKUP(A2,SP500相关数据!$B$11:$E$24727,4,TRUE)<>"",VLOOKUP(A2,SP500相关数据!$B$11:$E$24727,4,TRUE),IF(VLOOKUP(A2-1,SP500相关数据!$B$11:$E$24727,4,TRUE)<>"",VLOOKUP(A2-1,SP500相关数据!$B$11:$E$24727,4,TRUE),VLOOKUP(A2-2,SP500相关数据!$B$11:$E$24727,4,TRUE))),"") | D2: =IF(VLOOKUP(A2,高收益利差!$A:$B,2,TRUE)<>"",VLOOKUP(A2,高收益利差!$A:$B,2,TRUE),IF(VLOOKUP(A2-1,高收益利差!$A:$B,2,TRUE)<>"",VLOOKUP(A2-1,高收益利差!$A:$B,2,TRUE),VLOOKUP(A2-2,高收益利差!$A:$B,2,TRUE))) | E2: =IFERROR(VLOOKUP(A2,'10Y2Y'!$A:$B,2,TRUE),"") | F2: ="" | G2: ="" | H2: ="" | I2: =IFERROR(VLOOKUP(A2,'Sahm Rule'!$A:$B,2,TRUE),"") | J2: =IFERROR((B2/B2)^4-1-D2/100,"")
A3: 35440 | B3: =IF(VLOOKUP(A3,SP500相关数据!$B$11:$C$24727,2,TRUE)<>"",VLOOKUP(A3,SP500相关数据!$B$11:$C$24727,2,TRUE),IF(VLOOKUP(A3-1,SP500相关数据!$B$11:$C$24727,2,TRUE)<>"",VLOOKUP(A3-1,SP500相关数据!$B$11:$C$24727,2,TRUE),VLOOKUP(A3-2,SP500相关数据!$B$11:$C$24727,2,TRUE))) | C3: =IFERROR(IF(VLOOKUP(A3,SP500相关数据!$B$11:$E$24727,4,TRUE)<>"",VLOOKUP(A3,SP500相关数据!$B$11:$E$24727,4,TRUE),IF(VLOOKUP(A3-1,SP500相关数据!$B$11:$E$24727,4,TRUE)<>"",VLOOKUP(A3-1,SP500相关数据!$B$11:$E$24727,4,TRUE),VLOOKUP(A3-2,SP500相关数据!$B$11:$E$24727,4,TRUE))),"") | D3: =IF(VLOOKUP(A3,高收益利差!$A:$B,2,TRUE)<>"",VLOOKUP(A3,高收益利差!$A:$B,2,TRUE),IF(VLOOKUP(A3-1,高收益利差!$A:$B,2,TRUE)<>"",VLOOKUP(A3-1,高收益利差!$A:$B,2,TRUE),VLOOKUP(A3-2,高收益利差!$A:$B,2,TRUE))) | E3: =IFERROR(VLOOKUP(A3,'10Y2Y'!$A:$B,2,TRUE),"") | F3: ="" | G3: ="" | H3: ="" | I3: =IFERROR(VLOOKUP(A3,'Sahm Rule'!$A:$B,2,TRUE),"") | J3: =IFERROR((B3/B-10)^4-1-D3/100,"")
A4: 35447 | B4: =IF(VLOOKUP(A4,SP500相关数据!$B$11:$C$24727,2,TRUE)<>"",VLOOKUP(A4,SP500相关数据!$B$11:$C$24727,2,TRUE),IF(VLOOKUP(A4-1,SP500相关数据!$B$11:$C$24727,2,TRUE)<>"",VLOOKUP(A4-1,SP500相关数据!$B$11:$C$24727,2,TRUE),VLOOKUP(A4-2,SP500相关数据!$B$11:$C$24727,2,TRUE))) | C4: =IFERROR(IF(VLOOKUP(A4,SP500相关数据!$B$11:$E$24727,4,TRUE)<>"",VLOOKUP(A4,SP500相关数据!$B$11:$E$24727,4,TRUE),IF(VLOOKUP(A4-1,SP500相关数据!$B$11:$E$24727,4,TRUE)<>"",VLOOKUP(A4-1,SP500相关数据!$B$11:$E$24727,4,TRUE),VLOOKUP(A4-2,SP500相关数据!$B$11:$E$24727,4,TRUE))),"") | D4: =IF(VLOOKUP(A4,高收益利差!$A:$B,2,TRUE)<>"",VLOOKUP(A4,高收益利差!$A:$B,2,TRUE),IF(VLOOKUP(A4-1,高收益利差!$A:$B,2,TRUE)<>"",VLOOKUP(A4-1,高收益利差!$A:$B,2,TRUE),VLOOKUP(A4-2,高收益利差!$A:$B,2,TRUE))) | E4: =IFERROR(VLOOKUP(A4,'10Y2Y'!$A:$B,2,TRUE),"") | F4: ="" | G4: ="" | H4: ="" | I4: =IFERROR(VLOOKUP(A4,'Sahm Rule'!$A:$B,2,TRUE),"") | J4: =IFERROR((B4/B-9)^4-1-D4/100,"")
A5: 35454 | B5: =IF(VLOOKUP(A5,SP500相关数据!$B$11:$C$24727,2,TRUE)<>"",VLOOKUP(A5,SP500相关数据!$B$11:$C$24727,2,TRUE),IF(VLOOKUP(A5-1,SP500相关数据!$B$11:$C$24727,2,TRUE)<>"",VLOOKUP(A5-1,SP500相关数据!$B$11:$C$24727,2,TRUE),VLOOKUP(A5-2,SP500相关数据!$B$11:$C$24727,2,TRUE))) | C5: =IFERROR(IF(VLOOKUP(A5,SP500相关数据!$B$11:$E$24727,4,TRUE)<>"",VLOOKUP(A5,SP500相关数据!$B$11:$E$24727,4,TRUE),IF(VLOOKUP(A5-1,SP500相关数据!$B$11:$E$24727,4,TRUE)<>"",VLOOKUP(A5-1,SP500相关数据!$B$11:$E$24727,4,TRUE),VLOOKUP(A5-2,SP500相关数据!$B$11:$E$24727,4,TRUE))),"") | D5: =IF(VLOOKUP(A5,高收益利差!$A:$B,2,TRUE)<>"",VLOOKUP(A5,高收益利差!$A:$B,2,TRUE),IF(VLOOKUP(A5-1,高收益利差!$A:$B,2,TRUE)<>"",VLOOKUP(A5-1,高收益利差!$A:$B,2,TRUE),VLOOKUP(A5-2,高收益利差!$A:$B,2,TRUE))) | E5: =IFERROR(VLOOKUP(A5,'10Y2Y'!$A:$B,2,TRUE),"") | F5: ="" | G5: ="" | H5: ="" | I5: =IFERROR(VLOOKUP(A5,'Sahm Rule'!$A:$B,2,TRUE),"") | J5: =IFERROR((B5/B-8)^4-1-D5/100,"")
A6: 35461 | B6: =IF(VLOOKUP(A6,SP500相关数据!$B$11:$C$24727,2,TRUE)<>"",VLOOKUP(A6,SP500相关数据!$B$11:$C$24727,2,TRUE),IF(VLOOKUP(A6-1,SP500相关数据!$B$11:$C$24727,2,TRUE)<>"",VLOOKUP(A6-1,SP500相关数据!$B$11:$C$24727,2,TRUE),VLOOKUP(A6-2,SP500相关数据!$B$11:$C$24727,2,TRUE))) | C6: =IFERROR(IF(VLOOKUP(A6,SP500相关数据!$B$11:$E$24727,4,TRUE)<>"",VLOOKUP(A6,SP500相关数据!$B$11:$E$24727,4,TRUE),IF(VLOOKUP(A6-1,SP500相关数据!$B$11:$E$24727,4,TRUE)<>"",VLOOKUP(A6-1,SP500相关数据!$B$11:$E$24727,4,TRUE),VLOOKUP(A6-2,SP500相关数据!$B$11:$E$24727,4,TRUE))),"") | D6: =IF(VLOOKUP(A6,高收益利差!$A:$B,2,TRUE)<>"",VLOOKUP(A6,高收益利差!$A:$B,2,TRUE),IF(VLOOKUP(A6-1,高收益利差!$A:$B,2,TRUE)<>"",VLOOKUP(A6-1,高收益利差!$A:$B,2,TRUE),VLOOKUP(A6-2,高收益利差!$A:$B,2,TRUE))) | E6: =IFERROR(VLOOKUP(A6,'10Y2Y'!$A:$B,2,TRUE),"") | F6: ="" | G6: ="" | H6: ="" | I6: =IFERROR(VLOOKUP(A6,'Sahm Rule'!$A:$B,2,TRUE),"") | J6: =IFERROR((B6/B-7)^4-1-D6/100,"")
A7: 35468 | B7: =IF(VLOOKUP(A7,SP500相关数据!$B$11:$C$24727,2,TRUE)<>"",VLOOKUP(A7,SP500相关数据!$B$11:$C$24727,2,TRUE),IF(VLOOKUP(A7-1,SP500相关数据!$B$11:$C$24727,2,TRUE)<>"",VLOOKUP(A7-1,SP500相关数据!$B$11:$C$24727,2,TRUE),VLOOKUP(A7-2,SP500相关数据!$B$11:$C$24727,2,TRUE))) | C7: =IFERROR(IF(VLOOKUP(A7,SP500相关数据!$B$11:$E$24727,4,TRUE)<>"",VLOOKUP(A7,SP500相关数据!$B$11:$E$24727,4,TRUE),IF(VLOOKUP(A7-1,SP500相关数据!$B$11:$E$24727,4,TRUE)<>"",VLOOKUP(A7-1,SP500相关数据!$B$11:$E$24727,4,TRUE),VLOOKUP(A7-2,SP500相关数据!$B$11:$E$24727,4,TRUE))),"") | D7: =IF(VLOOKUP(A7,高收益利差!$A:$B,2,TRUE)<>"",VLOOKUP(A7,高收益利差!$A:$B,2,TRUE),IF(VLOOKUP(A7-1,高收益利差!$A:$B,2,TRUE)<>"",VLOOKUP(A7-1,高收益利差!$A:$B,2,TRUE),VLOOKUP(A7-2,高收益利差!$A:$B,2,TRUE))) | E7: =IFERROR(VLOOKUP(A7,'10Y2Y'!$A:$B,2,TRUE),"") | F7: ="" | G7: ="" | H7: ="" | I7: =IFERROR(VLOOKUP(A7,'Sahm Rule'!$A:$B,2,TRUE),"") | J7: =IFERROR((B7/B-6)^4-1-D7/100,"")
A8: 35475 | B8: =IF(VLOOKUP(A8,SP500相关数据!$B$11:$C$24727,2,TRUE)<>"",VLOOKUP(A8,SP500相关数据!$B$11:$C$24727,2,TRUE),IF(VLOOKUP(A8-1,SP500相关数据!$B$11:$C$24727,2,TRUE)<>"",VLOOKUP(A8-1,SP500相关数据!$B$11:$C$24727,2,TRUE),VLOOKUP(A8-2,SP500相关数据!$B$11:$C$24727,2,TRUE))) | C8: =IFERROR(IF(VLOOKUP(A8,SP500相关数据!$B$11:$E$24727,4,TRUE)<>"",VLOOKUP(A8,SP500相关数据!$B$11:$E$24727,4,TRUE),IF(VLOOKUP(A8-1,SP500相关数据!$B$11:$E$24727,4,TRUE)<>"",VLOOKUP(A8-1,SP500相关数据!$B$11:$E$24727,4,TRUE),VLOOKUP(A8-2,SP500相关数据!$B$11:$E$24727,4,TRUE))),"") | D8: =IF(VLOOKUP(A8,高收益利差!$A:$B,2,TRUE)<>"",VLOOKUP(A8,高收益利差!$A:$B,2,TRUE),IF(VLOOKUP(A8-1,高收益利差!$A:$B,2,TRUE)<>"",VLOOKUP(A8-1,高收益利差!$A:$B,2,TRUE),VLOOKUP(A8-2,高收益利差!$A:$B,2,TRUE))) | E8: =IFERROR(VLOOKUP(A8,'10Y2Y'!$A:$B,2,TRUE),"") | F8: ="" | G8: ="" | H8: ="" | I8: =IFERROR(VLOOKUP(A8,'Sahm Rule'!$A:$B,2,TRUE),"") | J8: =IFERROR((B8/B-5)^4-1-D8/100,"")
A9: 35482 | B9: =IF(VLOOKUP(A9,SP500相关数据!$B$11:$C$24727,2,TRUE)<>"",VLOOKUP(A9,SP500相关数据!$B$11:$C$24727,2,TRUE),IF(VLOOKUP(A9-1,SP500相关数据!$B$11:$C$24727,2,TRUE)<>"",VLOOKUP(A9-1,SP500相关数据!$B$11:$C$24727,2,TRUE),VLOOKUP(A9-2,SP500相关数据!$B$11:$C$24727,2,TRUE))) | C9: =IFERROR(IF(VLOOKUP(A9,SP500相关数据!$B$11:$E$24727,4,TRUE)<>"",VLOOKUP(A9,SP500相关数据!$B$11:$E$24727,4,TRUE),IF(VLOOKUP(A9-1,SP500相关数据!$B$11:$E$24727,4,TRUE)<>"",VLOOKUP(A9-1,SP500相关数据!$B$11:$E$24727,4,TRUE),VLOOKUP(A9-2,SP500相关数据!$B$11:$E$24727,4,TRUE))),"") | D9: =IF(VLOOKUP(A9,高收益利差!$A:$B,2,TRUE)<>"",VLOOKUP(A9,高收益利差!$A:$B,2,TRUE),IF(VLOOKUP(A9-1,高收益利差!$A:$B,2,TRUE)<>"",VLOOKUP(A9-1,高收益利差!$A:$B,2,TRUE),VLOOKUP(A9-2,高收益利差!$A:$B,2,TRUE))) | E9: =IFERROR(VLOOKUP(A9,'10Y2Y'!$A:$B,2,TRUE),"") | F9: ="" | G9: ="" | H9: ="" | I9: =IFERROR(VLOOKUP(A9,'Sahm Rule'!$A:$B,2,TRUE),"") | J9: =IFERROR((B9/B-4)^4-1-D9/100,"")
A10: 35489 | B10: =IF(VLOOKUP(A10,SP500相关数据!$B$11:$C$24727,2,TRUE)<>"",VLOOKUP(A10,SP500相关数据!$B$11:$C$24727,2,TRUE),IF(VLOOKUP(A10-1,SP500相关数据!$B$11:$C$24727,2,TRUE)<>"",VLOOKUP(A10-1,SP500相关数据!$B$11:$C$24727,2,TRUE),VLOOKUP(A10-2,SP500相关数据!$B$11:$C$24727,2,TRUE))) | C10: =IFERROR(IF(VLOOKUP(A10,SP500相关数据!$B$11:$E$24727,4,TRUE)<>"",VLOOKUP(A10,SP500相关数据!$B$11:$E$24727,4,TRUE),IF(VLOOKUP(A10-1,SP500相关数据!$B$11:$E$24727,4,TRUE)<>"",VLOOKUP(A10-1,SP500相关数据!$B$11:$E$24727,4,TRUE),VLOOKUP(A10-2,SP500相关数据!$B$11:$E$24727,4,TRUE))),"") | D10: =IF(VLOOKUP(A10,高收益利差!$A:$B,2,TRUE)<>"",VLOOKUP(A10,高收益利差!$A:$B,2,TRUE),IF(VLOOKUP(A10-1,高收益利差!$A:$B,2,TRUE)<>"",VLOOKUP(A10-1,高收益利差!$A:$B,2,TRUE),VLOOKUP(A10-2,高收益利差!$A:$B,2,TRUE))) | E10: =IFERROR(VLOOKUP(A10,'10Y2Y'!$A:$B,2,TRUE),"") | F10: ="" | G10: ="" | H10: ="" | I10: =IFERROR(VLOOKUP(A10,'Sahm Rule'!$A:$B,2,TRUE),"") | J10: =IFERROR((B10/B-3)^4-1-D10/100,"")
A11: 35496 | B11: =IF(VLOOKUP(A11,SP500相关数据!$B$11:$C$24727,2,TRUE)<>"",VLOOKUP(A11,SP500相关数据!$B$11:$C$24727,2,TRUE),IF(VLOOKUP(A11-1,SP500相关数据!$B$11:$C$24727,2,TRUE)<>"",VLOOKUP(A11-1,SP500相关数据!$B$11:$C$24727,2,TRUE),VLOOKUP(A11-2,SP500相关数据!$B$11:$C$24727,2,TRUE))) | C11: =IFERROR(IF(VLOOKUP(A11,SP500相关数据!$B$11:$E$24727,4,TRUE)<>"",VLOOKUP(A11,SP500相关数据!$B$11:$E$24727,4,TRUE),IF(VLOOKUP(A11-1,SP500相关数据!$B$11:$E$24727,4,TRUE)<>"",VLOOKUP(A11-1,SP500相关数据!$B$11:$E$24727,4,TRUE),VLOOKUP(A11-2,SP500相关数据!$B$11:$E$24727,4,TRUE))),"") | D11: =IF(VLOOKUP(A11,高收益利差!$A:$B,2,TRUE)<>"",VLOOKUP(A11,高收益利差!$A:$B,2,TRUE),IF(VLOOKUP(A11-1,高收益利差!$A:$B,2,TRUE)<>"",VLOOKUP(A11-1,高收益利差!$A:$B,2,TRUE),VLOOKUP(A11-2,高收益利差!$A:$B,2,TRUE))) | E11: =IFERROR(VLOOKUP(A11,'10Y2Y'!$A:$B,2,TRUE),"") | F11: ="" | G11: ="" | H11: ="" | I11: =IFERROR(VLOOKUP(A11,'Sahm Rule'!$A:$B,2,TRUE),"") | J11: =IFERROR((B11/B-2)^4-1-D11/100,"")
A12: 35503 | B12: =IF(VLOOKUP(A12,SP500相关数据!$B$11:$C$24727,2,TRUE)<>"",VLOOKUP(A12,SP500相关数据!$B$11:$C$24727,2,TRUE),IF(VLOOKUP(A12-1,SP500相关数据!$B$11:$C$24727,2,TRUE)<>"",VLOOKUP(A12-1,SP500相关数据!$B$11:$C$24727,2,TRUE),VLOOKUP(A12-2,SP500相关数据!$B$11:$C$24727,2,TRUE))) | C12: =IFERROR(IF(VLOOKUP(A12,SP500相关数据!$B$11:$E$24727,4,TRUE)<>"",VLOOKUP(A12,SP500相关数据!$B$11:$E$24727,4,TRUE),IF(VLOOKUP(A12-1,SP500相关数据!$B$11:$E$24727,4,TRUE)<>"",VLOOKUP(A12-1,SP500相关数据!$B$11:$E$24727,4,TRUE),VLOOKUP(A12-2,SP500相关数据!$B$11:$E$24727,4,TRUE))),"") | D12: =IF(VLOOKUP(A12,高收益利差!$A:$B,2,TRUE)<>"",VLOOKUP(A12,高收益利差!$A:$B,2,TRUE),IF(VLOOKUP(A12-1,高收益利差!$A:$B,2,TRUE)<>"",VLOOKUP(A12-1,高收益利差!$A:$B,2,TRUE),VLOOKUP(A12-2,高收益利差!$A:$B,2,TRUE))) | E12: =IFERROR(VLOOKUP(A12,'10Y2Y'!$A:$B,2,TRUE),"") | F12: ="" | G12: ="" | H12: ="" | I12: =IFERROR(VLOOKUP(A12,'Sahm Rule'!$A:$B,2,TRUE),"") | J12: =IFERROR((B12/B-1)^4-1-D12/100,"")
A13: 35510 | B13: =IF(VLOOKUP(A13,SP500相关数据!$B$11:$C$24727,2,TRUE)<>"",VLOOKUP(A13,SP500相关数据!$B$11:$C$24727,2,TRUE),IF(VLOOKUP(A13-1,SP500相关数据!$B$11:$C$24727,2,TRUE)<>"",VLOOKUP(A13-1,SP500相关数据!$B$11:$C$24727,2,TRUE),VLOOKUP(A13-2,SP500相关数据!$B$11:$C$24727,2,TRUE))) | C13: =IFERROR(IF(VLOOKUP(A13,SP500相关数据!$B$11:$E$24727,4,TRUE)<>"",VLOOKUP(A13,SP500相关数据!$B$11:$E$24727,4,TRUE),IF(VLOOKUP(A13-1,SP500相关数据!$B$11:$E$24727,4,TRUE)<>"",VLOOKUP(A13-1,SP500相关数据!$B$11:$E$24727,4,TRUE),VLOOKUP(A13-2,SP500相关数据!$B$11:$E$24727,4,TRUE))),"") | D13: =IF(VLOOKUP(A13,高收益利差!$A:$B,2,TRUE)<>"",VLOOKUP(A13,高收益利差!$A:$B,2,TRUE),IF(VLOOKUP(A13-1,高收益利差!$A:$B,2,TRUE)<>"",VLOOKUP(A13-1,高收益利差!$A:$B,2,TRUE),VLOOKUP(A13-2,高收益利差!$A:$B,2,TRUE))) | E13: =IFERROR(VLOOKUP(A13,'10Y2Y'!$A:$B,2,TRUE),"") | F13: ="" | G13: ="" | H13: ="" | I13: =IFERROR(VLOOKUP(A13,'Sahm Rule'!$A:$B,2,TRUE),"") | J13: =IFERROR((B13/B0)^4-1-D13/100,"")
A14: 35517 | B14: =IF(VLOOKUP(A14,SP500相关数据!$B$11:$C$24727,2,TRUE)<>"",VLOOKUP(A14,SP500相关数据!$B$11:$C$24727,2,TRUE),IF(VLOOKUP(A14-1,SP500相关数据!$B$11:$C$24727,2,TRUE)<>"",VLOOKUP(A14-1,SP500相关数据!$B$11:$C$24727,2,TRUE),VLOOKUP(A14-2,SP500相关数据!$B$11:$C$24727,2,TRUE))) | C14: =IFERROR(IF(VLOOKUP(A14,SP500相关数据!$B$11:$E$24727,4,TRUE)<>"",VLOOKUP(A14,SP500相关数据!$B$11:$E$24727,4,TRUE),IF(VLOOKUP(A14-1,SP500相关数据!$B$11:$E$24727,4,TRUE)<>"",VLOOKUP(A14-1,SP500相关数据!$B$11:$E$24727,4,TRUE),VLOOKUP(A14-2,SP500相关数据!$B$11:$E$24727,4,TRUE))),"") | D14: =IF(VLOOKUP(A14,高收益利差!$A:$B,2,TRUE)<>"",VLOOKUP(A14,高收益利差!$A:$B,2,TRUE),IF(VLOOKUP(A14-1,高收益利差!$A:$B,2,TRUE)<>"",VLOOKUP(A14-1,高收益利差!$A:$B,2,TRUE),VLOOKUP(A14-2,高收益利差!$A:$B,2,TRUE))) | E14: =IFERROR(VLOOKUP(A14,'10Y2Y'!$A:$B,2,TRUE),"") | F14: ="" | G14: ="" | H14: ="" | I14: =IFERROR(VLOOKUP(A14,'Sahm Rule'!$A:$B,2,TRUE),"") | J14: =IFERROR((B14/B1)^4-1-D14/100,"")
A15: 35524 | B15: =IF(VLOOKUP(A15,SP500相关数据!$B$11:$C$24727,2,TRUE)<>"",VLOOKUP(A15,SP500相关数据!$B$11:$C$24727,2,TRUE),IF(VLOOKUP(A15-1,SP500相关数据!$B$11:$C$24727,2,TRUE)<>"",VLOOKUP(A15-1,SP500相关数据!$B$11:$C$24727,2,TRUE),VLOOKUP(A15-2,SP500相关数据!$B$11:$C$24727,2,TRUE))) | C15: =IFERROR(IF(VLOOKUP(A15,SP500相关数据!$B$11:$E$24727,4,TRUE)<>"",VLOOKUP(A15,SP500相关数据!$B$11:$E$24727,4,TRUE),IF(VLOOKUP(A15-1,SP500相关数据!$B$11:$E$24727,4,TRUE)<>"",VLOOKUP(A15-1,SP500相关数据!$B$11:$E$24727,4,TRUE),VLOOKUP(A15-2,SP500相关数据!$B$11:$E$24727,4,TRUE))),"") | D15: =IF(VLOOKUP(A15,高收益利差!$A:$B,2,TRUE)<>"",VLOOKUP(A15,高收益利差!$A:$B,2,TRUE),IF(VLOOKUP(A15-1,高收益利差!$A:$B,2,TRUE)<>"",VLOOKUP(A15-1,高收益利差!$A:$B,2,TRUE),VLOOKUP(A15-2,高收益利差!$A:$B,2,TRUE))) | E15: =IFERROR(VLOOKUP(A15,'10Y2Y'!$A:$B,2,TRUE),"") | F15: =IFERROR(D15-D2,"") | G15: ="" | H15: ="" | I15: =IFERROR(VLOOKUP(A15,'Sahm Rule'!$A:$B,2,TRUE),"") | J15: =IFERROR((B15/B2)^4-1-D15/100,"")
A16: 35531 | B16: =IF(VLOOKUP(A16,SP500相关数据!$B$11:$C$24727,2,TRUE)<>"",VLOOKUP(A16,SP500相关数据!$B$11:$C$24727,2,TRUE),IF(VLOOKUP(A16-1,SP500相关数据!$B$11:$C$24727,2,TRUE)<>"",VLOOKUP(A16-1,SP500相关数据!$B$11:$C$24727,2,TRUE),VLOOKUP(A16-2,SP500相关数据!$B$11:$C$24727,2,TRUE))) | C16: =IFERROR(IF(VLOOKUP(A16,SP500相关数据!$B$11:$E$24727,4,TRUE)<>"",VLOOKUP(A16,SP500相关数据!$B$11:$E$24727,4,TRUE),IF(VLOOKUP(A16-1,SP500相关数据!$B$11:$E$24727,4,TRUE)<>"",VLOOKUP(A16-1,SP500相关数据!$B$11:$E$24727,4,TRUE),VLOOKUP(A16-2,SP500相关数据!$B$11:$E$24727,4,TRUE))),"") | D16: =IF(VLOOKUP(A16,高收益利差!$A:$B,2,TRUE)<>"",VLOOKUP(A16,高收益利差!$A:$B,2,TRUE),IF(VLOOKUP(A16-1,高收益利差!$A:$B,2,TRUE)<>"",VLOOKUP(A16-1,高收益利差!$A:$B,2,TRUE),VLOOKUP(A16-2,高收益利差!$A:$B,2,TRUE))) | E16: =IFERROR(VLOOKUP(A16,'10Y2Y'!$A:$B,2,TRUE),"") | F16: =IFERROR(D16-D3,"") | G16: ="" | H16: ="" | I16: =IFERROR(VLOOKUP(A16,'Sahm Rule'!$A:$B,2,TRUE),"") | J16: =IFERROR((B16/B3)^4-1-D16/100,"")
A17: 35538 | B17: =IF(VLOOKUP(A17,SP500相关数据!$B$11:$C$24727,2,TRUE)<>"",VLOOKUP(A17,SP500相关数据!$B$11:$C$24727,2,TRUE),IF(VLOOKUP(A17-1,SP500相关数据!$B$11:$C$24727,2,TRUE)<>"",VLOOKUP(A17-1,SP500相关数据!$B$11:$C$24727,2,TRUE),VLOOKUP(A17-2,SP500相关数据!$B$11:$C$24727,2,TRUE))) | C17: =IFERROR(IF(VLOOKUP(A17,SP500相关数据!$B$11:$E$24727,4,TRUE)<>"",VLOOKUP(A17,SP500相关数据!$B$11:$E$24727,4,TRUE),IF(VLOOKUP(A17-1,SP500相关数据!$B$11:$E$24727,4,TRUE)<>"",VLOOKUP(A17-1,SP500相关数据!$B$11:$E$24727,4,TRUE),VLOOKUP(A17-2,SP500相关数据!$B$11:$E$24727,4,TRUE))),"") | D17: =IF(VLOOKUP(A17,高收益利差!$A:$B,2,TRUE)<>"",VLOOKUP(A17,高收益利差!$A:$B,2,TRUE),IF(VLOOKUP(A17-1,高收益利差!$A:$B,2,TRUE)<>"",VLOOKUP(A17-1,高收益利差!$A:$B,2,TRUE),VLOOKUP(A17-2,高收益利差!$A:$B,2,TRUE))) | E17: =IFERROR(VLOOKUP(A17,'10Y2Y'!$A:$B,2,TRUE),"") | F17: =IFERROR(D17-D4,"") | G17: ="" | H17: ="" | I17: =IFERROR(VLOOKUP(A17,'Sahm Rule'!$A:$B,2,TRUE),"") | J17: =IFERROR((B17/B4)^4-1-D17/100,"")
A18: 35545 | B18: =IF(VLOOKUP(A18,SP500相关数据!$B$11:$C$24727,2,TRUE)<>"",VLOOKUP(A18,SP500相关数据!$B$11:$C$24727,2,TRUE),IF(VLOOKUP(A18-1,SP500相关数据!$B$11:$C$24727,2,TRUE)<>"",VLOOKUP(A18-1,SP500相关数据!$B$11:$C$24727,2,TRUE),VLOOKUP(A18-2,SP500相关数据!$B$11:$C$24727,2,TRUE))) | C18: =IFERROR(IF(VLOOKUP(A18,SP500相关数据!$B$11:$E$24727,4,TRUE)<>"",VLOOKUP(A18,SP500相关数据!$B$11:$E$24727,4,TRUE),IF(VLOOKUP(A18-1,SP500相关数据!$B$11:$E$24727,4,TRUE)<>"",VLOOKUP(A18-1,SP500相关数据!$B$11:$E$24727,4,TRUE),VLOOKUP(A18-2,SP500相关数据!$B$11:$E$24727,4,TRUE))),"") | D18: =IF(VLOOKUP(A18,高收益利差!$A:$B,2,TRUE)<>"",VLOOKUP(A18,高收益利差!$A:$B,2,TRUE),IF(VLOOKUP(A18-1,高收益利差!$A:$B,2,TRUE)<>"",VLOOKUP(A18-1,高收益利差!$A:$B,2,TRUE),VLOOKUP(A18-2,高收益利差!$A:$B,2,TRUE))) | E18: =IFERROR(VLOOKUP(A18,'10Y2Y'!$A:$B,2,TRUE),"") | F18: =IFERROR(D18-D5,"") | G18: ="" | H18: ="" | I18: =IFERROR(VLOOKUP(A18,'Sahm Rule'!$A:$B,2,TRUE),"") | J18: =IFERROR((B18/B5)^4-1-D18/100,"")
A19: 35552 | B19: =IF(VLOOKUP(A19,SP500相关数据!$B$11:$C$24727,2,TRUE)<>"",VLOOKUP(A19,SP500相关数据!$B$11:$C$24727,2,TRUE),IF(VLOOKUP(A19-1,SP500相关数据!$B$11:$C$24727,2,TRUE)<>"",VLOOKUP(A19-1,SP500相关数据!$B$11:$C$24727,2,TRUE),VLOOKUP(A19-2,SP500相关数据!$B$11:$C$24727,2,TRUE))) | C19: =IFERROR(IF(VLOOKUP(A19,SP500相关数据!$B$11:$E$24727,4,TRUE)<>"",VLOOKUP(A19,SP500相关数据!$B$11:$E$24727,4,TRUE),IF(VLOOKUP(A19-1,SP500相关数据!$B$11:$E$24727,4,TRUE)<>"",VLOOKUP(A19-1,SP500相关数据!$B$11:$E$24727,4,TRUE),VLOOKUP(A19-2,SP500相关数据!$B$11:$E$24727,4,TRUE))),"") | D19: =IF(VLOOKUP(A19,高收益利差!$A:$B,2,TRUE)<>"",VLOOKUP(A19,高收益利差!$A:$B,2,TRUE),IF(VLOOKUP(A19-1,高收益利差!$A:$B,2,TRUE)<>"",VLOOKUP(A19-1,高收益利差!$A:$B,2,TRUE),VLOOKUP(A19-2,高收益利差!$A:$B,2,TRUE))) | E19: =IFERROR(VLOOKUP(A19,'10Y2Y'!$A:$B,2,TRUE),"") | F19: =IFERROR(D19-D6,"") | G19: ="" | H19: ="" | I19: =IFERROR(VLOOKUP(A19,'Sahm Rule'!$A:$B,2,TRUE),"") | J19: =IFERROR((B19/B6)^4-1-D19/100,"")
A20: 35559 | B20: =IF(VLOOKUP(A20,SP500相关数据!$B$11:$C$24727,2,TRUE)<>"",VLOOKUP(A20,SP500相关数据!$B$11:$C$24727,2,TRUE),IF(VLOOKUP(A20-1,SP500相关数据!$B$11:$C$24727,2,TRUE)<>"",VLOOKUP(A20-1,SP500相关数据!$B$11:$C$24727,2,TRUE),VLOOKUP(A20-2,SP500相关数据!$B$11:$C$24727,2,TRUE))) | C20: =IFERROR(IF(VLOOKUP(A20,SP500相关数据!$B$11:$E$24727,4,TRUE)<>"",VLOOKUP(A20,SP500相关数据!$B$11:$E$24727,4,TRUE),IF(VLOOKUP(A20-1,SP500相关数据!$B$11:$E$24727,4,TRUE)<>"",VLOOKUP(A20-1,SP500相关数据!$B$11:$E$24727,4,TRUE),VLOOKUP(A20-2,SP500相关数据!$B$11:$E$24727,4,TRUE))),"") | D20: =IF(VLOOKUP(A20,高收益利差!$A:$B,2,TRUE)<>"",VLOOKUP(A20,高收益利差!$A:$B,2,TRUE),IF(VLOOKUP(A20-1,高收益利差!$A:$B,2,TRUE)<>"",VLOOKUP(A20-1,高收益利差!$A:$B,2,TRUE),VLOOKUP(A20-2,高收益利差!$A:$B,2,TRUE))) | E20: =IFERROR(VLOOKUP(A20,'10Y2Y'!$A:$B,2,TRUE),"") | F20: =IFERROR(D20-D7,"") | G20: ="" | H20: ="" | I20: =IFERROR(VLOOKUP(A20,'Sahm Rule'!$A:$B,2,TRUE),"") | J20: =IFERROR((B20/B7)^4-1-D20/100,"")
A21: 35566 | B21: =IF(VLOOKUP(A21,SP500相关数据!$B$11:$C$24727,2,TRUE)<>"",VLOOKUP(A21,SP500相关数据!$B$11:$C$24727,2,TRUE),IF(VLOOKUP(A21-1,SP500相关数据!$B$11:$C$24727,2,TRUE)<>"",VLOOKUP(A21-1,SP500相关数据!$B$11:$C$24727,2,TRUE),VLOOKUP(A21-2,SP500相关数据!$B$11:$C$24727,2,TRUE))) | C21: =IFERROR(IF(VLOOKUP(A21,SP500相关数据!$B$11:$E$24727,4,TRUE)<>"",VLOOKUP(A21,SP500相关数据!$B$11:$E$24727,4,TRUE),IF(VLOOKUP(A21-1,SP500相关数据!$B$11:$E$24727,4,TRUE)<>"",VLOOKUP(A21-1,SP500相关数据!$B$11:$E$24727,4,TRUE),VLOOKUP(A21-2,SP500相关数据!$B$11:$E$24727,4,TRUE))),"") | D21: =IF(VLOOKUP(A21,高收益利差!$A:$B,2,TRUE)<>"",VLOOKUP(A21,高收益利差!$A:$B,2,TRUE),IF(VLOOKUP(A21-1,高收益利差!$A:$B,2,TRUE)<>"",VLOOKUP(A21-1,高收益利差!$A:$B,2,TRUE),VLOOKUP(A21-2,高收益利差!$A:$B,2,TRUE))) | E21: =IFERROR(VLOOKUP(A21,'10Y2Y'!$A:$B,2,TRUE),"") | F21: =IFERROR(D21-D8,"") | G21: ="" | H21: ="" | I21: =IFERROR(VLOOKUP(A21,'Sahm Rule'!$A:$B,2,TRUE),"") | J21: =IFERROR((B21/B8)^4-1-D21/100,"")
A22: 35573 | B22: =IF(VLOOKUP(A22,SP500相关数据!$B$11:$C$24727,2,TRUE)<>"",VLOOKUP(A22,SP500相关数据!$B$11:$C$24727,2,TRUE),IF(VLOOKUP(A22-1,SP500相关数据!$B$11:$C$24727,2,TRUE)<>"",VLOOKUP(A22-1,SP500相关数据!$B$11:$C$24727,2,TRUE),VLOOKUP(A22-2,SP500相关数据!$B$11:$C$24727,2,TRUE))) | C22: =IFERROR(IF(VLOOKUP(A22,SP500相关数据!$B$11:$E$24727,4,TRUE)<>"",VLOOKUP(A22,SP500相关数据!$B$11:$E$24727,4,TRUE),IF(VLOOKUP(A22-1,SP500相关数据!$B$11:$E$24727,4,TRUE)<>"",VLOOKUP(A22-1,SP500相关数据!$B$11:$E$24727,4,TRUE),VLOOKUP(A22-2,SP500相关数据!$B$11:$E$24727,4,TRUE))),"") | D22: =IF(VLOOKUP(A22,高收益利差!$A:$B,2,TRUE)<>"",VLOOKUP(A22,高收益利差!$A:$B,2,TRUE),IF(VLOOKUP(A22-1,高收益利差!$A:$B,2,TRUE)<>"",VLOOKUP(A22-1,高收益利差!$A:$B,2,TRUE),VLOOKUP(A22-2,高收益利差!$A:$B,2,TRUE))) | E22: =IFERROR(VLOOKUP(A22,'10Y2Y'!$A:$B,2,TRUE),"") | F22: =IFERROR(D22-D9,"") | G22: ="" | H22: ="" | I22: =IFERROR(VLOOKUP(A22,'Sahm Rule'!$A:$B,2,TRUE),"") | J22: =IFERROR((B22/B9)^4-1-D22/100,"")
A23: 35580 | B23: =IF(VLOOKUP(A23,SP500相关数据!$B$11:$C$24727,2,TRUE)<>"",VLOOKUP(A23,SP500相关数据!$B$11:$C$24727,2,TRUE),IF(VLOOKUP(A23-1,SP500相关数据!$B$11:$C$24727,2,TRUE)<>"",VLOOKUP(A23-1,SP500相关数据!$B$11:$C$24727,2,TRUE),VLOOKUP(A23-2,SP500相关数据!$B$11:$C$24727,2,TRUE))) | C23: =IFERROR(IF(VLOOKUP(A23,SP500相关数据!$B$11:$E$24727,4,TRUE)<>"",VLOOKUP(A23,SP500相关数据!$B$11:$E$24727,4,TRUE),IF(VLOOKUP(A23-1,SP500相关数据!$B$11:$E$24727,4,TRUE)<>"",VLOOKUP(A23-1,SP500相关数据!$B$11:$E$24727,4,TRUE),VLOOKUP(A23-2,SP500相关数据!$B$11:$E$24727,4,TRUE))),"") | D23: =IF(VLOOKUP(A23,高收益利差!$A:$B,2,TRUE)<>"",VLOOKUP(A23,高收益利差!$A:$B,2,TRUE),IF(VLOOKUP(A23-1,高收益利差!$A:$B,2,TRUE)<>"",VLOOKUP(A23-1,高收益利差!$A:$B,2,TRUE),VLOOKUP(A23-2,高收益利差!$A:$B,2,TRUE))) | E23: =IFERROR(VLOOKUP(A23,'10Y2Y'!$A:$B,2,TRUE),"") | F23: =IFERROR(D23-D10,"") | G23: ="" | H23: ="" | I23: =IFERROR(VLOOKUP(A23,'Sahm Rule'!$A:$B,2,TRUE),"") | J23: =IFERROR((B23/B10)^4-1-D23/100,"")
A24: 35587 | B24: =IF(VLOOKUP(A24,SP500相关数据!$B$11:$C$24727,2,TRUE)<>"",VLOOKUP(A24,SP500相关数据!$B$11:$C$24727,2,TRUE),IF(VLOOKUP(A24-1,SP500相关数据!$B$11:$C$24727,2,TRUE)<>"",VLOOKUP(A24-1,SP500相关数据!$B$11:$C$24727,2,TRUE),VLOOKUP(A24-2,SP500相关数据!$B$11:$C$24727,2,TRUE))) | C24: =IFERROR(IF(VLOOKUP(A24,SP500相关数据!$B$11:$E$24727,4,TRUE)<>"",VLOOKUP(A24,SP500相关数据!$B$11:$E$24727,4,TRUE),IF(VLOOKUP(A24-1,SP500相关数据!$B$11:$E$24727,4,TRUE)<>"",VLOOKUP(A24-1,SP500相关数据!$B$11:$E$24727,4,TRUE),VLOOKUP(A24-2,SP500相关数据!$B$11:$E$24727,4,TRUE))),"") | D24: =IF(VLOOKUP(A24,高收益利差!$A:$B,2,TRUE)<>"",VLOOKUP(A24,高收益利差!$A:$B,2,TRUE),IF(VLOOKUP(A24-1,高收益利差!$A:$B,2,TRUE)<>"",VLOOKUP(A24-1,高收益利差!$A:$B,2,TRUE),VLOOKUP(A24-2,高收益利差!$A:$B,2,TRUE))) | E24: =IFERROR(VLOOKUP(A24,'10Y2Y'!$A:$B,2,TRUE),"") | F24: =IFERROR(D24-D11,"") | G24: ="" | H24: ="" | I24: =IFERROR(VLOOKUP(A24,'Sahm Rule'!$A:$B,2,TRUE),"") | J24: =IFERROR((B24/B11)^4-1-D24/100,"")
A25: 35594 | B25: =IF(VLOOKUP(A25,SP500相关数据!$B$11:$C$24727,2,TRUE)<>"",VLOOKUP(A25,SP500相关数据!$B$11:$C$24727,2,TRUE),IF(VLOOKUP(A25-1,SP500相关数据!$B$11:$C$24727,2,TRUE)<>"",VLOOKUP(A25-1,SP500相关数据!$B$11:$C$24727,2,TRUE),VLOOKUP(A25-2,SP500相关数据!$B$11:$C$24727,2,TRUE))) | C25: =IFERROR(IF(VLOOKUP(A25,SP500相关数据!$B$11:$E$24727,4,TRUE)<>"",VLOOKUP(A25,SP500相关数据!$B$11:$E$24727,4,TRUE),IF(VLOOKUP(A25-1,SP500相关数据!$B$11:$E$24727,4,TRUE)<>"",VLOOKUP(A25-1,SP500相关数据!$B$11:$E$24727,4,TRUE),VLOOKUP(A25-2,SP500相关数据!$B$11:$E$24727,4,TRUE))),"") | D25: =IF(VLOOKUP(A25,高收益利差!$A:$B,2,TRUE)<>"",VLOOKUP(A25,高收益利差!$A:$B,2,TRUE),IF(VLOOKUP(A25-1,高收益利差!$A:$B,2,TRUE)<>"",VLOOKUP(A25-1,高收益利差!$A:$B,2,TRUE),VLOOKUP(A25-2,高收益利差!$A:$B,2,TRUE))) | E25: =IFERROR(VLOOKUP(A25,'10Y2Y'!$A:$B,2,TRUE),"") | F25: =IFERROR(D25-D12,"") | G25: ="" | H25: ="" | I25: =IFERROR(VLOOKUP(A25,'Sahm Rule'!$A:$B,2,TRUE),"") | J25: =IFERROR((B25/B12)^4-1-D25/100,"")
A26: 35601 | B26: =IF(VLOOKUP(A26,SP500相关数据!$B$11:$C$24727,2,TRUE)<>"",VLOOKUP(A26,SP500相关数据!$B$11:$C$24727,2,TRUE),IF(VLOOKUP(A26-1,SP500相关数据!$B$11:$C$24727,2,TRUE)<>"",VLOOKUP(A26-1,SP500相关数据!$B$11:$C$24727,2,TRUE),VLOOKUP(A26-2,SP500相关数据!$B$11:$C$24727,2,TRUE))) | C26: =IFERROR(IF(VLOOKUP(A26,SP500相关数据!$B$11:$E$24727,4,TRUE)<>"",VLOOKUP(A26,SP500相关数据!$B$11:$E$24727,4,TRUE),IF(VLOOKUP(A26-1,SP500相关数据!$B$11:$E$24727,4,TRUE)<>"",VLOOKUP(A26-1,SP500相关数据!$B$11:$E$24727,4,TRUE),VLOOKUP(A26-2,SP500相关数据!$B$11:$E$24727,4,TRUE))),"") | D26: =IF(VLOOKUP(A26,高收益利差!$A:$B,2,TRUE)<>"",VLOOKUP(A26,高收益利差!$A:$B,2,TRUE),IF(VLOOKUP(A26-1,高收益利差!$A:$B,2,TRUE)<>"",VLOOKUP(A26-1,高收益利差!$A:$B,2,TRUE),VLOOKUP(A26-2,高收益利差!$A:$B,2,TRUE))) | E26: =IFERROR(VLOOKUP(A26,'10Y2Y'!$A:$B,2,TRUE),"") | F26: =IFERROR(D26-D13,"") | G26: ="" | H26: ="" | I26: =IFERROR(VLOOKUP(A26,'Sahm Rule'!$A:$B,2,TRUE),"") | J26: =IFERROR((B26/B13)^4-1-D26/100,"")
A27: 35608 | B27: =IF(VLOOKUP(A27,SP500相关数据!$B$11:$C$24727,2,TRUE)<>"",VLOOKUP(A27,SP500相关数据!$B$11:$C$24727,2,TRUE),IF(VLOOKUP(A27-1,SP500相关数据!$B$11:$C$24727,2,TRUE)<>"",VLOOKUP(A27-1,SP500相关数据!$B$11:$C$24727,2,TRUE),VLOOKUP(A27-2,SP500相关数据!$B$11:$C$24727,2,TRUE))) | C27: =IFERROR(IF(VLOOKUP(A27,SP500相关数据!$B$11:$E$24727,4,TRUE)<>"",VLOOKUP(A27,SP500相关数据!$B$11:$E$24727,4,TRUE),IF(VLOOKUP(A27-1,SP500相关数据!$B$11:$E$24727,4,TRUE)<>"",VLOOKUP(A27-1,SP500相关数据!$B$11:$E$24727,4,TRUE),VLOOKUP(A27-2,SP500相关数据!$B$11:$E$24727,4,TRUE))),"") | D27: =IF(VLOOKUP(A27,高收益利差!$A:$B,2,TRUE)<>"",VLOOKUP(A27,高收益利差!$A:$B,2,TRUE),IF(VLOOKUP(A27-1,高收益利差!$A:$B,2,TRUE)<>"",VLOOKUP(A27-1,高收益利差!$A:$B,2,TRUE),VLOOKUP(A27-2,高收益利差!$A:$B,2,TRUE))) | E27: =IFERROR(VLOOKUP(A27,'10Y2Y'!$A:$B,2,TRUE),"") | F27: =IFERROR(D27-D14,"") | G27: ="" | H27: ="" | I27: =IFERROR(VLOOKUP(A27,'Sahm Rule'!$A:$B,2,TRUE),"") | J27: =IFERROR((B27/B14)^4-1-D27/100,"")
A28: 35615 | B28: =IF(VLOOKUP(A28,SP500相关数据!$B$11:$C$24727,2,TRUE)<>"",VLOOKUP(A28,SP500相关数据!$B$11:$C$24727,2,TRUE),IF(VLOOKUP(A28-1,SP500相关数据!$B$11:$C$24727,2,TRUE)<>"",VLOOKUP(A28-1,SP500相关数据!$B$11:$C$24727,2,TRUE),VLOOKUP(A28-2,SP500相关数据!$B$11:$C$24727,2,TRUE))) | C28: =IFERROR(IF(VLOOKUP(A28,SP500相关数据!$B$11:$E$24727,4,TRUE)<>"",VLOOKUP(A28,SP500相关数据!$B$11:$E$24727,4,TRUE),IF(VLOOKUP(A28-1,SP500相关数据!$B$11:$E$24727,4,TRUE)<>"",VLOOKUP(A28-1,SP500相关数据!$B$11:$E$24727,4,TRUE),VLOOKUP(A28-2,SP500相关数据!$B$11:$E$24727,4,TRUE))),"") | D28: =IF(VLOOKUP(A28,高收益利差!$A:$B,2,TRUE)<>"",VLOOKUP(A28,高收益利差!$A:$B,2,TRUE),IF(VLOOKUP(A28-1,高收益利差!$A:$B,2,TRUE)<>"",VLOOKUP(A28-1,高收益利差!$A:$B,2,TRUE),VLOOKUP(A28-2,高收益利差!$A:$B,2,TRUE))) | E28: =IFERROR(VLOOKUP(A28,'10Y2Y'!$A:$B,2,TRUE),"") | F28: =IFERROR(D28-D15,"") | G28: ="" | H28: ="" | I28: =IFERROR(VLOOKUP(A28,'Sahm Rule'!$A:$B,2,TRUE),"") | J28: =IFERROR((B28/B15)^4-1-D28/100,"")
A29: 35622 | B29: =IF(VLOOKUP(A29,SP500相关数据!$B$11:$C$24727,2,TRUE)<>"",VLOOKUP(A29,SP500相关数据!$B$11:$C$24727,2,TRUE),IF(VLOOKUP(A29-1,SP500相关数据!$B$11:$C$24727,2,TRUE)<>"",VLOOKUP(A29-1,SP500相关数据!$B$11:$C$24727,2,TRUE),VLOOKUP(A29-2,SP500相关数据!$B$11:$C$24727,2,TRUE))) | C29: =IFERROR(IF(VLOOKUP(A29,SP500相关数据!$B$11:$E$24727,4,TRUE)<>"",VLOOKUP(A29,SP500相关数据!$B$11:$E$24727,4,TRUE),IF(VLOOKUP(A29-1,SP500相关数据!$B$11:$E$24727,4,TRUE)<>"",VLOOKUP(A29-1,SP500相关数据!$B$11:$E$24727,4,TRUE),VLOOKUP(A29-2,SP500相关数据!$B$11:$E$24727,4,TRUE))),"") | D29: =IF(VLOOKUP(A29,高收益利差!$A:$B,2,TRUE)<>"",VLOOKUP(A29,高收益利差!$A:$B,2,TRUE),IF(VLOOKUP(A29-1,高收益利差!$A:$B,2,TRUE)<>"",VLOOKUP(A29-1,高收益利差!$A:$B,2,TRUE),VLOOKUP(A29-2,高收益利差!$A:$B,2,TRUE))) | E29: =IFERROR(VLOOKUP(A29,'10Y2Y'!$A:$B,2,TRUE),"") | F29: =IFERROR(D29-D16,"") | G29: ="" | H29: ="" | I29: =IFERROR(VLOOKUP(A29,'Sahm Rule'!$A:$B,2,TRUE),"") | J29: =IFERROR((B29/B16)^4-1-D29/100,"")
A30: 35629 | B30: =IF(VLOOKUP(A30,SP500相关数据!$B$11:$C$24727,2,TRUE)<>"",VLOOKUP(A30,SP500相关数据!$B$11:$C$24727,2,TRUE),IF(VLOOKUP(A30-1,SP500相关数据!$B$11:$C$24727,2,TRUE)<>"",VLOOKUP(A30-1,SP500相关数据!$B$11:$C$24727,2,TRUE),VLOOKUP(A30-2,SP500相关数据!$B$11:$C$24727,2,TRUE))) | C30: =IFERROR(IF(VLOOKUP(A30,SP500相关数据!$B$11:$E$24727,4,TRUE)<>"",VLOOKUP(A30,SP500相关数据!$B$11:$E$24727,4,TRUE),IF(VLOOKUP(A30-1,SP500相关数据!$B$11:$E$24727,4,TRUE)<>"",VLOOKUP(A30-1,SP500相关数据!$B$11:$E$24727,4,TRUE),VLOOKUP(A30-2,SP500相关数据!$B$11:$E$24727,4,TRUE))),"") | D30: =IF(VLOOKUP(A30,高收益利差!$A:$B,2,TRUE)<>"",VLOOKUP(A30,高收益利差!$A:$B,2,TRUE),IF(VLOOKUP(A30-1,高收益利差!$A:$B,2,TRUE)<>"",VLOOKUP(A30-1,高收益利差!$A:$B,2,TRUE),VLOOKUP(A30-2,高收益利差!$A:$B,2,TRUE))) | E30: =IFERROR(VLOOKUP(A30,'10Y2Y'!$A:$B,2,TRUE),"") | F30: =IFERROR(D30-D17,"") | G30: ="" | H30: ="" | I30: =IFERROR(VLOOKUP(A30,'Sahm Rule'!$A:$B,2,TRUE),"") | J30: =IFERROR((B30/B17)^4-1-D30/100,"")
A31: 35636 | B31: =IF(VLOOKUP(A31,SP500相关数据!$B$11:$C$24727,2,TRUE)<>"",VLOOKUP(A31,SP500相关数据!$B$11:$C$24727,2,TRUE),IF(VLOOKUP(A31-1,SP500相关数据!$B$11:$C$24727,2,TRUE)<>"",VLOOKUP(A31-1,SP500相关数据!$B$11:$C$24727,2,TRUE),VLOOKUP(A31-2,SP500相关数据!$B$11:$C$24727,2,TRUE))) | C31: =IFERROR(IF(VLOOKUP(A31,SP500相关数据!$B$11:$E$24727,4,TRUE)<>"",VLOOKUP(A31,SP500相关数据!$B$11:$E$24727,4,TRUE),IF(VLOOKUP(A31-1,SP500相关数据!$B$11:$E$24727,4,TRUE)<>"",VLOOKUP(A31-1,SP500相关数据!$B$11:$E$24727,4,TRUE),VLOOKUP(A31-2,SP500相关数据!$B$11:$E$24727,4,TRUE))),"") | D31: =IF(VLOOKUP(A31,高收益利差!$A:$B,2,TRUE)<>"",VLOOKUP(A31,高收益利差!$A:$B,2,TRUE),IF(VLOOKUP(A31-1,高收益利差!$A:$B,2,TRUE)<>"",VLOOKUP(A31-1,高收益利差!$A:$B,2,TRUE),VLOOKUP(A31-2,高收益利差!$A:$B,2,TRUE))) | E31: =IFERROR(VLOOKUP(A31,'10Y2Y'!$A:$B,2,TRUE),"") | F31: =IFERROR(D31-D18,"") | G31: ="" | H31: ="" | I31: =IFERROR(VLOOKUP(A31,'Sahm Rule'!$A:$B,2,TRUE),"") | J31: =IFERROR((B31/B18)^4-1-D31/100,"")
A32: 35643 | B32: =IF(VLOOKUP(A32,SP500相关数据!$B$11:$C$24727,2,TRUE)<>"",VLOOKUP(A32,SP500相关数据!$B$11:$C$24727,2,TRUE),IF(VLOOKUP(A32-1,SP500相关数据!$B$11:$C$24727,2,TRUE)<>"",VLOOKUP(A32-1,SP500相关数据!$B$11:$C$24727,2,TRUE),VLOOKUP(A32-2,SP500相关数据!$B$11:$C$24727,2,TRUE))) | C32: =IFERROR(IF(VLOOKUP(A32,SP500相关数据!$B$11:$E$24727,4,TRUE)<>"",VLOOKUP(A32,SP500相关数据!$B$11:$E$24727,4,TRUE),IF(VLOOKUP(A32-1,SP500相关数据!$B$11:$E$24727,4,TRUE)<>"",VLOOKUP(A32-1,SP500相关数据!$B$11:$E$24727,4,TRUE),VLOOKUP(A32-2,SP500相关数据!$B$11:$E$24727,4,TRUE))),"") | D32: =IF(VLOOKUP(A32,高收益利差!$A:$B,2,TRUE)<>"",VLOOKUP(A32,高收益利差!$A:$B,2,TRUE),IF(VLOOKUP(A32-1,高收益利差!$A:$B,2,TRUE)<>"",VLOOKUP(A32-1,高收益利差!$A:$B,2,TRUE),VLOOKUP(A32-2,高收益利差!$A:$B,2,TRUE))) | E32: =IFERROR(VLOOKUP(A32,'10Y2Y'!$A:$B,2,TRUE),"") | F32: =IFERROR(D32-D19,"") | G32: ="" | H32: ="" | I32: =IFERROR(VLOOKUP(A32,'Sahm Rule'!$A:$B,2,TRUE),"") | J32: =IFERROR((B32/B19)^4-1-D32/100,"")
A33: 35650 | B33: =IF(VLOOKUP(A33,SP500相关数据!$B$11:$C$24727,2,TRUE)<>"",VLOOKUP(A33,SP500相关数据!$B$11:$C$24727,2,TRUE),IF(VLOOKUP(A33-1,SP500相关数据!$B$11:$C$24727,2,TRUE)<>"",VLOOKUP(A33-1,SP500相关数据!$B$11:$C$24727,2,TRUE),VLOOKUP(A33-2,SP500相关数据!$B$11:$C$24727,2,TRUE))) | C33: =IFERROR(IF(VLOOKUP(A33,SP500相关数据!$B$11:$E$24727,4,TRUE)<>"",VLOOKUP(A33,SP500相关数据!$B$11:$E$24727,4,TRUE),IF(VLOOKUP(A33-1,SP500相关数据!$B$11:$E$24727,4,TRUE)<>"",VLOOKUP(A33-1,SP500相关数据!$B$11:$E$24727,4,TRUE),VLOOKUP(A33-2,SP500相关数据!$B$11:$E$24727,4,TRUE))),"") | D33: =IF(VLOOKUP(A33,高收益利差!$A:$B,2,TRUE)<>"",VLOOKUP(A33,高收益利差!$A:$B,2,TRUE),IF(VLOOKUP(A33-1,高收益利差!$A:$B,2,TRUE)<>"",VLOOKUP(A33-1,高收益利差!$A:$B,2,TRUE),VLOOKUP(A33-2,高收益利差!$A:$B,2,TRUE))) | E33: =IFERROR(VLOOKUP(A33,'10Y2Y'!$A:$B,2,TRUE),"") | F33: =IFERROR(D33-D20,"") | G33: ="" | H33: ="" | I33: =IFERROR(VLOOKUP(A33,'Sahm Rule'!$A:$B,2,TRUE),"") | J33: =IFERROR((B33/B20)^4-1-D33/100,"")
A34: 35657 | B34: =IF(VLOOKUP(A34,SP500相关数据!$B$11:$C$24727,2,TRUE)<>"",VLOOKUP(A34,SP500相关数据!$B$11:$C$24727,2,TRUE),IF(VLOOKUP(A34-1,SP500相关数据!$B$11:$C$24727,2,TRUE)<>"",VLOOKUP(A34-1,SP500相关数据!$B$11:$C$24727,2,TRUE),VLOOKUP(A34-2,SP500相关数据!$B$11:$C$24727,2,TRUE))) | C34: =IFERROR(IF(VLOOKUP(A34,SP500相关数据!$B$11:$E$24727,4,TRUE)<>"",VLOOKUP(A34,SP500相关数据!$B$11:$E$24727,4,TRUE),IF(VLOOKUP(A34-1,SP500相关数据!$B$11:$E$24727,4,TRUE)<>"",VLOOKUP(A34-1,SP500相关数据!$B$11:$E$24727,4,TRUE),VLOOKUP(A34-2,SP500相关数据!$B$11:$E$24727,4,TRUE))),"") | D34: =IF(VLOOKUP(A34,高收益利差!$A:$B,2,TRUE)<>"",VLOOKUP(A34,高收益利差!$A:$B,2,TRUE),IF(VLOOKUP(A34-1,高收益利差!$A:$B,2,TRUE)<>"",VLOOKUP(A34-1,高收益利差!$A:$B,2,TRUE),VLOOKUP(A34-2,高收益利差!$A:$B,2,TRUE))) | E34: =IFERROR(VLOOKUP(A34,'10Y2Y'!$A:$B,2,TRUE),"") | F34: =IFERROR(D34-D21,"") | G34: ="" | H34: ="" | I34: =IFERROR(VLOOKUP(A34,'Sahm Rule'!$A:$B,2,TRUE),"") | J34: =IFERROR((B34/B21)^4-1-D34/100,"")
A35: 35664 | B35: =IF(VLOOKUP(A35,SP500相关数据!$B$11:$C$24727,2,TRUE)<>"",VLOOKUP(A35,SP500相关数据!$B$11:$C$24727,2,TRUE),IF(VLOOKUP(A35-1,SP500相关数据!$B$11:$C$24727,2,TRUE)<>"",VLOOKUP(A35-1,SP500相关数据!$B$11:$C$24727,2,TRUE),VLOOKUP(A35-2,SP500相关数据!$B$11:$C$24727,2,TRUE))) | C35: =IFERROR(IF(VLOOKUP(A35,SP500相关数据!$B$11:$E$24727,4,TRUE)<>"",VLOOKUP(A35,SP500相关数据!$B$11:$E$24727,4,TRUE),IF(VLOOKUP(A35-1,SP500相关数据!$B$11:$E$24727,4,TRUE)<>"",VLOOKUP(A35-1,SP500相关数据!$B$11:$E$24727,4,TRUE),VLOOKUP(A35-2,SP500相关数据!$B$11:$E$24727,4,TRUE))),"") | D35: =IF(VLOOKUP(A35,高收益利差!$A:$B,2,TRUE)<>"",VLOOKUP(A35,高收益利差!$A:$B,2,TRUE),IF(VLOOKUP(A35-1,高收益利差!$A:$B,2,TRUE)<>"",VLOOKUP(A35-1,高收益利差!$A:$B,2,TRUE),VLOOKUP(A35-2,高收益利差!$A:$B,2,TRUE))) | E35: =IFERROR(VLOOKUP(A35,'10Y2Y'!$A:$B,2,TRUE),"") | F35: =IFERROR(D35-D22,"") | G35: ="" | H35: ="" | I35: =IFERROR(VLOOKUP(A35,'Sahm Rule'!$A:$B,2,TRUE),"") | J35: =IFERROR((B35/B22)^4-1-D35/100,"")
A36: 35671 | B36: =IF(VLOOKUP(A36,SP500相关数据!$B$11:$C$24727,2,TRUE)<>"",VLOOKUP(A36,SP500相关数据!$B$11:$C$24727,2,TRUE),IF(VLOOKUP(A36-1,SP500相关数据!$B$11:$C$24727,2,TRUE)<>"",VLOOKUP(A36-1,SP500相关数据!$B$11:$C$24727,2,TRUE),VLOOKUP(A36-2,SP500相关数据!$B$11:$C$24727,2,TRUE))) | C36: =IFERROR(IF(VLOOKUP(A36,SP500相关数据!$B$11:$E$24727,4,TRUE)<>"",VLOOKUP(A36,SP500相关数据!$B$11:$E$24727,4,TRUE),IF(VLOOKUP(A36-1,SP500相关数据!$B$11:$E$24727,4,TRUE)<>"",VLOOKUP(A36-1,SP500相关数据!$B$11:$E$24727,4,TRUE),VLOOKUP(A36-2,SP500相关数据!$B$11:$E$24727,4,TRUE))),"") | D36: =IF(VLOOKUP(A36,高收益利差!$A:$B,2,TRUE)<>"",VLOOKUP(A36,高收益利差!$A:$B,2,TRUE),IF(VLOOKUP(A36-1,高收益利差!$A:$B,2,TRUE)<>"",VLOOKUP(A36-1,高收益利差!$A:$B,2,TRUE),VLOOKUP(A36-2,高收益利差!$A:$B,2,TRUE))) | E36: =IFERROR(VLOOKUP(A36,'10Y2Y'!$A:$B,2,TRUE),"") | F36: =IFERROR(D36-D23,"") | G36: ="" | H36: ="" | I36: =IFERROR(VLOOKUP(A36,'Sahm Rule'!$A:$B,2,TRUE),"") | J36: =IFERROR((B36/B23)^4-1-D36/100,"")
A37: 35678 | B37: =IF(VLOOKUP(A37,SP500相关数据!$B$11:$C$24727,2,TRUE)<>"",VLOOKUP(A37,SP500相关数据!$B$11:$C$24727,2,TRUE),IF(VLOOKUP(A37-1,SP500相关数据!$B$11:$C$24727,2,TRUE)<>"",VLOOKUP(A37-1,SP500相关数据!$B$11:$C$24727,2,TRUE),VLOOKUP(A37-2,SP500相关数据!$B$11:$C$24727,2,TRUE))) | C37: =IFERROR(IF(VLOOKUP(A37,SP500相关数据!$B$11:$E$24727,4,TRUE)<>"",VLOOKUP(A37,SP500相关数据!$B$11:$E$24727,4,TRUE),IF(VLOOKUP(A37-1,SP500相关数据!$B$11:$E$24727,4,TRUE)<>"",VLOOKUP(A37-1,SP500相关数据!$B$11:$E$24727,4,TRUE),VLOOKUP(A37-2,SP500相关数据!$B$11:$E$24727,4,TRUE))),"") | D37: =IF(VLOOKUP(A37,高收益利差!$A:$B,2,TRUE)<>"",VLOOKUP(A37,高收益利差!$A:$B,2,TRUE),IF(VLOOKUP(A37-1,高收益利差!$A:$B,2,TRUE)<>"",VLOOKUP(A37-1,高收益利差!$A:$B,2,TRUE),VLOOKUP(A37-2,高收益利差!$A:$B,2,TRUE))) | E37: =IFERROR(VLOOKUP(A37,'10Y2Y'!$A:$B,2,TRUE),"") | F37: =IFERROR(D37-D24,"") | G37: ="" | H37: ="" | I37: =IFERROR(VLOOKUP(A37,'Sahm Rule'!$A:$B,2,TRUE),"") | J37: =IFERROR((B37/B24)^4-1-D37/100,"")
A38: 35685 | B38: =IF(VLOOKUP(A38,SP500相关数据!$B$11:$C$24727,2,TRUE)<>"",VLOOKUP(A38,SP500相关数据!$B$11:$C$24727,2,TRUE),IF(VLOOKUP(A38-1,SP500相关数据!$B$11:$C$24727,2,TRUE)<>"",VLOOKUP(A38-1,SP500相关数据!$B$11:$C$24727,2,TRUE),VLOOKUP(A38-2,SP500相关数据!$B$11:$C$24727,2,TRUE))) | C38: =IFERROR(IF(VLOOKUP(A38,SP500相关数据!$B$11:$E$24727,4,TRUE)<>"",VLOOKUP(A38,SP500相关数据!$B$11:$E$24727,4,TRUE),IF(VLOOKUP(A38-1,SP500相关数据!$B$11:$E$24727,4,TRUE)<>"",VLOOKUP(A38-1,SP500相关数据!$B$11:$E$24727,4,TRUE),VLOOKUP(A38-2,SP500相关数据!$B$11:$E$24727,4,TRUE))),"") | D38: =IF(VLOOKUP(A38,高收益利差!$A:$B,2,TRUE)<>"",VLOOKUP(A38,高收益利差!$A:$B,2,TRUE),IF(VLOOKUP(A38-1,高收益利差!$A:$B,2,TRUE)<>"",VLOOKUP(A38-1,高收益利差!$A:$B,2,TRUE),VLOOKUP(A38-2,高收益利差!$A:$B,2,TRUE))) | E38: =IFERROR(VLOOKUP(A38,'10Y2Y'!$A:$B,2,TRUE),"") | F38: =IFERROR(D38-D25,"") | G38: ="" | H38: ="" | I38: =IFERROR(VLOOKUP(A38,'Sahm Rule'!$A:$B,2,TRUE),"") | J38: =IFERROR((B38/B25)^4-1-D38/100,"")
A39: 35692 | B39: =IF(VLOOKUP(A39,SP500相关数据!$B$11:$C$24727,2,TRUE)<>"",VLOOKUP(A39,SP500相关数据!$B$11:$C$24727,2,TRUE),IF(VLOOKUP(A39-1,SP500相关数据!$B$11:$C$24727,2,TRUE)<>"",VLOOKUP(A39-1,SP500相关数据!$B$11:$C$24727,2,TRUE),VLOOKUP(A39-2,SP500相关数据!$B$11:$C$24727,2,TRUE))) | C39: =IFERROR(IF(VLOOKUP(A39,SP500相关数据!$B$11:$E$24727,4,TRUE)<>"",VLOOKUP(A39,SP500相关数据!$B$11:$E$24727,4,TRUE),IF(VLOOKUP(A39-1,SP500相关数据!$B$11:$E$24727,4,TRUE)<>"",VLOOKUP(A39-1,SP500相关数据!$B$11:$E$24727,4,TRUE),VLOOKUP(A39-2,SP500相关数据!$B$11:$E$24727,4,TRUE))),"") | D39: =IF(VLOOKUP(A39,高收益利差!$A:$B,2,TRUE)<>"",VLOOKUP(A39,高收益利差!$A:$B,2,TRUE),IF(VLOOKUP(A39-1,高收益利差!$A:$B,2,TRUE)<>"",VLOOKUP(A39-1,高收益利差!$A:$B,2,TRUE),VLOOKUP(A39-2,高收益利差!$A:$B,2,TRUE))) | E39: =IFERROR(VLOOKUP(A39,'10Y2Y'!$A:$B,2,TRUE),"") | F39: =IFERROR(D39-D26,"") | G39: ="" | H39: ="" | I39: =IFERROR(VLOOKUP(A39,'Sahm Rule'!$A:$B,2,TRUE),"") | J39: =IFERROR((B39/B26)^4-1-D39/100,"")
A40: 35699 | B40: =IF(VLOOKUP(A40,SP500相关数据!$B$11:$C$24727,2,TRUE)<>"",VLOOKUP(A40,SP500相关数据!$B$11:$C$24727,2,TRUE),IF(VLOOKUP(A40-1,SP500相关数据!$B$11:$C$24727,2,TRUE)<>"",VLOOKUP(A40-1,SP500相关数据!$B$11:$C$24727,2,TRUE),VLOOKUP(A40-2,SP500相关数据!$B$11:$C$24727,2,TRUE))) | C40: =IFERROR(IF(VLOOKUP(A40,SP500相关数据!$B$11:$E$24727,4,TRUE)<>"",VLOOKUP(A40,SP500相关数据!$B$11:$E$24727,4,TRUE),IF(VLOOKUP(A40-1,SP500相关数据!$B$11:$E$24727,4,TRUE)<>"",VLOOKUP(A40-1,SP500相关数据!$B$11:$E$24727,4,TRUE),VLOOKUP(A40-2,SP500相关数据!$B$11:$E$24727,4,TRUE))),"") | D40: =IF(VLOOKUP(A40,高收益利差!$A:$B,2,TRUE)<>"",VLOOKUP(A40,高收益利差!$A:$B,2,TRUE),IF(VLOOKUP(A40-1,高收益利差!$A:$B,2,TRUE)<>"",VLOOKUP(A40-1,高收益利差!$A:$B,2,TRUE),VLOOKUP(A40-2,高收益利差!$A:$B,2,TRUE))) | E40: =IFERROR(VLOOKUP(A40,'10Y2Y'!$A:$B,2,TRUE),"") | F40: =IFERROR(D40-D27,"") | G40: ="" | H40: ="" | I40: =IFERROR(VLOOKUP(A40,'Sahm Rule'!$A:$B,2,TRUE),"") | J40: =IFERROR((B40/B27)^4-1-D40/100,"")
A41: 35706 | B41: =IF(VLOOKUP(A41,SP500相关数据!$B$11:$C$24727,2,TRUE)<>"",VLOOKUP(A41,SP500相关数据!$B$11:$C$24727,2,TRUE),IF(VLOOKUP(A41-1,SP500相关数据!$B$11:$C$24727,2,TRUE)<>"",VLOOKUP(A41-1,SP500相关数据!$B$11:$C$24727,2,TRUE),VLOOKUP(A41-2,SP500相关数据!$B$11:$C$24727,2,TRUE))) | C41: =IFERROR(IF(VLOOKUP(A41,SP500相关数据!$B$11:$E$24727,4,TRUE)<>"",VLOOKUP(A41,SP500相关数据!$B$11:$E$24727,4,TRUE),IF(VLOOKUP(A41-1,SP500相关数据!$B$11:$E$24727,4,TRUE)<>"",VLOOKUP(A41-1,SP500相关数据!$B$11:$E$24727,4,TRUE),VLOOKUP(A41-2,SP500相关数据!$B$11:$E$24727,4,TRUE))),"") | D41: =IF(VLOOKUP(A41,高收益利差!$A:$B,2,TRUE)<>"",VLOOKUP(A41,高收益利差!$A:$B,2,TRUE),IF(VLOOKUP(A41-1,高收益利差!$A:$B,2,TRUE)<>"",VLOOKUP(A41-1,高收益利差!$A:$B,2,TRUE),VLOOKUP(A41-2,高收益利差!$A:$B,2,TRUE))) | E41: =IFERROR(VLOOKUP(A41,'10Y2Y'!$A:$B,2,TRUE),"") | F41: =IFERROR(D41-D28,"") | G41: ="" | H41: ="" | I41: =IFERROR(VLOOKUP(A41,'Sahm Rule'!$A:$B,2,TRUE),"") | J41: =IFERROR((B41/B28)^4-1-D41/100,"")
A42: 35713 | B42: =IF(VLOOKUP(A42,SP500相关数据!$B$11:$C$24727,2,TRUE)<>"",VLOOKUP(A42,SP500相关数据!$B$11:$C$24727,2,TRUE),IF(VLOOKUP(A42-1,SP500相关数据!$B$11:$C$24727,2,TRUE)<>"",VLOOKUP(A42-1,SP500相关数据!$B$11:$C$24727,2,TRUE),VLOOKUP(A42-2,SP500相关数据!$B$11:$C$24727,2,TRUE))) | C42: =IFERROR(IF(VLOOKUP(A42,SP500相关数据!$B$11:$E$24727,4,TRUE)<>"",VLOOKUP(A42,SP500相关数据!$B$11:$E$24727,4,TRUE),IF(VLOOKUP(A42-1,SP500相关数据!$B$11:$E$24727,4,TRUE)<>"",VLOOKUP(A42-1,SP500相关数据!$B$11:$E$24727,4,TRUE),VLOOKUP(A42-2,SP500相关数据!$B$11:$E$24727,4,TRUE))),"") | D42: =IF(VLOOKUP(A42,高收益利差!$A:$B,2,TRUE)<>"",VLOOKUP(A42,高收益利差!$A:$B,2,TRUE),IF(VLOOKUP(A42-1,高收益利差!$A:$B,2,TRUE)<>"",VLOOKUP(A42-1,高收益利差!$A:$B,2,TRUE),VLOOKUP(A42-2,高收益利差!$A:$B,2,TRUE))) | E42: =IFERROR(VLOOKUP(A42,'10Y2Y'!$A:$B,2,TRUE),"") | F42: =IFERROR(D42-D29,"") | G42: =IFERROR(B42/AVERAGE(B3:B42)-1,"") | H42: ="" | I42: =IFERROR(VLOOKUP(A42,'Sahm Rule'!$A:$B,2,TRUE),"") | J42: =IFERROR((B42/B29)^4-1-D42/100,"")
A43: 35720 | B43: =IF(VLOOKUP(A43,SP500相关数据!$B$11:$C$24727,2,TRUE)<>"",VLOOKUP(A43,SP500相关数据!$B$11:$C$24727,2,TRUE),IF(VLOOKUP(A43-1,SP500相关数据!$B$11:$C$24727,2,TRUE)<>"",VLOOKUP(A43-1,SP500相关数据!$B$11:$C$24727,2,TRUE),VLOOKUP(A43-2,SP500相关数据!$B$11:$C$24727,2,TRUE))) | C43: =IFERROR(IF(VLOOKUP(A43,SP500相关数据!$B$11:$E$24727,4,TRUE)<>"",VLOOKUP(A43,SP500相关数据!$B$11:$E$24727,4,TRUE),IF(VLOOKUP(A43-1,SP500相关数据!$B$11:$E$24727,4,TRUE)<>"",VLOOKUP(A43-1,SP500相关数据!$B$11:$E$24727,4,TRUE),VLOOKUP(A43-2,SP500相关数据!$B$11:$E$24727,4,TRUE))),"") | D43: =IF(VLOOKUP(A43,高收益利差!$A:$B,2,TRUE)<>"",VLOOKUP(A43,高收益利差!$A:$B,2,TRUE),IF(VLOOKUP(A43-1,高收益利差!$A:$B,2,TRUE)<>"",VLOOKUP(A43-1,高收益利差!$A:$B,2,TRUE),VLOOKUP(A43-2,高收益利差!$A:$B,2,TRUE))) | E43: =IFERROR(VLOOKUP(A43,'10Y2Y'!$A:$B,2,TRUE),"") | F43: =IFERROR(D43-D30,"") | G43: =IFERROR(B43/AVERAGE(B4:B43)-1,"") | H43: ="" | I43: =IFERROR(VLOOKUP(A43,'Sahm Rule'!$A:$B,2,TRUE),"") | J43: =IFERROR((B43/B30)^4-1-D43/100,"")
A44: 35727 | B44: =IF(VLOOKUP(A44,SP500相关数据!$B$11:$C$24727,2,TRUE)<>"",VLOOKUP(A44,SP500相关数据!$B$11:$C$24727,2,TRUE),IF(VLOOKUP(A44-1,SP500相关数据!$B$11:$C$24727,2,TRUE)<>"",VLOOKUP(A44-1,SP500相关数据!$B$11:$C$24727,2,TRUE),VLOOKUP(A44-2,SP500相关数据!$B$11:$C$24727,2,TRUE))) | C44: =IFERROR(IF(VLOOKUP(A44,SP500相关数据!$B$11:$E$24727,4,TRUE)<>"",VLOOKUP(A44,SP500相关数据!$B$11:$E$24727,4,TRUE),IF(VLOOKUP(A44-1,SP500相关数据!$B$11:$E$24727,4,TRUE)<>"",VLOOKUP(A44-1,SP500相关数据!$B$11:$E$24727,4,TRUE),VLOOKUP(A44-2,SP500相关数据!$B$11:$E$24727,4,TRUE))),"") | D44: =IF(VLOOKUP(A44,高收益利差!$A:$B,2,TRUE)<>"",VLOOKUP(A44,高收益利差!$A:$B,2,TRUE),IF(VLOOKUP(A44-1,高收益利差!$A:$B,2,TRUE)<>"",VLOOKUP(A44-1,高收益利差!$A:$B,2,TRUE),VLOOKUP(A44-2,高收益利差!$A:$B,2,TRUE))) | E44: =IFERROR(VLOOKUP(A44,'10Y2Y'!$A:$B,2,TRUE),"") | F44: =IFERROR(D44-D31,"") | G44: =IFERROR(B44/AVERAGE(B5:B44)-1,"") | H44: ="" | I44: =IFERROR(VLOOKUP(A44,'Sahm Rule'!$A:$B,2,TRUE),"") | J44: =IFERROR((B44/B31)^4-1-D44/100,"")
A45: 35734 | B45: =IF(VLOOKUP(A45,SP500相关数据!$B$11:$C$24727,2,TRUE)<>"",VLOOKUP(A45,SP500相关数据!$B$11:$C$24727,2,TRUE),IF(VLOOKUP(A45-1,SP500相关数据!$B$11:$C$24727,2,TRUE)<>"",VLOOKUP(A45-1,SP500相关数据!$B$11:$C$24727,2,TRUE),VLOOKUP(A45-2,SP500相关数据!$B$11:$C$24727,2,TRUE))) | C45: =IFERROR(IF(VLOOKUP(A45,SP500相关数据!$B$11:$E$24727,4,TRUE)<>"",VLOOKUP(A45,SP500相关数据!$B$11:$E$24727,4,TRUE),IF(VLOOKUP(A45-1,SP500相关数据!$B$11:$E$24727,4,TRUE)<>"",VLOOKUP(A45-1,SP500相关数据!$B$11:$E$24727,4,TRUE),VLOOKUP(A45-2,SP500相关数据!$B$11:$E$24727,4,TRUE))),"") | D45: =IF(VLOOKUP(A45,高收益利差!$A:$B,2,TRUE)<>"",VLOOKUP(A45,高收益利差!$A:$B,2,TRUE),IF(VLOOKUP(A45-1,高收益利差!$A:$B,2,TRUE)<>"",VLOOKUP(A45-1,高收益利差!$A:$B,2,TRUE),VLOOKUP(A45-2,高收益利差!$A:$B,2,TRUE))) | E45: =IFERROR(VLOOKUP(A45,'10Y2Y'!$A:$B,2,TRUE),"") | F45: =IFERROR(D45-D32,"") | G45: =IFERROR(B45/AVERAGE(B6:B45)-1,"") | H45: ="" | I45: =IFERROR(VLOOKUP(A45,'Sahm Rule'!$A:$B,2,TRUE),"") | J45: =IFERROR((B45/B32)^4-1-D45/100,"")
A46: 35741 | B46: =IF(VLOOKUP(A46,SP500相关数据!$B$11:$C$24727,2,TRUE)<>"",VLOOKUP(A46,SP500相关数据!$B$11:$C$24727,2,TRUE),IF(VLOOKUP(A46-1,SP500相关数据!$B$11:$C$24727,2,TRUE)<>"",VLOOKUP(A46-1,SP500相关数据!$B$11:$C$24727,2,TRUE),VLOOKUP(A46-2,SP500相关数据!$B$11:$C$24727,2,TRUE))) | C46: =IFERROR(IF(VLOOKUP(A46,SP500相关数据!$B$11:$E$24727,4,TRUE)<>"",VLOOKUP(A46,SP500相关数据!$B$11:$E$24727,4,TRUE),IF(VLOOKUP(A46-1,SP500相关数据!$B$11:$E$24727,4,TRUE)<>"",VLOOKUP(A46-1,SP500相关数据!$B$11:$E$24727,4,TRUE),VLOOKUP(A46-2,SP500相关数据!$B$11:$E$24727,4,TRUE))),"") | D46: =IF(VLOOKUP(A46,高收益利差!$A:$B,2,TRUE)<>"",VLOOKUP(A46,高收益利差!$A:$B,2,TRUE),IF(VLOOKUP(A46-1,高收益利差!$A:$B,2,TRUE)<>"",VLOOKUP(A46-1,高收益利差!$A:$B,2,TRUE),VLOOKUP(A46-2,高收益利差!$A:$B,2,TRUE))) | E46: =IFERROR(VLOOKUP(A46,'10Y2Y'!$A:$B,2,TRUE),"") | F46: =IFERROR(D46-D33,"") | G46: =IFERROR(B46/AVERAGE(B7:B46)-1,"") | H46: ="" | I46: =IFERROR(VLOOKUP(A46,'Sahm Rule'!$A:$B,2,TRUE),"") | J46: =IFERROR((B46/B33)^4-1-D46/100,"")
A47: 35748 | B47: =IF(VLOOKUP(A47,SP500相关数据!$B$11:$C$24727,2,TRUE)<>"",VLOOKUP(A47,SP500相关数据!$B$11:$C$24727,2,TRUE),IF(VLOOKUP(A47-1,SP500相关数据!$B$11:$C$24727,2,TRUE)<>"",VLOOKUP(A47-1,SP500相关数据!$B$11:$C$24727,2,TRUE),VLOOKUP(A47-2,SP500相关数据!$B$11:$C$24727,2,TRUE))) | C47: =IFERROR(IF(VLOOKUP(A47,SP500相关数据!$B$11:$E$24727,4,TRUE)<>"",VLOOKUP(A47,SP500相关数据!$B$11:$E$24727,4,TRUE),IF(VLOOKUP(A47-1,SP500相关数据!$B$11:$E$24727,4,TRUE)<>"",VLOOKUP(A47-1,SP500相关数据!$B$11:$E$24727,4,TRUE),VLOOKUP(A47-2,SP500相关数据!$B$11:$E$24727,4,TRUE))),"") | D47: =IF(VLOOKUP(A47,高收益利差!$A:$B,2,TRUE)<>"",VLOOKUP(A47,高收益利差!$A:$B,2,TRUE),IF(VLOOKUP(A47-1,高收益利差!$A:$B,2,TRUE)<>"",VLOOKUP(A47-1,高收益利差!$A:$B,2,TRUE),VLOOKUP(A47-2,高收益利差!$A:$B,2,TRUE))) | E47: =IFERROR(VLOOKUP(A47,'10Y2Y'!$A:$B,2,TRUE),"") | F47: =IFERROR(D47-D34,"") | G47: =IFERROR(B47/AVERAGE(B8:B47)-1,"") | H47: ="" | I47: =IFERROR(VLOOKUP(A47,'Sahm Rule'!$A:$B,2,TRUE),"") | J47: =IFERROR((B47/B34)^4-1-D47/100,"")
A48: 35755 | B48: =IF(VLOOKUP(A48,SP500相关数据!$B$11:$C$24727,2,TRUE)<>"",VLOOKUP(A48,SP500相关数据!$B$11:$C$24727,2,TRUE),IF(VLOOKUP(A48-1,SP500相关数据!$B$11:$C$24727,2,TRUE)<>"",VLOOKUP(A48-1,SP500相关数据!$B$11:$C$24727,2,TRUE),VLOOKUP(A48-2,SP500相关数据!$B$11:$C$24727,2,TRUE))) | C48: =IFERROR(IF(VLOOKUP(A48,SP500相关数据!$B$11:$E$24727,4,TRUE)<>"",VLOOKUP(A48,SP500相关数据!$B$11:$E$24727,4,TRUE),IF(VLOOKUP(A48-1,SP500相关数据!$B$11:$E$24727,4,TRUE)<>"",VLOOKUP(A48-1,SP500相关数据!$B$11:$E$24727,4,TRUE),VLOOKUP(A48-2,SP500相关数据!$B$11:$E$24727,4,TRUE))),"") | D48: =IF(VLOOKUP(A48,高收益利差!$A:$B,2,TRUE)<>"",VLOOKUP(A48,高收益利差!$A:$B,2,TRUE),IF(VLOOKUP(A48-1,高收益利差!$A:$B,2,TRUE)<>"",VLOOKUP(A48-1,高收益利差!$A:$B,2,TRUE),VLOOKUP(A48-2,高收益利差!$A:$B,2,TRUE))) | E48: =IFERROR(VLOOKUP(A48,'10Y2Y'!$A:$B,2,TRUE),"") | F48: =IFERROR(D48-D35,"") | G48: =IFERROR(B48/AVERAGE(B9:B48)-1,"") | H48: ="" | I48: =IFERROR(VLOOKUP(A48,'Sahm Rule'!$A:$B,2,TRUE),"") | J48: =IFERROR((B48/B35)^4-1-D48/100,"")
A49: 35762 | B49: =IF(VLOOKUP(A49,SP500相关数据!$B$11:$C$24727,2,TRUE)<>"",VLOOKUP(A49,SP500相关数据!$B$11:$C$24727,2,TRUE),IF(VLOOKUP(A49-1,SP500相关数据!$B$11:$C$24727,2,TRUE)<>"",VLOOKUP(A49-1,SP500相关数据!$B$11:$C$24727,2,TRUE),VLOOKUP(A49-2,SP500相关数据!$B$11:$C$24727,2,TRUE))) | C49: =IFERROR(IF(VLOOKUP(A49,SP500相关数据!$B$11:$E$24727,4,TRUE)<>"",VLOOKUP(A49,SP500相关数据!$B$11:$E$24727,4,TRUE),IF(VLOOKUP(A49-1,SP500相关数据!$B$11:$E$24727,4,TRUE)<>"",VLOOKUP(A49-1,SP500相关数据!$B$11:$E$24727,4,TRUE),VLOOKUP(A49-2,SP500相关数据!$B$11:$E$24727,4,TRUE))),"") | D49: =IF(VLOOKUP(A49,高收益利差!$A:$B,2,TRUE)<>"",VLOOKUP(A49,高收益利差!$A:$B,2,TRUE),IF(VLOOKUP(A49-1,高收益利差!$A:$B,2,TRUE)<>"",VLOOKUP(A49-1,高收益利差!$A:$B,2,TRUE),VLOOKUP(A49-2,高收益利差!$A:$B,2,TRUE))) | E49: =IFERROR(VLOOKUP(A49,'10Y2Y'!$A:$B,2,TRUE),"") | F49: =IFERROR(D49-D36,"") | G49: =IFERROR(B49/AVERAGE(B10:B49)-1,"") | H49: ="" | I49: =IFERROR(VLOOKUP(A49,'Sahm Rule'!$A:$B,2,TRUE),"") | J49: =IFERROR((B49/B36)^4-1-D49/100,"")
A50: 35769 | B50: =IF(VLOOKUP(A50,SP500相关数据!$B$11:$C$24727,2,TRUE)<>"",VLOOKUP(A50,SP500相关数据!$B$11:$C$24727,2,TRUE),IF(VLOOKUP(A50-1,SP500相关数据!$B$11:$C$24727,2,TRUE)<>"",VLOOKUP(A50-1,SP500相关数据!$B$11:$C$24727,2,TRUE),VLOOKUP(A50-2,SP500相关数据!$B$11:$C$24727,2,TRUE))) | C50: =IFERROR(IF(VLOOKUP(A50,SP500相关数据!$B$11:$E$24727,4,TRUE)<>"",VLOOKUP(A50,SP500相关数据!$B$11:$E$24727,4,TRUE),IF(VLOOKUP(A50-1,SP500相关数据!$B$11:$E$24727,4,TRUE)<>"",VLOOKUP(A50-1,SP500相关数据!$B$11:$E$24727,4,TRUE),VLOOKUP(A50-2,SP500相关数据!$B$11:$E$24727,4,TRUE))),"") | D50: =IF(VLOOKUP(A50,高收益利差!$A:$B,2,TRUE)<>"",VLOOKUP(A50,高收益利差!$A:$B,2,TRUE),IF(VLOOKUP(A50-1,高收益利差!$A:$B,2,TRUE)<>"",VLOOKUP(A50-1,高收益利差!$A:$B,2,TRUE),VLOOKUP(A50-2,高收益利差!$A:$B,2,TRUE))) | E50: =IFERROR(VLOOKUP(A50,'10Y2Y'!$A:$B,2,TRUE),"") | F50: =IFERROR(D50-D37,"") | G50: =IFERROR(B50/AVERAGE(B11:B50)-1,"") | H50: ="" | I50: =IFERROR(VLOOKUP(A50,'Sahm Rule'!$A:$B,2,TRUE),"") | J50: =IFERROR((B50/B37)^4-1-D50/100,"")
A51: 35776 | B51: =IF(VLOOKUP(A51,SP500相关数据!$B$11:$C$24727,2,TRUE)<>"",VLOOKUP(A51,SP500相关数据!$B$11:$C$24727,2,TRUE),IF(VLOOKUP(A51-1,SP500相关数据!$B$11:$C$24727,2,TRUE)<>"",VLOOKUP(A51-1,SP500相关数据!$B$11:$C$24727,2,TRUE),VLOOKUP(A51-2,SP500相关数据!$B$11:$C$24727,2,TRUE))) | C51: =IFERROR(IF(VLOOKUP(A51,SP500相关数据!$B$11:$E$24727,4,TRUE)<>"",VLOOKUP(A51,SP500相关数据!$B$11:$E$24727,4,TRUE),IF(VLOOKUP(A51-1,SP500相关数据!$B$11:$E$24727,4,TRUE)<>"",VLOOKUP(A51-1,SP500相关数据!$B$11:$E$24727,4,TRUE),VLOOKUP(A51-2,SP500相关数据!$B$11:$E$24727,4,TRUE))),"") | D51: =IF(VLOOKUP(A51,高收益利差!$A:$B,2,TRUE)<>"",VLOOKUP(A51,高收益利差!$A:$B,2,TRUE),IF(VLOOKUP(A51-1,高收益利差!$A:$B,2,TRUE)<>"",VLOOKUP(A51-1,高收益利差!$A:$B,2,TRUE),VLOOKUP(A51-2,高收益利差!$A:$B,2,TRUE))) | E51: =IFERROR(VLOOKUP(A51,'10Y2Y'!$A:$B,2,TRUE),"") | F51: =IFERROR(D51-D38,"") | G51: =IFERROR(B51/AVERAGE(B12:B51)-1,"") | H51: ="" | I51: =IFERROR(VLOOKUP(A51,'Sahm Rule'!$A:$B,2,TRUE),"") | J51: =IFERROR((B51/B38)^4-1-D51/100,"")
A52: 35783 | B52: =IF(VLOOKUP(A52,SP500相关数据!$B$11:$C$24727,2,TRUE)<>"",VLOOKUP(A52,SP500相关数据!$B$11:$C$24727,2,TRUE),IF(VLOOKUP(A52-1,SP500相关数据!$B$11:$C$24727,2,TRUE)<>"",VLOOKUP(A52-1,SP500相关数据!$B$11:$C$24727,2,TRUE),VLOOKUP(A52-2,SP500相关数据!$B$11:$C$24727,2,TRUE))) | C52: =IFERROR(IF(VLOOKUP(A52,SP500相关数据!$B$11:$E$24727,4,TRUE)<>"",VLOOKUP(A52,SP500相关数据!$B$11:$E$24727,4,TRUE),IF(VLOOKUP(A52-1,SP500相关数据!$B$11:$E$24727,4,TRUE)<>"",VLOOKUP(A52-1,SP500相关数据!$B$11:$E$24727,4,TRUE),VLOOKUP(A52-2,SP500相关数据!$B$11:$E$24727,4,TRUE))),"") | D52: =IF(VLOOKUP(A52,高收益利差!$A:$B,2,TRUE)<>"",VLOOKUP(A52,高收益利差!$A:$B,2,TRUE),IF(VLOOKUP(A52-1,高收益利差!$A:$B,2,TRUE)<>"",VLOOKUP(A52-1,高收益利差!$A:$B,2,TRUE),VLOOKUP(A52-2,高收益利差!$A:$B,2,TRUE))) | E52: =IFERROR(VLOOKUP(A52,'10Y2Y'!$A:$B,2,TRUE),"") | F52: =IFERROR(D52-D39,"") | G52: =IFERROR(B52/AVERAGE(B13:B52)-1,"") | H52: ="" | I52: =IFERROR(VLOOKUP(A52,'Sahm Rule'!$A:$B,2,TRUE),"") | J52: =IFERROR((B52/B39)^4-1-D52/100,"")
A53: 35790 | B53: =IF(VLOOKUP(A53,SP500相关数据!$B$11:$C$24727,2,TRUE)<>"",VLOOKUP(A53,SP500相关数据!$B$11:$C$24727,2,TRUE),IF(VLOOKUP(A53-1,SP500相关数据!$B$11:$C$24727,2,TRUE)<>"",VLOOKUP(A53-1,SP500相关数据!$B$11:$C$24727,2,TRUE),VLOOKUP(A53-2,SP500相关数据!$B$11:$C$24727,2,TRUE))) | C53: =IFERROR(IF(VLOOKUP(A53,SP500相关数据!$B$11:$E$24727,4,TRUE)<>"",VLOOKUP(A53,SP500相关数据!$B$11:$E$24727,4,TRUE),IF(VLOOKUP(A53-1,SP500相关数据!$B$11:$E$24727,4,TRUE)<>"",VLOOKUP(A53-1,SP500相关数据!$B$11:$E$24727,4,TRUE),VLOOKUP(A53-2,SP500相关数据!$B$11:$E$24727,4,TRUE))),"") | D53: =IF(VLOOKUP(A53,高收益利差!$A:$B,2,TRUE)<>"",VLOOKUP(A53,高收益利差!$A:$B,2,TRUE),IF(VLOOKUP(A53-1,高收益利差!$A:$B,2,TRUE)<>"",VLOOKUP(A53-1,高收益利差!$A:$B,2,TRUE),VLOOKUP(A53-2,高收益利差!$A:$B,2,TRUE))) | E53: =IFERROR(VLOOKUP(A53,'10Y2Y'!$A:$B,2,TRUE),"") | F53: =IFERROR(D53-D40,"") | G53: =IFERROR(B53/AVERAGE(B14:B53)-1,"") | H53: ="" | I53: =IFERROR(VLOOKUP(A53,'Sahm Rule'!$A:$B,2,TRUE),"") | J53: =IFERROR((B53/B40)^4-1-D53/100,"")
A54: 35797 | B54: =IF(VLOOKUP(A54,SP500相关数据!$B$11:$C$24727,2,TRUE)<>"",VLOOKUP(A54,SP500相关数据!$B$11:$C$24727,2,TRUE),IF(VLOOKUP(A54-1,SP500相关数据!$B$11:$C$24727,2,TRUE)<>"",VLOOKUP(A54-1,SP500相关数据!$B$11:$C$24727,2,TRUE),VLOOKUP(A54-2,SP500相关数据!$B$11:$C$24727,2,TRUE))) | C54: =IFERROR(IF(VLOOKUP(A54,SP500相关数据!$B$11:$E$24727,4,TRUE)<>"",VLOOKUP(A54,SP500相关数据!$B$11:$E$24727,4,TRUE),IF(VLOOKUP(A54-1,SP500相关数据!$B$11:$E$24727,4,TRUE)<>"",VLOOKUP(A54-1,SP500相关数据!$B$11:$E$24727,4,TRUE),VLOOKUP(A54-2,SP500相关数据!$B$11:$E$24727,4,TRUE))),"") | D54: =IF(VLOOKUP(A54,高收益利差!$A:$B,2,TRUE)<>"",VLOOKUP(A54,高收益利差!$A:$B,2,TRUE),IF(VLOOKUP(A54-1,高收益利差!$A:$B,2,TRUE)<>"",VLOOKUP(A54-1,高收益利差!$A:$B,2,TRUE),VLOOKUP(A54-2,高收益利差!$A:$B,2,TRUE))) | E54: =IFERROR(VLOOKUP(A54,'10Y2Y'!$A:$B,2,TRUE),"") | F54: =IFERROR(D54-D41,"") | G54: =IFERROR(B54/AVERAGE(B15:B54)-1,"") | H54: ="" | I54: =IFERROR(VLOOKUP(A54,'Sahm Rule'!$A:$B,2,TRUE),"") | J54: =IFERROR((B54/B41)^4-1-D54/100,"")
A55: 35804 | B55: =IF(VLOOKUP(A55,SP500相关数据!$B$11:$C$24727,2,TRUE)<>"",VLOOKUP(A55,SP500相关数据!$B$11:$C$24727,2,TRUE),IF(VLOOKUP(A55-1,SP500相关数据!$B$11:$C$24727,2,TRUE)<>"",VLOOKUP(A55-1,SP500相关数据!$B$11:$C$24727,2,TRUE),VLOOKUP(A55-2,SP500相关数据!$B$11:$C$24727,2,TRUE))) | C55: =IFERROR(IF(VLOOKUP(A55,SP500相关数据!$B$11:$E$24727,4,TRUE)<>"",VLOOKUP(A55,SP500相关数据!$B$11:$E$24727,4,TRUE),IF(VLOOKUP(A55-1,SP500相关数据!$B$11:$E$24727,4,TRUE)<>"",VLOOKUP(A55-1,SP500相关数据!$B$11:$E$24727,4,TRUE),VLOOKUP(A55-2,SP500相关数据!$B$11:$E$24727,4,TRUE))),"") | D55: =IF(VLOOKUP(A55,高收益利差!$A:$B,2,TRUE)<>"",VLOOKUP(A55,高收益利差!$A:$B,2,TRUE),IF(VLOOKUP(A55-1,高收益利差!$A:$B,2,TRUE)<>"",VLOOKUP(A55-1,高收益利差!$A:$B,2,TRUE),VLOOKUP(A55-2,高收益利差!$A:$B,2,TRUE))) | E55: =IFERROR(VLOOKUP(A55,'10Y2Y'!$A:$B,2,TRUE),"") | F55: =IFERROR(D55-D42,"") | G55: =IFERROR(B55/AVERAGE(B16:B55)-1,"") | H55: =IF(B55="","",IFERROR(AVERAGE(B16:B55)/AVERAGE(B3:B42)-1,"")) | I55: =IFERROR(VLOOKUP(A55,'Sahm Rule'!$A:$B,2,TRUE),"") | J55: =IFERROR((B55/B42)^4-1-D55/100,"")
A56: 35811 | B56: =IF(VLOOKUP(A56,SP500相关数据!$B$11:$C$24727,2,TRUE)<>"",VLOOKUP(A56,SP500相关数据!$B$11:$C$24727,2,TRUE),IF(VLOOKUP(A56-1,SP500相关数据!$B$11:$C$24727,2,TRUE)<>"",VLOOKUP(A56-1,SP500相关数据!$B$11:$C$24727,2,TRUE),VLOOKUP(A56-2,SP500相关数据!$B$11:$C$24727,2,TRUE))) | C56: =IFERROR(IF(VLOOKUP(A56,SP500相关数据!$B$11:$E$24727,4,TRUE)<>"",VLOOKUP(A56,SP500相关数据!$B$11:$E$24727,4,TRUE),IF(VLOOKUP(A56-1,SP500相关数据!$B$11:$E$24727,4,TRUE)<>"",VLOOKUP(A56-1,SP500相关数据!$B$11:$E$24727,4,TRUE),VLOOKUP(A56-2,SP500相关数据!$B$11:$E$24727,4,TRUE))),"") | D56: =IF(VLOOKUP(A56,高收益利差!$A:$B,2,TRUE)<>"",VLOOKUP(A56,高收益利差!$A:$B,2,TRUE),IF(VLOOKUP(A56-1,高收益利差!$A:$B,2,TRUE)<>"",VLOOKUP(A56-1,高收益利差!$A:$B,2,TRUE),VLOOKUP(A56-2,高收益利差!$A:$B,2,TRUE))) | E56: =IFERROR(VLOOKUP(A56,'10Y2Y'!$A:$B,2,TRUE),"") | F56: =IFERROR(D56-D43,"") | G56: =IFERROR(B56/AVERAGE(B17:B56)-1,"") | H56: =IF(B56="","",IFERROR(AVERAGE(B17:B56)/AVERAGE(B4:B43)-1,"")) | I56: =IFERROR(VLOOKUP(A56,'Sahm Rule'!$A:$B,2,TRUE),"") | J56: =IFERROR((B56/B43)^4-1-D56/100,"")
A57: 35818 | B57: =IF(VLOOKUP(A57,SP500相关数据!$B$11:$C$24727,2,TRUE)<>"",VLOOKUP(A57,SP500相关数据!$B$11:$C$24727,2,TRUE),IF(VLOOKUP(A57-1,SP500相关数据!$B$11:$C$24727,2,TRUE)<>"",VLOOKUP(A57-1,SP500相关数据!$B$11:$C$24727,2,TRUE),VLOOKUP(A57-2,SP500相关数据!$B$11:$C$24727,2,TRUE))) | C57: =IFERROR(IF(VLOOKUP(A57,SP500相关数据!$B$11:$E$24727,4,TRUE)<>"",VLOOKUP(A57,SP500相关数据!$B$11:$E$24727,4,TRUE),IF(VLOOKUP(A57-1,SP500相关数据!$B$11:$E$24727,4,TRUE)<>"",VLOOKUP(A57-1,SP500相关数据!$B$11:$E$24727,4,TRUE),VLOOKUP(A57-2,SP500相关数据!$B$11:$E$24727,4,TRUE))),"") | D57: =IF(VLOOKUP(A57,高收益利差!$A:$B,2,TRUE)<>"",VLOOKUP(A57,高收益利差!$A:$B,2,TRUE),IF(VLOOKUP(A57-1,高收益利差!$A:$B,2,TRUE)<>"",VLOOKUP(A57-1,高收益利差!$A:$B,2,TRUE),VLOOKUP(A57-2,高收益利差!$A:$B,2,TRUE))) | E57: =IFERROR(VLOOKUP(A57,'10Y2Y'!$A:$B,2,TRUE),"") | F57: =IFERROR(D57-D44,"") | G57: =IFERROR(B57/AVERAGE(B18:B57)-1,"") | H57: =IF(B57="","",IFERROR(AVERAGE(B18:B57)/AVERAGE(B5:B44)-1,"")) | I57: =IFERROR(VLOOKUP(A57,'Sahm Rule'!$A:$B,2,TRUE),"") | J57: =IFERROR((B57/B44)^4-1-D57/100,"")
A58: 35825 | B58: =IF(VLOOKUP(A58,SP500相关数据!$B$11:$C$24727,2,TRUE)<>"",VLOOKUP(A58,SP500相关数据!$B$11:$C$24727,2,TRUE),IF(VLOOKUP(A58-1,SP500相关数据!$B$11:$C$24727,2,TRUE)<>"",VLOOKUP(A58-1,SP500相关数据!$B$11:$C$24727,2,TRUE),VLOOKUP(A58-2,SP500相关数据!$B$11:$C$24727,2,TRUE))) | C58: =IFERROR(IF(VLOOKUP(A58,SP500相关数据!$B$11:$E$24727,4,TRUE)<>"",VLOOKUP(A58,SP500相关数据!$B$11:$E$24727,4,TRUE),IF(VLOOKUP(A58-1,SP500相关数据!$B$11:$E$24727,4,TRUE)<>"",VLOOKUP(A58-1,SP500相关数据!$B$11:$E$24727,4,TRUE),VLOOKUP(A58-2,SP500相关数据!$B$11:$E$24727,4,TRUE))),"") | D58: =IF(VLOOKUP(A58,高收益利差!$A:$B,2,TRUE)<>"",VLOOKUP(A58,高收益利差!$A:$B,2,TRUE),IF(VLOOKUP(A58-1,高收益利差!$A:$B,2,TRUE)<>"",VLOOKUP(A58-1,高收益利差!$A:$B,2,TRUE),VLOOKUP(A58-2,高收益利差!$A:$B,2,TRUE))) | E58: =IFERROR(VLOOKUP(A58,'10Y2Y'!$A:$B,2,TRUE),"") | F58: =IFERROR(D58-D45,"") | G58: =IFERROR(B58/AVERAGE(B19:B58)-1,"") | H58: =IF(B58="","",IFERROR(AVERAGE(B19:B58)/AVERAGE(B6:B45)-1,"")) | I58: =IFERROR(VLOOKUP(A58,'Sahm Rule'!$A:$B,2,TRUE),"") | J58: =IFERROR((B58/B45)^4-1-D58/100,"")
A59: 35832 | B59: =IF(VLOOKUP(A59,SP500相关数据!$B$11:$C$24727,2,TRUE)<>"",VLOOKUP(A59,SP500相关数据!$B$11:$C$24727,2,TRUE),IF(VLOOKUP(A59-1,SP500相关数据!$B$11:$C$24727,2,TRUE)<>"",VLOOKUP(A59-1,SP500相关数据!$B$11:$C$24727,2,TRUE),VLOOKUP(A59-2,SP500相关数据!$B$11:$C$24727,2,TRUE))) | C59: =IFERROR(IF(VLOOKUP(A59,SP500相关数据!$B$11:$E$24727,4,TRUE)<>"",VLOOKUP(A59,SP500相关数据!$B$11:$E$24727,4,TRUE),IF(VLOOKUP(A59-1,SP500相关数据!$B$11:$E$24727,4,TRUE)<>"",VLOOKUP(A59-1,SP500相关数据!$B$11:$E$24727,4,TRUE),VLOOKUP(A59-2,SP500相关数据!$B$11:$E$24727,4,TRUE))),"") | D59: =IF(VLOOKUP(A59,高收益利差!$A:$B,2,TRUE)<>"",VLOOKUP(A59,高收益利差!$A:$B,2,TRUE),IF(VLOOKUP(A59-1,高收益利差!$A:$B,2,TRUE)<>"",VLOOKUP(A59-1,高收益利差!$A:$B,2,TRUE),VLOOKUP(A59-2,高收益利差!$A:$B,2,TRUE))) | E59: =IFERROR(VLOOKUP(A59,'10Y2Y'!$A:$B,2,TRUE),"") | F59: =IFERROR(D59-D46,"") | G59: =IFERROR(B59/AVERAGE(B20:B59)-1,"") | H59: =IF(B59="","",IFERROR(AVERAGE(B20:B59)/AVERAGE(B7:B46)-1,"")) | I59: =IFERROR(VLOOKUP(A59,'Sahm Rule'!$A:$B,2,TRUE),"") | J59: =IFERROR((B59/B46)^4-1-D59/100,"")
A60: 35839 | B60: =IF(VLOOKUP(A60,SP500相关数据!$B$11:$C$24727,2,TRUE)<>"",VLOOKUP(A60,SP500相关数据!$B$11:$C$24727,2,TRUE),IF(VLOOKUP(A60-1,SP500相关数据!$B$11:$C$24727,2,TRUE)<>"",VLOOKUP(A60-1,SP500相关数据!$B$11:$C$24727,2,TRUE),VLOOKUP(A60-2,SP500相关数据!$B$11:$C$24727,2,TRUE))) | C60: =IFERROR(IF(VLOOKUP(A60,SP500相关数据!$B$11:$E$24727,4,TRUE)<>"",VLOOKUP(A60,SP500相关数据!$B$11:$E$24727,4,TRUE),IF(VLOOKUP(A60-1,SP500相关数据!$B$11:$E$24727,4,TRUE)<>"",VLOOKUP(A60-1,SP500相关数据!$B$11:$E$24727,4,TRUE),VLOOKUP(A60-2,SP500相关数据!$B$11:$E$24727,4,TRUE))),"") | D60: =IF(VLOOKUP(A60,高收益利差!$A:$B,2,TRUE)<>"",VLOOKUP(A60,高收益利差!$A:$B,2,TRUE),IF(VLOOKUP(A60-1,高收益利差!$A:$B,2,TRUE)<>"",VLOOKUP(A60-1,高收益利差!$A:$B,2,TRUE),VLOOKUP(A60-2,高收益利差!$A:$B,2,TRUE))) | E60: =IFERROR(VLOOKUP(A60,'10Y2Y'!$A:$B,2,TRUE),"") | F60: =IFERROR(D60-D47,"") | G60: =IFERROR(B60/AVERAGE(B21:B60)-1,"") | H60: =IF(B60="","",IFERROR(AVERAGE(B21:B60)/AVERAGE(B8:B47)-1,"")) | I60: =IFERROR(VLOOKUP(A60,'Sahm Rule'!$A:$B,2,TRUE),"") | J60: =IFERROR((B60/B47)^4-1-D60/100,"")
A61: 35846 | B61: =IF(VLOOKUP(A61,SP500相关数据!$B$11:$C$24727,2,TRUE)<>"",VLOOKUP(A61,SP500相关数据!$B$11:$C$24727,2,TRUE),IF(VLOOKUP(A61-1,SP500相关数据!$B$11:$C$24727,2,TRUE)<>"",VLOOKUP(A61-1,SP500相关数据!$B$11:$C$24727,2,TRUE),VLOOKUP(A61-2,SP500相关数据!$B$11:$C$24727,2,TRUE))) | C61: =IFERROR(IF(VLOOKUP(A61,SP500相关数据!$B$11:$E$24727,4,TRUE)<>"",VLOOKUP(A61,SP500相关数据!$B$11:$E$24727,4,TRUE),IF(VLOOKUP(A61-1,SP500相关数据!$B$11:$E$24727,4,TRUE)<>"",VLOOKUP(A61-1,SP500相关数据!$B$11:$E$24727,4,TRUE),VLOOKUP(A61-2,SP500相关数据!$B$11:$E$24727,4,TRUE))),"") | D61: =IF(VLOOKUP(A61,高收益利差!$A:$B,2,TRUE)<>"",VLOOKUP(A61,高收益利差!$A:$B,2,TRUE),IF(VLOOKUP(A61-1,高收益利差!$A:$B,2,TRUE)<>"",VLOOKUP(A61-1,高收益利差!$A:$B,2,TRUE),VLOOKUP(A61-2,高收益利差!$A:$B,2,TRUE))) | E61: =IFERROR(VLOOKUP(A61,'10Y2Y'!$A:$B,2,TRUE),"") | F61: =IFERROR(D61-D48,"") | G61: =IFERROR(B61/AVERAGE(B22:B61)-1,"") | H61: =IF(B61="","",IFERROR(AVERAGE(B22:B61)/AVERAGE(B9:B48)-1,"")) | I61: =IFERROR(VLOOKUP(A61,'Sahm Rule'!$A:$B,2,TRUE),"") | J61: =IFERROR((B61/B48)^4-1-D61/100,"")
A62: 35853 | B62: =IF(VLOOKUP(A62,SP500相关数据!$B$11:$C$24727,2,TRUE)<>"",VLOOKUP(A62,SP500相关数据!$B$11:$C$24727,2,TRUE),IF(VLOOKUP(A62-1,SP500相关数据!$B$11:$C$24727,2,TRUE)<>"",VLOOKUP(A62-1,SP500相关数据!$B$11:$C$24727,2,TRUE),VLOOKUP(A62-2,SP500相关数据!$B$11:$C$24727,2,TRUE))) | C62: =IFERROR(IF(VLOOKUP(A62,SP500相关数据!$B$11:$E$24727,4,TRUE)<>"",VLOOKUP(A62,SP500相关数据!$B$11:$E$24727,4,TRUE),IF(VLOOKUP(A62-1,SP500相关数据!$B$11:$E$24727,4,TRUE)<>"",VLOOKUP(A62-1,SP500相关数据!$B$11:$E$24727,4,TRUE),VLOOKUP(A62-2,SP500相关数据!$B$11:$E$24727,4,TRUE))),"") | D62: =IF(VLOOKUP(A62,高收益利差!$A:$B,2,TRUE)<>"",VLOOKUP(A62,高收益利差!$A:$B,2,TRUE),IF(VLOOKUP(A62-1,高收益利差!$A:$B,2,TRUE)<>"",VLOOKUP(A62-1,高收益利差!$A:$B,2,TRUE),VLOOKUP(A62-2,高收益利差!$A:$B,2,TRUE))) | E62: =IFERROR(VLOOKUP(A62,'10Y2Y'!$A:$B,2,TRUE),"") | F62: =IFERROR(D62-D49,"") | G62: =IFERROR(B62/AVERAGE(B23:B62)-1,"") | H62: =IF(B62="","",IFERROR(AVERAGE(B23:B62)/AVERAGE(B10:B49)-1,"")) | I62: =IFERROR(VLOOKUP(A62,'Sahm Rule'!$A:$B,2,TRUE),"") | J62: =IFERROR((B62/B49)^4-1-D62/100,"")
A63: 35860 | B63: =IF(VLOOKUP(A63,SP500相关数据!$B$11:$C$24727,2,TRUE)<>"",VLOOKUP(A63,SP500相关数据!$B$11:$C$24727,2,TRUE),IF(VLOOKUP(A63-1,SP500相关数据!$B$11:$C$24727,2,TRUE)<>"",VLOOKUP(A63-1,SP500相关数据!$B$11:$C$24727,2,TRUE),VLOOKUP(A63-2,SP500相关数据!$B$11:$C$24727,2,TRUE))) | C63: =IFERROR(IF(VLOOKUP(A63,SP500相关数据!$B$11:$E$24727,4,TRUE)<>"",VLOOKUP(A63,SP500相关数据!$B$11:$E$24727,4,TRUE),IF(VLOOKUP(A63-1,SP500相关数据!$B$11:$E$24727,4,TRUE)<>"",VLOOKUP(A63-1,SP500相关数据!$B$11:$E$24727,4,TRUE),VLOOKUP(A63-2,SP500相关数据!$B$11:$E$24727,4,TRUE))),"") | D63: =IF(VLOOKUP(A63,高收益利差!$A:$B,2,TRUE)<>"",VLOOKUP(A63,高收益利差!$A:$B,2,TRUE),IF(VLOOKUP(A63-1,高收益利差!$A:$B,2,TRUE)<>"",VLOOKUP(A63-1,高收益利差!$A:$B,2,TRUE),VLOOKUP(A63-2,高收益利差!$A:$B,2,TRUE))) | E63: =IFERROR(VLOOKUP(A63,'10Y2Y'!$A:$B,2,TRUE),"") | F63: =IFERROR(D63-D50,"") | G63: =IFERROR(B63/AVERAGE(B24:B63)-1,"") | H63: =IF(B63="","",IFERROR(AVERAGE(B24:B63)/AVERAGE(B11:B50)-1,"")) | I63: =IFERROR(VLOOKUP(A63,'Sahm Rule'!$A:$B,2,TRUE),"") | J63: =IFERROR((B63/B50)^4-1-D63/100,"")
A64: 35867 | B64: =IF(VLOOKUP(A64,SP500相关数据!$B$11:$C$24727,2,TRUE)<>"",VLOOKUP(A64,SP500相关数据!$B$11:$C$24727,2,TRUE),IF(VLOOKUP(A64-1,SP500相关数据!$B$11:$C$24727,2,TRUE)<>"",VLOOKUP(A64-1,SP500相关数据!$B$11:$C$24727,2,TRUE),VLOOKUP(A64-2,SP500相关数据!$B$11:$C$24727,2,TRUE))) | C64: =IFERROR(IF(VLOOKUP(A64,SP500相关数据!$B$11:$E$24727,4,TRUE)<>"",VLOOKUP(A64,SP500相关数据!$B$11:$E$24727,4,TRUE),IF(VLOOKUP(A64-1,SP500相关数据!$B$11:$E$24727,4,TRUE)<>"",VLOOKUP(A64-1,SP500相关数据!$B$11:$E$24727,4,TRUE),VLOOKUP(A64-2,SP500相关数据!$B$11:$E$24727,4,TRUE))),"") | D64: =IF(VLOOKUP(A64,高收益利差!$A:$B,2,TRUE)<>"",VLOOKUP(A64,高收益利差!$A:$B,2,TRUE),IF(VLOOKUP(A64-1,高收益利差!$A:$B,2,TRUE)<>"",VLOOKUP(A64-1,高收益利差!$A:$B,2,TRUE),VLOOKUP(A64-2,高收益利差!$A:$B,2,TRUE))) | E64: =IFERROR(VLOOKUP(A64,'10Y2Y'!$A:$B,2,TRUE),"") | F64: =IFERROR(D64-D51,"") | G64: =IFERROR(B64/AVERAGE(B25:B64)-1,"") | H64: =IF(B64="","",IFERROR(AVERAGE(B25:B64)/AVERAGE(B12:B51)-1,"")) | I64: =IFERROR(VLOOKUP(A64,'Sahm Rule'!$A:$B,2,TRUE),"") | J64: =IFERROR((B64/B51)^4-1-D64/100,"")
A65: 35874 | B65: =IF(VLOOKUP(A65,SP500相关数据!$B$11:$C$24727,2,TRUE)<>"",VLOOKUP(A65,SP500相关数据!$B$11:$C$24727,2,TRUE),IF(VLOOKUP(A65-1,SP500相关数据!$B$11:$C$24727,2,TRUE)<>"",VLOOKUP(A65-1,SP500相关数据!$B$11:$C$24727,2,TRUE),VLOOKUP(A65-2,SP500相关数据!$B$11:$C$24727,2,TRUE))) | C65: =IFERROR(IF(VLOOKUP(A65,SP500相关数据!$B$11:$E$24727,4,TRUE)<>"",VLOOKUP(A65,SP500相关数据!$B$11:$E$24727,4,TRUE),IF(VLOOKUP(A65-1,SP500相关数据!$B$11:$E$24727,4,TRUE)<>"",VLOOKUP(A65-1,SP500相关数据!$B$11:$E$24727,4,TRUE),VLOOKUP(A65-2,SP500相关数据!$B$11:$E$24727,4,TRUE))),"") | D65: =IF(VLOOKUP(A65,高收益利差!$A:$B,2,TRUE)<>"",VLOOKUP(A65,高收益利差!$A:$B,2,TRUE),IF(VLOOKUP(A65-1,高收益利差!$A:$B,2,TRUE)<>"",VLOOKUP(A65-1,高收益利差!$A:$B,2,TRUE),VLOOKUP(A65-2,高收益利差!$A:$B,2,TRUE))) | E65: =IFERROR(VLOOKUP(A65,'10Y2Y'!$A:$B,2,TRUE),"") | F65: =IFERROR(D65-D52,"") | G65: =IFERROR(B65/AVERAGE(B26:B65)-1,"") | H65: =IF(B65="","",IFERROR(AVERAGE(B26:B65)/AVERAGE(B13:B52)-1,"")) | I65: =IFERROR(VLOOKUP(A65,'Sahm Rule'!$A:$B,2,TRUE),"") | J65: =IFERROR((B65/B52)^4-1-D65/100,"")
A66: 35881 | B66: =IF(VLOOKUP(A66,SP500相关数据!$B$11:$C$24727,2,TRUE)<>"",VLOOKUP(A66,SP500相关数据!$B$11:$C$24727,2,TRUE),IF(VLOOKUP(A66-1,SP500相关数据!$B$11:$C$24727,2,TRUE)<>"",VLOOKUP(A66-1,SP500相关数据!$B$11:$C$24727,2,TRUE),VLOOKUP(A66-2,SP500相关数据!$B$11:$C$24727,2,TRUE))) | C66: =IFERROR(IF(VLOOKUP(A66,SP500相关数据!$B$11:$E$24727,4,TRUE)<>"",VLOOKUP(A66,SP500相关数据!$B$11:$E$24727,4,TRUE),IF(VLOOKUP(A66-1,SP500相关数据!$B$11:$E$24727,4,TRUE)<>"",VLOOKUP(A66-1,SP500相关数据!$B$11:$E$24727,4,TRUE),VLOOKUP(A66-2,SP500相关数据!$B$11:$E$24727,4,TRUE))),"") | D66: =IF(VLOOKUP(A66,高收益利差!$A:$B,2,TRUE)<>"",VLOOKUP(A66,高收益利差!$A:$B,2,TRUE),IF(VLOOKUP(A66-1,高收益利差!$A:$B,2,TRUE)<>"",VLOOKUP(A66-1,高收益利差!$A:$B,2,TRUE),VLOOKUP(A66-2,高收益利差!$A:$B,2,TRUE))) | E66: =IFERROR(VLOOKUP(A66,'10Y2Y'!$A:$B,2,TRUE),"") | F66: =IFERROR(D66-D53,"") | G66: =IFERROR(B66/AVERAGE(B27:B66)-1,"") | H66: =IF(B66="","",IFERROR(AVERAGE(B27:B66)/AVERAGE(B14:B53)-1,"")) | I66: =IFERROR(VLOOKUP(A66,'Sahm Rule'!$A:$B,2,TRUE),"") | J66: =IFERROR((B66/B53)^4-1-D66/100,"")
A67: 35888 | B67: =IF(VLOOKUP(A67,SP500相关数据!$B$11:$C$24727,2,TRUE)<>"",VLOOKUP(A67,SP500相关数据!$B$11:$C$24727,2,TRUE),IF(VLOOKUP(A67-1,SP500相关数据!$B$11:$C$24727,2,TRUE)<>"",VLOOKUP(A67-1,SP500相关数据!$B$11:$C$24727,2,TRUE),VLOOKUP(A67-2,SP500相关数据!$B$11:$C$24727,2,TRUE))) | C67: =IFERROR(IF(VLOOKUP(A67,SP500相关数据!$B$11:$E$24727,4,TRUE)<>"",VLOOKUP(A67,SP500相关数据!$B$11:$E$24727,4,TRUE),IF(VLOOKUP(A67-1,SP500相关数据!$B$11:$E$24727,4,TRUE)<>"",VLOOKUP(A67-1,SP500相关数据!$B$11:$E$24727,4,TRUE),VLOOKUP(A67-2,SP500相关数据!$B$11:$E$24727,4,TRUE))),"") | D67: =IF(VLOOKUP(A67,高收益利差!$A:$B,2,TRUE)<>"",VLOOKUP(A67,高收益利差!$A:$B,2,TRUE),IF(VLOOKUP(A67-1,高收益利差!$A:$B,2,TRUE)<>"",VLOOKUP(A67-1,高收益利差!$A:$B,2,TRUE),VLOOKUP(A67-2,高收益利差!$A:$B,2,TRUE))) | E67: =IFERROR(VLOOKUP(A67,'10Y2Y'!$A:$B,2,TRUE),"") | F67: =IFERROR(D67-D54,"") | G67: =IFERROR(B67/AVERAGE(B28:B67)-1,"") | H67: =IF(B67="","",IFERROR(AVERAGE(B28:B67)/AVERAGE(B15:B54)-1,"")) | I67: =IFERROR(VLOOKUP(A67,'Sahm Rule'!$A:$B,2,TRUE),"") | J67: =IFERROR((B67/B54)^4-1-D67/100,"")
A68: 35895 | B68: =IF(VLOOKUP(A68,SP500相关数据!$B$11:$C$24727,2,TRUE)<>"",VLOOKUP(A68,SP500相关数据!$B$11:$C$24727,2,TRUE),IF(VLOOKUP(A68-1,SP500相关数据!$B$11:$C$24727,2,TRUE)<>"",VLOOKUP(A68-1,SP500相关数据!$B$11:$C$24727,2,TRUE),VLOOKUP(A68-2,SP500相关数据!$B$11:$C$24727,2,TRUE))) | C68: =IFERROR(IF(VLOOKUP(A68,SP500相关数据!$B$11:$E$24727,4,TRUE)<>"",VLOOKUP(A68,SP500相关数据!$B$11:$E$24727,4,TRUE),IF(VLOOKUP(A68-1,SP500相关数据!$B$11:$E$24727,4,TRUE)<>"",VLOOKUP(A68-1,SP500相关数据!$B$11:$E$24727,4,TRUE),VLOOKUP(A68-2,SP500相关数据!$B$11:$E$24727,4,TRUE))),"") | D68: =IF(VLOOKUP(A68,高收益利差!$A:$B,2,TRUE)<>"",VLOOKUP(A68,高收益利差!$A:$B,2,TRUE),IF(VLOOKUP(A68-1,高收益利差!$A:$B,2,TRUE)<>"",VLOOKUP(A68-1,高收益利差!$A:$B,2,TRUE),VLOOKUP(A68-2,高收益利差!$A:$B,2,TRUE))) | E68: =IFERROR(VLOOKUP(A68,'10Y2Y'!$A:$B,2,TRUE),"") | F68: =IFERROR(D68-D55,"") | G68: =IFERROR(B68/AVERAGE(B29:B68)-1,"") | H68: =IF(B68="","",IFERROR(AVERAGE(B29:B68)/AVERAGE(B16:B55)-1,"")) | I68: =IFERROR(VLOOKUP(A68,'Sahm Rule'!$A:$B,2,TRUE),"") | J68: =IFERROR((B68/B55)^4-1-D68/100,"")
A69: 35902 | B69: =IF(VLOOKUP(A69,SP500相关数据!$B$11:$C$24727,2,TRUE)<>"",VLOOKUP(A69,SP500相关数据!$B$11:$C$24727,2,TRUE),IF(VLOOKUP(A69-1,SP500相关数据!$B$11:$C$24727,2,TRUE)<>"",VLOOKUP(A69-1,SP500相关数据!$B$11:$C$24727,2,TRUE),VLOOKUP(A69-2,SP500相关数据!$B$11:$C$24727,2,TRUE))) | C69: =IFERROR(IF(VLOOKUP(A69,SP500相关数据!$B$11:$E$24727,4,TRUE)<>"",VLOOKUP(A69,SP500相关数据!$B$11:$E$24727,4,TRUE),IF(VLOOKUP(A69-1,SP500相关数据!$B$11:$E$24727,4,TRUE)<>"",VLOOKUP(A69-1,SP500相关数据!$B$11:$E$24727,4,TRUE),VLOOKUP(A69-2,SP500相关数据!$B$11:$E$24727,4,TRUE))),"") | D69: =IF(VLOOKUP(A69,高收益利差!$A:$B,2,TRUE)<>"",VLOOKUP(A69,高收益利差!$A:$B,2,TRUE),IF(VLOOKUP(A69-1,高收益利差!$A:$B,2,TRUE)<>"",VLOOKUP(A69-1,高收益利差!$A:$B,2,TRUE),VLOOKUP(A69-2,高收益利差!$A:$B,2,TRUE))) | E69: =IFERROR(VLOOKUP(A69,'10Y2Y'!$A:$B,2,TRUE),"") | F69: =IFERROR(D69-D56,"") | G69: =IFERROR(B69/AVERAGE(B30:B69)-1,"") | H69: =IF(B69="","",IFERROR(AVERAGE(B30:B69)/AVERAGE(B17:B56)-1,"")) | I69: =IFERROR(VLOOKUP(A69,'Sahm Rule'!$A:$B,2,TRUE),"") | J69: =IFERROR((B69/B56)^4-1-D69/100,"")
A70: 35909 | B70: =IF(VLOOKUP(A70,SP500相关数据!$B$11:$C$24727,2,TRUE)<>"",VLOOKUP(A70,SP500相关数据!$B$11:$C$24727,2,TRUE),IF(VLOOKUP(A70-1,SP500相关数据!$B$11:$C$24727,2,TRUE)<>"",VLOOKUP(A70-1,SP500相关数据!$B$11:$C$24727,2,TRUE),VLOOKUP(A70-2,SP500相关数据!$B$11:$C$24727,2,TRUE))) | C70: =IFERROR(IF(VLOOKUP(A70,SP500相关数据!$B$11:$E$24727,4,TRUE)<>"",VLOOKUP(A70,SP500相关数据!$B$11:$E$24727,4,TRUE),IF(VLOOKUP(A70-1,SP500相关数据!$B$11:$E$24727,4,TRUE)<>"",VLOOKUP(A70-1,SP500相关数据!$B$11:$E$24727,4,TRUE),VLOOKUP(A70-2,SP500相关数据!$B$11:$E$24727,4,TRUE))),"") | D70: =IF(VLOOKUP(A70,高收益利差!$A:$B,2,TRUE)<>"",VLOOKUP(A70,高收益利差!$A:$B,2,TRUE),IF(VLOOKUP(A70-1,高收益利差!$A:$B,2,TRUE)<>"",VLOOKUP(A70-1,高收益利差!$A:$B,2,TRUE),VLOOKUP(A70-2,高收益利差!$A:$B,2,TRUE))) | E70: =IFERROR(VLOOKUP(A70,'10Y2Y'!$A:$B,2,TRUE),"") | F70: =IFERROR(D70-D57,"") | G70: =IFERROR(B70/AVERAGE(B31:B70)-1,"") | H70: =IF(B70="","",IFERROR(AVERAGE(B31:B70)/AVERAGE(B18:B57)-1,"")) | I70: =IFERROR(VLOOKUP(A70,'Sahm Rule'!$A:$B,2,TRUE),"") | J70: =IFERROR((B70/B57)^4-1-D70/100,"")
A71: 35916 | B71: =IF(VLOOKUP(A71,SP500相关数据!$B$11:$C$24727,2,TRUE)<>"",VLOOKUP(A71,SP500相关数据!$B$11:$C$24727,2,TRUE),IF(VLOOKUP(A71-1,SP500相关数据!$B$11:$C$24727,2,TRUE)<>"",VLOOKUP(A71-1,SP500相关数据!$B$11:$C$24727,2,TRUE),VLOOKUP(A71-2,SP500相关数据!$B$11:$C$24727,2,TRUE))) | C71: =IFERROR(IF(VLOOKUP(A71,SP500相关数据!$B$11:$E$24727,4,TRUE)<>"",VLOOKUP(A71,SP500相关数据!$B$11:$E$24727,4,TRUE),IF(VLOOKUP(A71-1,SP500相关数据!$B$11:$E$24727,4,TRUE)<>"",VLOOKUP(A71-1,SP500相关数据!$B$11:$E$24727,4,TRUE),VLOOKUP(A71-2,SP500相关数据!$B$11:$E$24727,4,TRUE))),"") | D71: =IF(VLOOKUP(A71,高收益利差!$A:$B,2,TRUE)<>"",VLOOKUP(A71,高收益利差!$A:$B,2,TRUE),IF(VLOOKUP(A71-1,高收益利差!$A:$B,2,TRUE)<>"",VLOOKUP(A71-1,高收益利差!$A:$B,2,TRUE),VLOOKUP(A71-2,高收益利差!$A:$B,2,TRUE))) | E71: =IFERROR(VLOOKUP(A71,'10Y2Y'!$A:$B,2,TRUE),"") | F71: =IFERROR(D71-D58,"") | G71: =IFERROR(B71/AVERAGE(B32:B71)-1,"") | H71: =IF(B71="","",IFERROR(AVERAGE(B32:B71)/AVERAGE(B19:B58)-1,"")) | I71: =IFERROR(VLOOKUP(A71,'Sahm Rule'!$A:$B,2,TRUE),"") | J71: =IFERROR((B71/B58)^4-1-D71/100,"")
A72: 35923 | B72: =IF(VLOOKUP(A72,SP500相关数据!$B$11:$C$24727,2,TRUE)<>"",VLOOKUP(A72,SP500相关数据!$B$11:$C$24727,2,TRUE),IF(VLOOKUP(A72-1,SP500相关数据!$B$11:$C$24727,2,TRUE)<>"",VLOOKUP(A72-1,SP500相关数据!$B$11:$C$24727,2,TRUE),VLOOKUP(A72-2,SP500相关数据!$B$11:$C$24727,2,TRUE))) | C72: =IFERROR(IF(VLOOKUP(A72,SP500相关数据!$B$11:$E$24727,4,TRUE)<>"",VLOOKUP(A72,SP500相关数据!$B$11:$E$24727,4,TRUE),IF(VLOOKUP(A72-1,SP500相关数据!$B$11:$E$24727,4,TRUE)<>"",VLOOKUP(A72-1,SP500相关数据!$B$11:$E$24727,4,TRUE),VLOOKUP(A72-2,SP500相关数据!$B$11:$E$24727,4,TRUE))),"") | D72: =IF(VLOOKUP(A72,高收益利差!$A:$B,2,TRUE)<>"",VLOOKUP(A72,高收益利差!$A:$B,2,TRUE),IF(VLOOKUP(A72-1,高收益利差!$A:$B,2,TRUE)<>"",VLOOKUP(A72-1,高收益利差!$A:$B,2,TRUE),VLOOKUP(A72-2,高收益利差!$A:$B,2,TRUE))) | E72: =IFERROR(VLOOKUP(A72,'10Y2Y'!$A:$B,2,TRUE),"") | F72: =IFERROR(D72-D59,"") | G72: =IFERROR(B72/AVERAGE(B33:B72)-1,"") | H72: =IF(B72="","",IFERROR(AVERAGE(B33:B72)/AVERAGE(B20:B59)-1,"")) | I72: =IFERROR(VLOOKUP(A72,'Sahm Rule'!$A:$B,2,TRUE),"") | J72: =IFERROR((B72/B59)^4-1-D72/100,"")
A73: 35930 | B73: =IF(VLOOKUP(A73,SP500相关数据!$B$11:$C$24727,2,TRUE)<>"",VLOOKUP(A73,SP500相关数据!$B$11:$C$24727,2,TRUE),IF(VLOOKUP(A73-1,SP500相关数据!$B$11:$C$24727,2,TRUE)<>"",VLOOKUP(A73-1,SP500相关数据!$B$11:$C$24727,2,TRUE),VLOOKUP(A73-2,SP500相关数据!$B$11:$C$24727,2,TRUE))) | C73: =IFERROR(IF(VLOOKUP(A73,SP500相关数据!$B$11:$E$24727,4,TRUE)<>"",VLOOKUP(A73,SP500相关数据!$B$11:$E$24727,4,TRUE),IF(VLOOKUP(A73-1,SP500相关数据!$B$11:$E$24727,4,TRUE)<>"",VLOOKUP(A73-1,SP500相关数据!$B$11:$E$24727,4,TRUE),VLOOKUP(A73-2,SP500相关数据!$B$11:$E$24727,4,TRUE))),"") | D73: =IF(VLOOKUP(A73,高收益利差!$A:$B,2,TRUE)<>"",VLOOKUP(A73,高收益利差!$A:$B,2,TRUE),IF(VLOOKUP(A73-1,高收益利差!$A:$B,2,TRUE)<>"",VLOOKUP(A73-1,高收益利差!$A:$B,2,TRUE),VLOOKUP(A73-2,高收益利差!$A:$B,2,TRUE))) | E73: =IFERROR(VLOOKUP(A73,'10Y2Y'!$A:$B,2,TRUE),"") | F73: =IFERROR(D73-D60,"") | G73: =IFERROR(B73/AVERAGE(B34:B73)-1,"") | H73: =IF(B73="","",IFERROR(AVERAGE(B34:B73)/AVERAGE(B21:B60)-1,"")) | I73: =IFERROR(VLOOKUP(A73,'Sahm Rule'!$A:$B,2,TRUE),"") | J73: =IFERROR((B73/B60)^4-1-D73/100,"")
A74: 35937 | B74: =IF(VLOOKUP(A74,SP500相关数据!$B$11:$C$24727,2,TRUE)<>"",VLOOKUP(A74,SP500相关数据!$B$11:$C$24727,2,TRUE),IF(VLOOKUP(A74-1,SP500相关数据!$B$11:$C$24727,2,TRUE)<>"",VLOOKUP(A74-1,SP500相关数据!$B$11:$C$24727,2,TRUE),VLOOKUP(A74-2,SP500相关数据!$B$11:$C$24727,2,TRUE))) | C74: =IFERROR(IF(VLOOKUP(A74,SP500相关数据!$B$11:$E$24727,4,TRUE)<>"",VLOOKUP(A74,SP500相关数据!$B$11:$E$24727,4,TRUE),IF(VLOOKUP(A74-1,SP500相关数据!$B$11:$E$24727,4,TRUE)<>"",VLOOKUP(A74-1,SP500相关数据!$B$11:$E$24727,4,TRUE),VLOOKUP(A74-2,SP500相关数据!$B$11:$E$24727,4,TRUE))),"") | D74: =IF(VLOOKUP(A74,高收益利差!$A:$B,2,TRUE)<>"",VLOOKUP(A74,高收益利差!$A:$B,2,TRUE),IF(VLOOKUP(A74-1,高收益利差!$A:$B,2,TRUE)<>"",VLOOKUP(A74-1,高收益利差!$A:$B,2,TRUE),VLOOKUP(A74-2,高收益利差!$A:$B,2,TRUE))) | E74: =IFERROR(VLOOKUP(A74,'10Y2Y'!$A:$B,2,TRUE),"") | F74: =IFERROR(D74-D61,"") | G74: =IFERROR(B74/AVERAGE(B35:B74)-1,"") | H74: =IF(B74="","",IFERROR(AVERAGE(B35:B74)/AVERAGE(B22:B61)-1,"")) | I74: =IFERROR(VLOOKUP(A74,'Sahm Rule'!$A:$B,2,TRUE),"") | J74: =IFERROR((B74/B61)^4-1-D74/100,"")
A75: 35944 | B75: =IF(VLOOKUP(A75,SP500相关数据!$B$11:$C$24727,2,TRUE)<>"",VLOOKUP(A75,SP500相关数据!$B$11:$C$24727,2,TRUE),IF(VLOOKUP(A75-1,SP500相关数据!$B$11:$C$24727,2,TRUE)<>"",VLOOKUP(A75-1,SP500相关数据!$B$11:$C$24727,2,TRUE),VLOOKUP(A75-2,SP500相关数据!$B$11:$C$24727,2,TRUE))) | C75: =IFERROR(IF(VLOOKUP(A75,SP500相关数据!$B$11:$E$24727,4,TRUE)<>"",VLOOKUP(A75,SP500相关数据!$B$11:$E$24727,4,TRUE),IF(VLOOKUP(A75-1,SP500相关数据!$B$11:$E$24727,4,TRUE)<>"",VLOOKUP(A75-1,SP500相关数据!$B$11:$E$24727,4,TRUE),VLOOKUP(A75-2,SP500相关数据!$B$11:$E$24727,4,TRUE))),"") | D75: =IF(VLOOKUP(A75,高收益利差!$A:$B,2,TRUE)<>"",VLOOKUP(A75,高收益利差!$A:$B,2,TRUE),IF(VLOOKUP(A75-1,高收益利差!$A:$B,2,TRUE)<>"",VLOOKUP(A75-1,高收益利差!$A:$B,2,TRUE),VLOOKUP(A75-2,高收益利差!$A:$B,2,TRUE))) | E75: =IFERROR(VLOOKUP(A75,'10Y2Y'!$A:$B,2,TRUE),"") | F75: =IFERROR(D75-D62,"") | G75: =IFERROR(B75/AVERAGE(B36:B75)-1,"") | H75: =IF(B75="","",IFERROR(AVERAGE(B36:B75)/AVERAGE(B23:B62)-1,"")) | I75: =IFERROR(VLOOKUP(A75,'Sahm Rule'!$A:$B,2,TRUE),"") | J75: =IFERROR((B75/B62)^4-1-D75/100,"")
A76: 35951 | B76: =IF(VLOOKUP(A76,SP500相关数据!$B$11:$C$24727,2,TRUE)<>"",VLOOKUP(A76,SP500相关数据!$B$11:$C$24727,2,TRUE),IF(VLOOKUP(A76-1,SP500相关数据!$B$11:$C$24727,2,TRUE)<>"",VLOOKUP(A76-1,SP500相关数据!$B$11:$C$24727,2,TRUE),VLOOKUP(A76-2,SP500相关数据!$B$11:$C$24727,2,TRUE))) | C76: =IFERROR(IF(VLOOKUP(A76,SP500相关数据!$B$11:$E$24727,4,TRUE)<>"",VLOOKUP(A76,SP500相关数据!$B$11:$E$24727,4,TRUE),IF(VLOOKUP(A76-1,SP500相关数据!$B$11:$E$24727,4,TRUE)<>"",VLOOKUP(A76-1,SP500相关数据!$B$11:$E$24727,4,TRUE),VLOOKUP(A76-2,SP500相关数据!$B$11:$E$24727,4,TRUE))),"") | D76: =IF(VLOOKUP(A76,高收益利差!$A:$B,2,TRUE)<>"",VLOOKUP(A76,高收益利差!$A:$B,2,TRUE),IF(VLOOKUP(A76-1,高收益利差!$A:$B,2,TRUE)<>"",VLOOKUP(A76-1,高收益利差!$A:$B,2,TRUE),VLOOKUP(A76-2,高收益利差!$A:$B,2,TRUE))) | E76: =IFERROR(VLOOKUP(A76,'10Y2Y'!$A:$B,2,TRUE),"") | F76: =IFERROR(D76-D63,"") | G76: =IFERROR(B76/AVERAGE(B37:B76)-1,"") | H76: =IF(B76="","",IFERROR(AVERAGE(B37:B76)/AVERAGE(B24:B63)-1,"")) | I76: =IFERROR(VLOOKUP(A76,'Sahm Rule'!$A:$B,2,TRUE),"") | J76: =IFERROR((B76/B63)^4-1-D76/100,"")
A77: 35958 | B77: =IF(VLOOKUP(A77,SP500相关数据!$B$11:$C$24727,2,TRUE)<>"",VLOOKUP(A77,SP500相关数据!$B$11:$C$24727,2,TRUE),IF(VLOOKUP(A77-1,SP500相关数据!$B$11:$C$24727,2,TRUE)<>"",VLOOKUP(A77-1,SP500相关数据!$B$11:$C$24727,2,TRUE),VLOOKUP(A77-2,SP500相关数据!$B$11:$C$24727,2,TRUE))) | C77: =IFERROR(IF(VLOOKUP(A77,SP500相关数据!$B$11:$E$24727,4,TRUE)<>"",VLOOKUP(A77,SP500相关数据!$B$11:$E$24727,4,TRUE),IF(VLOOKUP(A77-1,SP500相关数据!$B$11:$E$24727,4,TRUE)<>"",VLOOKUP(A77-1,SP500相关数据!$B$11:$E$24727,4,TRUE),VLOOKUP(A77-2,SP500相关数据!$B$11:$E$24727,4,TRUE))),"") | D77: =IF(VLOOKUP(A77,高收益利差!$A:$B,2,TRUE)<>"",VLOOKUP(A77,高收益利差!$A:$B,2,TRUE),IF(VLOOKUP(A77-1,高收益利差!$A:$B,2,TRUE)<>"",VLOOKUP(A77-1,高收益利差!$A:$B,2,TRUE),VLOOKUP(A77-2,高收益利差!$A:$B,2,TRUE))) | E77: =IFERROR(VLOOKUP(A77,'10Y2Y'!$A:$B,2,TRUE),"") | F77: =IFERROR(D77-D64,"") | G77: =IFERROR(B77/AVERAGE(B38:B77)-1,"") | H77: =IF(B77="","",IFERROR(AVERAGE(B38:B77)/AVERAGE(B25:B64)-1,"")) | I77: =IFERROR(VLOOKUP(A77,'Sahm Rule'!$A:$B,2,TRUE),"") | J77: =IFERROR((B77/B64)^4-1-D77/100,"")
A78: 35965 | B78: =IF(VLOOKUP(A78,SP500相关数据!$B$11:$C$24727,2,TRUE)<>"",VLOOKUP(A78,SP500相关数据!$B$11:$C$24727,2,TRUE),IF(VLOOKUP(A78-1,SP500相关数据!$B$11:$C$24727,2,TRUE)<>"",VLOOKUP(A78-1,SP500相关数据!$B$11:$C$24727,2,TRUE),VLOOKUP(A78-2,SP500相关数据!$B$11:$C$24727,2,TRUE))) | C78: =IFERROR(IF(VLOOKUP(A78,SP500相关数据!$B$11:$E$24727,4,TRUE)<>"",VLOOKUP(A78,SP500相关数据!$B$11:$E$24727,4,TRUE),IF(VLOOKUP(A78-1,SP500相关数据!$B$11:$E$24727,4,TRUE)<>"",VLOOKUP(A78-1,SP500相关数据!$B$11:$E$24727,4,TRUE),VLOOKUP(A78-2,SP500相关数据!$B$11:$E$24727,4,TRUE))),"") | D78: =IF(VLOOKUP(A78,高收益利差!$A:$B,2,TRUE)<>"",VLOOKUP(A78,高收益利差!$A:$B,2,TRUE),IF(VLOOKUP(A78-1,高收益利差!$A:$B,2,TRUE)<>"",VLOOKUP(A78-1,高收益利差!$A:$B,2,TRUE),VLOOKUP(A78-2,高收益利差!$A:$B,2,TRUE))) | E78: =IFERROR(VLOOKUP(A78,'10Y2Y'!$A:$B,2,TRUE),"") | F78: =IFERROR(D78-D65,"") | G78: =IFERROR(B78/AVERAGE(B39:B78)-1,"") | H78: =IF(B78="","",IFERROR(AVERAGE(B39:B78)/AVERAGE(B26:B65)-1,"")) | I78: =IFERROR(VLOOKUP(A78,'Sahm Rule'!$A:$B,2,TRUE),"") | J78: =IFERROR((B78/B65)^4-1-D78/100,"")
A79: 35972 | B79: =IF(VLOOKUP(A79,SP500相关数据!$B$11:$C$24727,2,TRUE)<>"",VLOOKUP(A79,SP500相关数据!$B$11:$C$24727,2,TRUE),IF(VLOOKUP(A79-1,SP500相关数据!$B$11:$C$24727,2,TRUE)<>"",VLOOKUP(A79-1,SP500相关数据!$B$11:$C$24727,2,TRUE),VLOOKUP(A79-2,SP500相关数据!$B$11:$C$24727,2,TRUE))) | C79: =IFERROR(IF(VLOOKUP(A79,SP500相关数据!$B$11:$E$24727,4,TRUE)<>"",VLOOKUP(A79,SP500相关数据!$B$11:$E$24727,4,TRUE),IF(VLOOKUP(A79-1,SP500相关数据!$B$11:$E$24727,4,TRUE)<>"",VLOOKUP(A79-1,SP500相关数据!$B$11:$E$24727,4,TRUE),VLOOKUP(A79-2,SP500相关数据!$B$11:$E$24727,4,TRUE))),"") | D79: =IF(VLOOKUP(A79,高收益利差!$A:$B,2,TRUE)<>"",VLOOKUP(A79,高收益利差!$A:$B,2,TRUE),IF(VLOOKUP(A79-1,高收益利差!$A:$B,2,TRUE)<>"",VLOOKUP(A79-1,高收益利差!$A:$B,2,TRUE),VLOOKUP(A79-2,高收益利差!$A:$B,2,TRUE))) | E79: =IFERROR(VLOOKUP(A79,'10Y2Y'!$A:$B,2,TRUE),"") | F79: =IFERROR(D79-D66,"") | G79: =IFERROR(B79/AVERAGE(B40:B79)-1,"") | H79: =IF(B79="","",IFERROR(AVERAGE(B40:B79)/AVERAGE(B27:B66)-1,"")) | I79: =IFERROR(VLOOKUP(A79,'Sahm Rule'!$A:$B,2,TRUE),"") | J79: =IFERROR((B79/B66)^4-1-D79/100,"")
A80: 35979 | B80: =IF(VLOOKUP(A80,SP500相关数据!$B$11:$C$24727,2,TRUE)<>"",VLOOKUP(A80,SP500相关数据!$B$11:$C$24727,2,TRUE),IF(VLOOKUP(A80-1,SP500相关数据!$B$11:$C$24727,2,TRUE)<>"",VLOOKUP(A80-1,SP500相关数据!$B$11:$C$24727,2,TRUE),VLOOKUP(A80-2,SP500相关数据!$B$11:$C$24727,2,TRUE))) | C80: =IFERROR(IF(VLOOKUP(A80,SP500相关数据!$B$11:$E$24727,4,TRUE)<>"",VLOOKUP(A80,SP500相关数据!$B$11:$E$24727,4,TRUE),IF(VLOOKUP(A80-1,SP500相关数据!$B$11:$E$24727,4,TRUE)<>"",VLOOKUP(A80-1,SP500相关数据!$B$11:$E$24727,4,TRUE),VLOOKUP(A80-2,SP500相关数据!$B$11:$E$24727,4,TRUE))),"") | D80: =IF(VLOOKUP(A80,高收益利差!$A:$B,2,TRUE)<>"",VLOOKUP(A80,高收益利差!$A:$B,2,TRUE),IF(VLOOKUP(A80-1,高收益利差!$A:$B,2,TRUE)<>"",VLOOKUP(A80-1,高收益利差!$A:$B,2,TRUE),VLOOKUP(A80-2,高收益利差!$A:$B,2,TRUE))) | E80: =IFERROR(VLOOKUP(A80,'10Y2Y'!$A:$B,2,TRUE),"") | F80: =IFERROR(D80-D67,"") | G80: =IFERROR(B80/AVERAGE(B41:B80)-1,"") | H80: =IF(B80="","",IFERROR(AVERAGE(B41:B80)/AVERAGE(B28:B67)-1,"")) | I80: =IFERROR(VLOOKUP(A80,'Sahm Rule'!$A:$B,2,TRUE),"") | J80: =IFERROR((B80/B67)^4-1-D80/100,"")
A81: 35986 | B81: =IF(VLOOKUP(A81,SP500相关数据!$B$11:$C$24727,2,TRUE)<>"",VLOOKUP(A81,SP500相关数据!$B$11:$C$24727,2,TRUE),IF(VLOOKUP(A81-1,SP500相关数据!$B$11:$C$24727,2,TRUE)<>"",VLOOKUP(A81-1,SP500相关数据!$B$11:$C$24727,2,TRUE),VLOOKUP(A81-2,SP500相关数据!$B$11:$C$24727,2,TRUE))) | C81: =IFERROR(IF(VLOOKUP(A81,SP500相关数据!$B$11:$E$24727,4,TRUE)<>"",VLOOKUP(A81,SP500相关数据!$B$11:$E$24727,4,TRUE),IF(VLOOKUP(A81-1,SP500相关数据!$B$11:$E$24727,4,TRUE)<>"",VLOOKUP(A81-1,SP500相关数据!$B$11:$E$24727,4,TRUE),VLOOKUP(A81-2,SP500相关数据!$B$11:$E$24727,4,TRUE))),"") | D81: =IF(VLOOKUP(A81,高收益利差!$A:$B,2,TRUE)<>"",VLOOKUP(A81,高收益利差!$A:$B,2,TRUE),IF(VLOOKUP(A81-1,高收益利差!$A:$B,2,TRUE)<>"",VLOOKUP(A81-1,高收益利差!$A:$B,2,TRUE),VLOOKUP(A81-2,高收益利差!$A:$B,2,TRUE))) | E81: =IFERROR(VLOOKUP(A81,'10Y2Y'!$A:$B,2,TRUE),"") | F81: =IFERROR(D81-D68,"") | G81: =IFERROR(B81/AVERAGE(B42:B81)-1,"") | H81: =IF(B81="","",IFERROR(AVERAGE(B42:B81)/AVERAGE(B29:B68)-1,"")) | I81: =IFERROR(VLOOKUP(A81,'Sahm Rule'!$A:$B,2,TRUE),"") | J81: =IFERROR((B81/B68)^4-1-D81/100,"")
A82: 35993 | B82: =IF(VLOOKUP(A82,SP500相关数据!$B$11:$C$24727,2,TRUE)<>"",VLOOKUP(A82,SP500相关数据!$B$11:$C$24727,2,TRUE),IF(VLOOKUP(A82-1,SP500相关数据!$B$11:$C$24727,2,TRUE)<>"",VLOOKUP(A82-1,SP500相关数据!$B$11:$C$24727,2,TRUE),VLOOKUP(A82-2,SP500相关数据!$B$11:$C$24727,2,TRUE))) | C82: =IFERROR(IF(VLOOKUP(A82,SP500相关数据!$B$11:$E$24727,4,TRUE)<>"",VLOOKUP(A82,SP500相关数据!$B$11:$E$24727,4,TRUE),IF(VLOOKUP(A82-1,SP500相关数据!$B$11:$E$24727,4,TRUE)<>"",VLOOKUP(A82-1,SP500相关数据!$B$11:$E$24727,4,TRUE),VLOOKUP(A82-2,SP500相关数据!$B$11:$E$24727,4,TRUE))),"") | D82: =IF(VLOOKUP(A82,高收益利差!$A:$B,2,TRUE)<>"",VLOOKUP(A82,高收益利差!$A:$B,2,TRUE),IF(VLOOKUP(A82-1,高收益利差!$A:$B,2,TRUE)<>"",VLOOKUP(A82-1,高收益利差!$A:$B,2,TRUE),VLOOKUP(A82-2,高收益利差!$A:$B,2,TRUE))) | E82: =IFERROR(VLOOKUP(A82,'10Y2Y'!$A:$B,2,TRUE),"") | F82: =IFERROR(D82-D69,"") | G82: =IFERROR(B82/AVERAGE(B43:B82)-1,"") | H82: =IF(B82="","",IFERROR(AVERAGE(B43:B82)/AVERAGE(B30:B69)-1,"")) | I82: =IFERROR(VLOOKUP(A82,'Sahm Rule'!$A:$B,2,TRUE),"") | J82: =IFERROR((B82/B69)^4-1-D82/100,"")
A83: 36000 | B83: =IF(VLOOKUP(A83,SP500相关数据!$B$11:$C$24727,2,TRUE)<>"",VLOOKUP(A83,SP500相关数据!$B$11:$C$24727,2,TRUE),IF(VLOOKUP(A83-1,SP500相关数据!$B$11:$C$24727,2,TRUE)<>"",VLOOKUP(A83-1,SP500相关数据!$B$11:$C$24727,2,TRUE),VLOOKUP(A83-2,SP500相关数据!$B$11:$C$24727,2,TRUE))) | C83: =IFERROR(IF(VLOOKUP(A83,SP500相关数据!$B$11:$E$24727,4,TRUE)<>"",VLOOKUP(A83,SP500相关数据!$B$11:$E$24727,4,TRUE),IF(VLOOKUP(A83-1,SP500相关数据!$B$11:$E$24727,4,TRUE)<>"",VLOOKUP(A83-1,SP500相关数据!$B$11:$E$24727,4,TRUE),VLOOKUP(A83-2,SP500相关数据!$B$11:$E$24727,4,TRUE))),"") | D83: =IF(VLOOKUP(A83,高收益利差!$A:$B,2,TRUE)<>"",VLOOKUP(A83,高收益利差!$A:$B,2,TRUE),IF(VLOOKUP(A83-1,高收益利差!$A:$B,2,TRUE)<>"",VLOOKUP(A83-1,高收益利差!$A:$B,2,TRUE),VLOOKUP(A83-2,高收益利差!$A:$B,2,TRUE))) | E83: =IFERROR(VLOOKUP(A83,'10Y2Y'!$A:$B,2,TRUE),"") | F83: =IFERROR(D83-D70,"") | G83: =IFERROR(B83/AVERAGE(B44:B83)-1,"") | H83: =IF(B83="","",IFERROR(AVERAGE(B44:B83)/AVERAGE(B31:B70)-1,"")) | I83: =IFERROR(VLOOKUP(A83,'Sahm Rule'!$A:$B,2,TRUE),"") | J83: =IFERROR((B83/B70)^4-1-D83/100,"")
A84: 36007 | B84: =IF(VLOOKUP(A84,SP500相关数据!$B$11:$C$24727,2,TRUE)<>"",VLOOKUP(A84,SP500相关数据!$B$11:$C$24727,2,TRUE),IF(VLOOKUP(A84-1,SP500相关数据!$B$11:$C$24727,2,TRUE)<>"",VLOOKUP(A84-1,SP500相关数据!$B$11:$C$24727,2,TRUE),VLOOKUP(A84-2,SP500相关数据!$B$11:$C$24727,2,TRUE))) | C84: =IFERROR(IF(VLOOKUP(A84,SP500相关数据!$B$11:$E$24727,4,TRUE)<>"",VLOOKUP(A84,SP500相关数据!$B$11:$E$24727,4,TRUE),IF(VLOOKUP(A84-1,SP500相关数据!$B$11:$E$24727,4,TRUE)<>"",VLOOKUP(A84-1,SP500相关数据!$B$11:$E$24727,4,TRUE),VLOOKUP(A84-2,SP500相关数据!$B$11:$E$24727,4,TRUE))),"") | D84: =IF(VLOOKUP(A84,高收益利差!$A:$B,2,TRUE)<>"",VLOOKUP(A84,高收益利差!$A:$B,2,TRUE),IF(VLOOKUP(A84-1,高收益利差!$A:$B,2,TRUE)<>"",VLOOKUP(A84-1,高收益利差!$A:$B,2,TRUE),VLOOKUP(A84-2,高收益利差!$A:$B,2,TRUE))) | E84: =IFERROR(VLOOKUP(A84,'10Y2Y'!$A:$B,2,TRUE),"") | F84: =IFERROR(D84-D71,"") | G84: =IFERROR(B84/AVERAGE(B45:B84)-1,"") | H84: =IF(B84="","",IFERROR(AVERAGE(B45:B84)/AVERAGE(B32:B71)-1,"")) | I84: =IFERROR(VLOOKUP(A84,'Sahm Rule'!$A:$B,2,TRUE),"") | J84: =IFERROR((B84/B71)^4-1-D84/100,"")
A85: 36014 | B85: =IF(VLOOKUP(A85,SP500相关数据!$B$11:$C$24727,2,TRUE)<>"",VLOOKUP(A85,SP500相关数据!$B$11:$C$24727,2,TRUE),IF(VLOOKUP(A85-1,SP500相关数据!$B$11:$C$24727,2,TRUE)<>"",VLOOKUP(A85-1,SP500相关数据!$B$11:$C$24727,2,TRUE),VLOOKUP(A85-2,SP500相关数据!$B$11:$C$24727,2,TRUE))) | C85: =IFERROR(IF(VLOOKUP(A85,SP500相关数据!$B$11:$E$24727,4,TRUE)<>"",VLOOKUP(A85,SP500相关数据!$B$11:$E$24727,4,TRUE),IF(VLOOKUP(A85-1,SP500相关数据!$B$11:$E$24727,4,TRUE)<>"",VLOOKUP(A85-1,SP500相关数据!$B$11:$E$24727,4,TRUE),VLOOKUP(A85-2,SP500相关数据!$B$11:$E$24727,4,TRUE))),"") | D85: =IF(VLOOKUP(A85,高收益利差!$A:$B,2,TRUE)<>"",VLOOKUP(A85,高收益利差!$A:$B,2,TRUE),IF(VLOOKUP(A85-1,高收益利差!$A:$B,2,TRUE)<>"",VLOOKUP(A85-1,高收益利差!$A:$B,2,TRUE),VLOOKUP(A85-2,高收益利差!$A:$B,2,TRUE))) | E85: =IFERROR(VLOOKUP(A85,'10Y2Y'!$A:$B,2,TRUE),"") | F85: =IFERROR(D85-D72,"") | G85: =IFERROR(B85/AVERAGE(B46:B85)-1,"") | H85: =IF(B85="","",IFERROR(AVERAGE(B46:B85)/AVERAGE(B33:B72)-1,"")) | I85: =IFERROR(VLOOKUP(A85,'Sahm Rule'!$A:$B,2,TRUE),"") | J85: =IFERROR((B85/B72)^4-1-D85/100,"")
A86: 36021 | B86: =IF(VLOOKUP(A86,SP500相关数据!$B$11:$C$24727,2,TRUE)<>"",VLOOKUP(A86,SP500相关数据!$B$11:$C$24727,2,TRUE),IF(VLOOKUP(A86-1,SP500相关数据!$B$11:$C$24727,2,TRUE)<>"",VLOOKUP(A86-1,SP500相关数据!$B$11:$C$24727,2,TRUE),VLOOKUP(A86-2,SP500相关数据!$B$11:$C$24727,2,TRUE))) | C86: =IFERROR(IF(VLOOKUP(A86,SP500相关数据!$B$11:$E$24727,4,TRUE)<>"",VLOOKUP(A86,SP500相关数据!$B$11:$E$24727,4,TRUE),IF(VLOOKUP(A86-1,SP500相关数据!$B$11:$E$24727,4,TRUE)<>"",VLOOKUP(A86-1,SP500相关数据!$B$11:$E$24727,4,TRUE),VLOOKUP(A86-2,SP500相关数据!$B$11:$E$24727,4,TRUE))),"") | D86: =IF(VLOOKUP(A86,高收益利差!$A:$B,2,TRUE)<>"",VLOOKUP(A86,高收益利差!$A:$B,2,TRUE),IF(VLOOKUP(A86-1,高收益利差!$A:$B,2,TRUE)<>"",VLOOKUP(A86-1,高收益利差!$A:$B,2,TRUE),VLOOKUP(A86-2,高收益利差!$A:$B,2,TRUE))) | E86: =IFERROR(VLOOKUP(A86,'10Y2Y'!$A:$B,2,TRUE),"") | F86: =IFERROR(D86-D73,"") | G86: =IFERROR(B86/AVERAGE(B47:B86)-1,"") | H86: =IF(B86="","",IFERROR(AVERAGE(B47:B86)/AVERAGE(B34:B73)-1,"")) | I86: =IFERROR(VLOOKUP(A86,'Sahm Rule'!$A:$B,2,TRUE),"") | J86: =IFERROR((B86/B73)^4-1-D86/100,"")
A87: 36028 | B87: =IF(VLOOKUP(A87,SP500相关数据!$B$11:$C$24727,2,TRUE)<>"",VLOOKUP(A87,SP500相关数据!$B$11:$C$24727,2,TRUE),IF(VLOOKUP(A87-1,SP500相关数据!$B$11:$C$24727,2,TRUE)<>"",VLOOKUP(A87-1,SP500相关数据!$B$11:$C$24727,2,TRUE),VLOOKUP(A87-2,SP500相关数据!$B$11:$C$24727,2,TRUE))) | C87: =IFERROR(IF(VLOOKUP(A87,SP500相关数据!$B$11:$E$24727,4,TRUE)<>"",VLOOKUP(A87,SP500相关数据!$B$11:$E$24727,4,TRUE),IF(VLOOKUP(A87-1,SP500相关数据!$B$11:$E$24727,4,TRUE)<>"",VLOOKUP(A87-1,SP500相关数据!$B$11:$E$24727,4,TRUE),VLOOKUP(A87-2,SP500相关数据!$B$11:$E$24727,4,TRUE))),"") | D87: =IF(VLOOKUP(A87,高收益利差!$A:$B,2,TRUE)<>"",VLOOKUP(A87,高收益利差!$A:$B,2,TRUE),IF(VLOOKUP(A87-1,高收益利差!$A:$B,2,TRUE)<>"",VLOOKUP(A87-1,高收益利差!$A:$B,2,TRUE),VLOOKUP(A87-2,高收益利差!$A:$B,2,TRUE))) | E87: =IFERROR(VLOOKUP(A87,'10Y2Y'!$A:$B,2,TRUE),"") | F87: =IFERROR(D87-D74,"") | G87: =IFERROR(B87/AVERAGE(B48:B87)-1,"") | H87: =IF(B87="","",IFERROR(AVERAGE(B48:B87)/AVERAGE(B35:B74)-1,"")) | I87: =IFERROR(VLOOKUP(A87,'Sahm Rule'!$A:$B,2,TRUE),"") | J87: =IFERROR((B87/B74)^4-1-D87/100,"")
A88: 36035 | B88: =IF(VLOOKUP(A88,SP500相关数据!$B$11:$C$24727,2,TRUE)<>"",VLOOKUP(A88,SP500相关数据!$B$11:$C$24727,2,TRUE),IF(VLOOKUP(A88-1,SP500相关数据!$B$11:$C$24727,2,TRUE)<>"",VLOOKUP(A88-1,SP500相关数据!$B$11:$C$24727,2,TRUE),VLOOKUP(A88-2,SP500相关数据!$B$11:$C$24727,2,TRUE))) | C88: =IFERROR(IF(VLOOKUP(A88,SP500相关数据!$B$11:$E$24727,4,TRUE)<>"",VLOOKUP(A88,SP500相关数据!$B$11:$E$24727,4,TRUE),IF(VLOOKUP(A88-1,SP500相关数据!$B$11:$E$24727,4,TRUE)<>"",VLOOKUP(A88-1,SP500相关数据!$B$11:$E$24727,4,TRUE),VLOOKUP(A88-2,SP500相关数据!$B$11:$E$24727,4,TRUE))),"") | D88: =IF(VLOOKUP(A88,高收益利差!$A:$B,2,TRUE)<>"",VLOOKUP(A88,高收益利差!$A:$B,2,TRUE),IF(VLOOKUP(A88-1,高收益利差!$A:$B,2,TRUE)<>"",VLOOKUP(A88-1,高收益利差!$A:$B,2,TRUE),VLOOKUP(A88-2,高收益利差!$A:$B,2,TRUE))) | E88: =IFERROR(VLOOKUP(A88,'10Y2Y'!$A:$B,2,TRUE),"") | F88: =IFERROR(D88-D75,"") | G88: =IFERROR(B88/AVERAGE(B49:B88)-1,"") | H88: =IF(B88="","",IFERROR(AVERAGE(B49:B88)/AVERAGE(B36:B75)-1,"")) | I88: =IFERROR(VLOOKUP(A88,'Sahm Rule'!$A:$B,2,TRUE),"") | J88: =IFERROR((B88/B75)^4-1-D88/100,"")
A89: 36042 | B89: =IF(VLOOKUP(A89,SP500相关数据!$B$11:$C$24727,2,TRUE)<>"",VLOOKUP(A89,SP500相关数据!$B$11:$C$24727,2,TRUE),IF(VLOOKUP(A89-1,SP500相关数据!$B$11:$C$24727,2,TRUE)<>"",VLOOKUP(A89-1,SP500相关数据!$B$11:$C$24727,2,TRUE),VLOOKUP(A89-2,SP500相关数据!$B$11:$C$24727,2,TRUE))) | C89: =IFERROR(IF(VLOOKUP(A89,SP500相关数据!$B$11:$E$24727,4,TRUE)<>"",VLOOKUP(A89,SP500相关数据!$B$11:$E$24727,4,TRUE),IF(VLOOKUP(A89-1,SP500相关数据!$B$11:$E$24727,4,TRUE)<>"",VLOOKUP(A89-1,SP500相关数据!$B$11:$E$24727,4,TRUE),VLOOKUP(A89-2,SP500相关数据!$B$11:$E$24727,4,TRUE))),"") | D89: =IF(VLOOKUP(A89,高收益利差!$A:$B,2,TRUE)<>"",VLOOKUP(A89,高收益利差!$A:$B,2,TRUE),IF(VLOOKUP(A89-1,高收益利差!$A:$B,2,TRUE)<>"",VLOOKUP(A89-1,高收益利差!$A:$B,2,TRUE),VLOOKUP(A89-2,高收益利差!$A:$B,2,TRUE))) | E89: =IFERROR(VLOOKUP(A89,'10Y2Y'!$A:$B,2,TRUE),"") | F89: =IFERROR(D89-D76,"") | G89: =IFERROR(B89/AVERAGE(B50:B89)-1,"") | H89: =IF(B89="","",IFERROR(AVERAGE(B50:B89)/AVERAGE(B37:B76)-1,"")) | I89: =IFERROR(VLOOKUP(A89,'Sahm Rule'!$A:$B,2,TRUE),"") | J89: =IFERROR((B89/B76)^4-1-D89/100,"")
A90: 36049 | B90: =IF(VLOOKUP(A90,SP500相关数据!$B$11:$C$24727,2,TRUE)<>"",VLOOKUP(A90,SP500相关数据!$B$11:$C$24727,2,TRUE),IF(VLOOKUP(A90-1,SP500相关数据!$B$11:$C$24727,2,TRUE)<>"",VLOOKUP(A90-1,SP500相关数据!$B$11:$C$24727,2,TRUE),VLOOKUP(A90-2,SP500相关数据!$B$11:$C$24727,2,TRUE))) | C90: =IFERROR(IF(VLOOKUP(A90,SP500相关数据!$B$11:$E$24727,4,TRUE)<>"",VLOOKUP(A90,SP500相关数据!$B$11:$E$24727,4,TRUE),IF(VLOOKUP(A90-1,SP500相关数据!$B$11:$E$24727,4,TRUE)<>"",VLOOKUP(A90-1,SP500相关数据!$B$11:$E$24727,4,TRUE),VLOOKUP(A90-2,SP500相关数据!$B$11:$E$24727,4,TRUE))),"") | D90: =IF(VLOOKUP(A90,高收益利差!$A:$B,2,TRUE)<>"",VLOOKUP(A90,高收益利差!$A:$B,2,TRUE),IF(VLOOKUP(A90-1,高收益利差!$A:$B,2,TRUE)<>"",VLOOKUP(A90-1,高收益利差!$A:$B,2,TRUE),VLOOKUP(A90-2,高收益利差!$A:$B,2,TRUE))) | E90: =IFERROR(VLOOKUP(A90,'10Y2Y'!$A:$B,2,TRUE),"") | F90: =IFERROR(D90-D77,"") | G90: =IFERROR(B90/AVERAGE(B51:B90)-1,"") | H90: =IF(B90="","",IFERROR(AVERAGE(B51:B90)/AVERAGE(B38:B77)-1,"")) | I90: =IFERROR(VLOOKUP(A90,'Sahm Rule'!$A:$B,2,TRUE),"") | J90: =IFERROR((B90/B77)^4-1-D90/100,"")
A91: 36056 | B91: =IF(VLOOKUP(A91,SP500相关数据!$B$11:$C$24727,2,TRUE)<>"",VLOOKUP(A91,SP500相关数据!$B$11:$C$24727,2,TRUE),IF(VLOOKUP(A91-1,SP500相关数据!$B$11:$C$24727,2,TRUE)<>"",VLOOKUP(A91-1,SP500相关数据!$B$11:$C$24727,2,TRUE),VLOOKUP(A91-2,SP500相关数据!$B$11:$C$24727,2,TRUE))) | C91: =IFERROR(IF(VLOOKUP(A91,SP500相关数据!$B$11:$E$24727,4,TRUE)<>"",VLOOKUP(A91,SP500相关数据!$B$11:$E$24727,4,TRUE),IF(VLOOKUP(A91-1,SP500相关数据!$B$11:$E$24727,4,TRUE)<>"",VLOOKUP(A91-1,SP500相关数据!$B$11:$E$24727,4,TRUE),VLOOKUP(A91-2,SP500相关数据!$B$11:$E$24727,4,TRUE))),"") | D91: =IF(VLOOKUP(A91,高收益利差!$A:$B,2,TRUE)<>"",VLOOKUP(A91,高收益利差!$A:$B,2,TRUE),IF(VLOOKUP(A91-1,高收益利差!$A:$B,2,TRUE)<>"",VLOOKUP(A91-1,高收益利差!$A:$B,2,TRUE),VLOOKUP(A91-2,高收益利差!$A:$B,2,TRUE))) | E91: =IFERROR(VLOOKUP(A91,'10Y2Y'!$A:$B,2,TRUE),"") | F91: =IFERROR(D91-D78,"") | G91: =IFERROR(B91/AVERAGE(B52:B91)-1,"") | H91: =IF(B91="","",IFERROR(AVERAGE(B52:B91)/AVERAGE(B39:B78)-1,"")) | I91: =IFERROR(VLOOKUP(A91,'Sahm Rule'!$A:$B,2,TRUE),"") | J91: =IFERROR((B91/B78)^4-1-D91/100,"")
A92: 36063 | B92: =IF(VLOOKUP(A92,SP500相关数据!$B$11:$C$24727,2,TRUE)<>"",VLOOKUP(A92,SP500相关数据!$B$11:$C$24727,2,TRUE),IF(VLOOKUP(A92-1,SP500相关数据!$B$11:$C$24727,2,TRUE)<>"",VLOOKUP(A92-1,SP500相关数据!$B$11:$C$24727,2,TRUE),VLOOKUP(A92-2,SP500相关数据!$B$11:$C$24727,2,TRUE))) | C92: =IFERROR(IF(VLOOKUP(A92,SP500相关数据!$B$11:$E$24727,4,TRUE)<>"",VLOOKUP(A92,SP500相关数据!$B$11:$E$24727,4,TRUE),IF(VLOOKUP(A92-1,SP500相关数据!$B$11:$E$24727,4,TRUE)<>"",VLOOKUP(A92-1,SP500相关数据!$B$11:$E$24727,4,TRUE),VLOOKUP(A92-2,SP500相关数据!$B$11:$E$24727,4,TRUE))),"") | D92: =IF(VLOOKUP(A92,高收益利差!$A:$B,2,TRUE)<>"",VLOOKUP(A92,高收益利差!$A:$B,2,TRUE),IF(VLOOKUP(A92-1,高收益利差!$A:$B,2,TRUE)<>"",VLOOKUP(A92-1,高收益利差!$A:$B,2,TRUE),VLOOKUP(A92-2,高收益利差!$A:$B,2,TRUE))) | E92: =IFERROR(VLOOKUP(A92,'10Y2Y'!$A:$B,2,TRUE),"") | F92: =IFERROR(D92-D79,"") | G92: =IFERROR(B92/AVERAGE(B53:B92)-1,"") | H92: =IF(B92="","",IFERROR(AVERAGE(B53:B92)/AVERAGE(B40:B79)-1,"")) | I92: =IFERROR(VLOOKUP(A92,'Sahm Rule'!$A:$B,2,TRUE),"") | J92: =IFERROR((B92/B79)^4-1-D92/100,"")
A93: 36070 | B93: =IF(VLOOKUP(A93,SP500相关数据!$B$11:$C$24727,2,TRUE)<>"",VLOOKUP(A93,SP500相关数据!$B$11:$C$24727,2,TRUE),IF(VLOOKUP(A93-1,SP500相关数据!$B$11:$C$24727,2,TRUE)<>"",VLOOKUP(A93-1,SP500相关数据!$B$11:$C$24727,2,TRUE),VLOOKUP(A93-2,SP500相关数据!$B$11:$C$24727,2,TRUE))) | C93: =IFERROR(IF(VLOOKUP(A93,SP500相关数据!$B$11:$E$24727,4,TRUE)<>"",VLOOKUP(A93,SP500相关数据!$B$11:$E$24727,4,TRUE),IF(VLOOKUP(A93-1,SP500相关数据!$B$11:$E$24727,4,TRUE)<>"",VLOOKUP(A93-1,SP500相关数据!$B$11:$E$24727,4,TRUE),VLOOKUP(A93-2,SP500相关数据!$B$11:$E$24727,4,TRUE))),"") | D93: =IF(VLOOKUP(A93,高收益利差!$A:$B,2,TRUE)<>"",VLOOKUP(A93,高收益利差!$A:$B,2,TRUE),IF(VLOOKUP(A93-1,高收益利差!$A:$B,2,TRUE)<>"",VLOOKUP(A93-1,高收益利差!$A:$B,2,TRUE),VLOOKUP(A93-2,高收益利差!$A:$B,2,TRUE))) | E93: =IFERROR(VLOOKUP(A93,'10Y2Y'!$A:$B,2,TRUE),"") | F93: =IFERROR(D93-D80,"") | G93: =IFERROR(B93/AVERAGE(B54:B93)-1,"") | H93: =IF(B93="","",IFERROR(AVERAGE(B54:B93)/AVERAGE(B41:B80)-1,"")) | I93: =IFERROR(VLOOKUP(A93,'Sahm Rule'!$A:$B,2,TRUE),"") | J93: =IFERROR((B93/B80)^4-1-D93/100,"")
A94: 36077 | B94: =IF(VLOOKUP(A94,SP500相关数据!$B$11:$C$24727,2,TRUE)<>"",VLOOKUP(A94,SP500相关数据!$B$11:$C$24727,2,TRUE),IF(VLOOKUP(A94-1,SP500相关数据!$B$11:$C$24727,2,TRUE)<>"",VLOOKUP(A94-1,SP500相关数据!$B$11:$C$24727,2,TRUE),VLOOKUP(A94-2,SP500相关数据!$B$11:$C$24727,2,TRUE))) | C94: =IFERROR(IF(VLOOKUP(A94,SP500相关数据!$B$11:$E$24727,4,TRUE)<>"",VLOOKUP(A94,SP500相关数据!$B$11:$E$24727,4,TRUE),IF(VLOOKUP(A94-1,SP500相关数据!$B$11:$E$24727,4,TRUE)<>"",VLOOKUP(A94-1,SP500相关数据!$B$11:$E$24727,4,TRUE),VLOOKUP(A94-2,SP500相关数据!$B$11:$E$24727,4,TRUE))),"") | D94: =IF(VLOOKUP(A94,高收益利差!$A:$B,2,TRUE)<>"",VLOOKUP(A94,高收益利差!$A:$B,2,TRUE),IF(VLOOKUP(A94-1,高收益利差!$A:$B,2,TRUE)<>"",VLOOKUP(A94-1,高收益利差!$A:$B,2,TRUE),VLOOKUP(A94-2,高收益利差!$A:$B,2,TRUE))) | E94: =IFERROR(VLOOKUP(A94,'10Y2Y'!$A:$B,2,TRUE),"") | F94: =IFERROR(D94-D81,"") | G94: =IFERROR(B94/AVERAGE(B55:B94)-1,"") | H94: =IF(B94="","",IFERROR(AVERAGE(B55:B94)/AVERAGE(B42:B81)-1,"")) | I94: =IFERROR(VLOOKUP(A94,'Sahm Rule'!$A:$B,2,TRUE),"") | J94: =IFERROR((B94/B81)^4-1-D94/100,"")
A95: 36084 | B95: =IF(VLOOKUP(A95,SP500相关数据!$B$11:$C$24727,2,TRUE)<>"",VLOOKUP(A95,SP500相关数据!$B$11:$C$24727,2,TRUE),IF(VLOOKUP(A95-1,SP500相关数据!$B$11:$C$24727,2,TRUE)<>"",VLOOKUP(A95-1,SP500相关数据!$B$11:$C$24727,2,TRUE),VLOOKUP(A95-2,SP500相关数据!$B$11:$C$24727,2,TRUE))) | C95: =IFERROR(IF(VLOOKUP(A95,SP500相关数据!$B$11:$E$24727,4,TRUE)<>"",VLOOKUP(A95,SP500相关数据!$B$11:$E$24727,4,TRUE),IF(VLOOKUP(A95-1,SP500相关数据!$B$11:$E$24727,4,TRUE)<>"",VLOOKUP(A95-1,SP500相关数据!$B$11:$E$24727,4,TRUE),VLOOKUP(A95-2,SP500相关数据!$B$11:$E$24727,4,TRUE))),"") | D95: =IF(VLOOKUP(A95,高收益利差!$A:$B,2,TRUE)<>"",VLOOKUP(A95,高收益利差!$A:$B,2,TRUE),IF(VLOOKUP(A95-1,高收益利差!$A:$B,2,TRUE)<>"",VLOOKUP(A95-1,高收益利差!$A:$B,2,TRUE),VLOOKUP(A95-2,高收益利差!$A:$B,2,TRUE))) | E95: =IFERROR(VLOOKUP(A95,'10Y2Y'!$A:$B,2,TRUE),"") | F95: =IFERROR(D95-D82,"") | G95: =IFERROR(B95/AVERAGE(B56:B95)-1,"") | H95: =IF(B95="","",IFERROR(AVERAGE(B56:B95)/AVERAGE(B43:B82)-1,"")) | I95: =IFERROR(VLOOKUP(A95,'Sahm Rule'!$A:$B,2,TRUE),"") | J95: =IFERROR((B95/B82)^4-1-D95/100,"")
A96: 36091 | B96: =IF(VLOOKUP(A96,SP500相关数据!$B$11:$C$24727,2,TRUE)<>"",VLOOKUP(A96,SP500相关数据!$B$11:$C$24727,2,TRUE),IF(VLOOKUP(A96-1,SP500相关数据!$B$11:$C$24727,2,TRUE)<>"",VLOOKUP(A96-1,SP500相关数据!$B$11:$C$24727,2,TRUE),VLOOKUP(A96-2,SP500相关数据!$B$11:$C$24727,2,TRUE))) | C96: =IFERROR(IF(VLOOKUP(A96,SP500相关数据!$B$11:$E$24727,4,TRUE)<>"",VLOOKUP(A96,SP500相关数据!$B$11:$E$24727,4,TRUE),IF(VLOOKUP(A96-1,SP500相关数据!$B$11:$E$24727,4,TRUE)<>"",VLOOKUP(A96-1,SP500相关数据!$B$11:$E$24727,4,TRUE),VLOOKUP(A96-2,SP500相关数据!$B$11:$E$24727,4,TRUE))),"") | D96: =IF(VLOOKUP(A96,高收益利差!$A:$B,2,TRUE)<>"",VLOOKUP(A96,高收益利差!$A:$B,2,TRUE),IF(VLOOKUP(A96-1,高收益利差!$A:$B,2,TRUE)<>"",VLOOKUP(A96-1,高收益利差!$A:$B,2,TRUE),VLOOKUP(A96-2,高收益利差!$A:$B,2,TRUE))) | E96: =IFERROR(VLOOKUP(A96,'10Y2Y'!$A:$B,2,TRUE),"") | F96: =IFERROR(D96-D83,"") | G96: =IFERROR(B96/AVERAGE(B57:B96)-1,"") | H96: =IF(B96="","",IFERROR(AVERAGE(B57:B96)/AVERAGE(B44:B83)-1,"")) | I96: =IFERROR(VLOOKUP(A96,'Sahm Rule'!$A:$B,2,TRUE),"") | J96: =IFERROR((B96/B83)^4-1-D96/100,"")
A97: 36098 | B97: =IF(VLOOKUP(A97,SP500相关数据!$B$11:$C$24727,2,TRUE)<>"",VLOOKUP(A97,SP500相关数据!$B$11:$C$24727,2,TRUE),IF(VLOOKUP(A97-1,SP500相关数据!$B$11:$C$24727,2,TRUE)<>"",VLOOKUP(A97-1,SP500相关数据!$B$11:$C$24727,2,TRUE),VLOOKUP(A97-2,SP500相关数据!$B$11:$C$24727,2,TRUE))) | C97: =IFERROR(IF(VLOOKUP(A97,SP500相关数据!$B$11:$E$24727,4,TRUE)<>"",VLOOKUP(A97,SP500相关数据!$B$11:$E$24727,4,TRUE),IF(VLOOKUP(A97-1,SP500相关数据!$B$11:$E$24727,4,TRUE)<>"",VLOOKUP(A97-1,SP500相关数据!$B$11:$E$24727,4,TRUE),VLOOKUP(A97-2,SP500相关数据!$B$11:$E$24727,4,TRUE))),"") | D97: =IF(VLOOKUP(A97,高收益利差!$A:$B,2,TRUE)<>"",VLOOKUP(A97,高收益利差!$A:$B,2,TRUE),IF(VLOOKUP(A97-1,高收益利差!$A:$B,2,TRUE)<>"",VLOOKUP(A97-1,高收益利差!$A:$B,2,TRUE),VLOOKUP(A97-2,高收益利差!$A:$B,2,TRUE))) | E97: =IFERROR(VLOOKUP(A97,'10Y2Y'!$A:$B,2,TRUE),"") | F97: =IFERROR(D97-D84,"") | G97: =IFERROR(B97/AVERAGE(B58:B97)-1,"") | H97: =IF(B97="","",IFERROR(AVERAGE(B58:B97)/AVERAGE(B45:B84)-1,"")) | I97: =IFERROR(VLOOKUP(A97,'Sahm Rule'!$A:$B,2,TRUE),"") | J97: =IFERROR((B97/B84)^4-1-D97/100,"")
A98: 36105 | B98: =IF(VLOOKUP(A98,SP500相关数据!$B$11:$C$24727,2,TRUE)<>"",VLOOKUP(A98,SP500相关数据!$B$11:$C$24727,2,TRUE),IF(VLOOKUP(A98-1,SP500相关数据!$B$11:$C$24727,2,TRUE)<>"",VLOOKUP(A98-1,SP500相关数据!$B$11:$C$24727,2,TRUE),VLOOKUP(A98-2,SP500相关数据!$B$11:$C$24727,2,TRUE))) | C98: =IFERROR(IF(VLOOKUP(A98,SP500相关数据!$B$11:$E$24727,4,TRUE)<>"",VLOOKUP(A98,SP500相关数据!$B$11:$E$24727,4,TRUE),IF(VLOOKUP(A98-1,SP500相关数据!$B$11:$E$24727,4,TRUE)<>"",VLOOKUP(A98-1,SP500相关数据!$B$11:$E$24727,4,TRUE),VLOOKUP(A98-2,SP500相关数据!$B$11:$E$24727,4,TRUE))),"") | D98: =IF(VLOOKUP(A98,高收益利差!$A:$B,2,TRUE)<>"",VLOOKUP(A98,高收益利差!$A:$B,2,TRUE),IF(VLOOKUP(A98-1,高收益利差!$A:$B,2,TRUE)<>"",VLOOKUP(A98-1,高收益利差!$A:$B,2,TRUE),VLOOKUP(A98-2,高收益利差!$A:$B,2,TRUE))) | E98: =IFERROR(VLOOKUP(A98,'10Y2Y'!$A:$B,2,TRUE),"") | F98: =IFERROR(D98-D85,"") | G98: =IFERROR(B98/AVERAGE(B59:B98)-1,"") | H98: =IF(B98="","",IFERROR(AVERAGE(B59:B98)/AVERAGE(B46:B85)-1,"")) | I98: =IFERROR(VLOOKUP(A98,'Sahm Rule'!$A:$B,2,TRUE),"") | J98: =IFERROR((B98/B85)^4-1-D98/100,"")
A99: 36112 | B99: =IF(VLOOKUP(A99,SP500相关数据!$B$11:$C$24727,2,TRUE)<>"",VLOOKUP(A99,SP500相关数据!$B$11:$C$24727,2,TRUE),IF(VLOOKUP(A99-1,SP500相关数据!$B$11:$C$24727,2,TRUE)<>"",VLOOKUP(A99-1,SP500相关数据!$B$11:$C$24727,2,TRUE),VLOOKUP(A99-2,SP500相关数据!$B$11:$C$24727,2,TRUE))) | C99: =IFERROR(IF(VLOOKUP(A99,SP500相关数据!$B$11:$E$24727,4,TRUE)<>"",VLOOKUP(A99,SP500相关数据!$B$11:$E$24727,4,TRUE),IF(VLOOKUP(A99-1,SP500相关数据!$B$11:$E$24727,4,TRUE)<>"",VLOOKUP(A99-1,SP500相关数据!$B$11:$E$24727,4,TRUE),VLOOKUP(A99-2,SP500相关数据!$B$11:$E$24727,4,TRUE))),"") | D99: =IF(VLOOKUP(A99,高收益利差!$A:$B,2,TRUE)<>"",VLOOKUP(A99,高收益利差!$A:$B,2,TRUE),IF(VLOOKUP(A99-1,高收益利差!$A:$B,2,TRUE)<>"",VLOOKUP(A99-1,高收益利差!$A:$B,2,TRUE),VLOOKUP(A99-2,高收益利差!$A:$B,2,TRUE))) | E99: =IFERROR(VLOOKUP(A99,'10Y2Y'!$A:$B,2,TRUE),"") | F99: =IFERROR(D99-D86,"") | G99: =IFERROR(B99/AVERAGE(B60:B99)-1,"") | H99: =IF(B99="","",IFERROR(AVERAGE(B60:B99)/AVERAGE(B47:B86)-1,"")) | I99: =IFERROR(VLOOKUP(A99,'Sahm Rule'!$A:$B,2,TRUE),"") | J99: =IFERROR((B99/B86)^4-1-D99/100,"")
A100: 36119 | B100: =IF(VLOOKUP(A100,SP500相关数据!$B$11:$C$24727,2,TRUE)<>"",VLOOKUP(A100,SP500相关数据!$B$11:$C$24727,2,TRUE),IF(VLOOKUP(A100-1,SP500相关数据!$B$11:$C$24727,2,TRUE)<>"",VLOOKUP(A100-1,SP500相关数据!$B$11:$C$24727,2,TRUE),VLOOKUP(A100-2,SP500相关数据!$B$11:$C$24727,2,TRUE))) | C100: =IFERROR(IF(VLOOKUP(A100,SP500相关数据!$B$11:$E$24727,4,TRUE)<>"",VLOOKUP(A100,SP500相关数据!$B$11:$E$24727,4,TRUE),IF(VLOOKUP(A100-1,SP500相关数据!$B$11:$E$24727,4,TRUE)<>"",VLOOKUP(A100-1,SP500相关数据!$B$11:$E$24727,4,TRUE),VLOOKUP(A100-2,SP500相关数据!$B$11:$E$24727,4,TRUE))),"") | D100: =IF(VLOOKUP(A100,高收益利差!$A:$B,2,TRUE)<>"",VLOOKUP(A100,高收益利差!$A:$B,2,TRUE),IF(VLOOKUP(A100-1,高收益利差!$A:$B,2,TRUE)<>"",VLOOKUP(A100-1,高收益利差!$A:$B,2,TRUE),VLOOKUP(A100-2,高收益利差!$A:$B,2,TRUE))) | E100: =IFERROR(VLOOKUP(A100,'10Y2Y'!$A:$B,2,TRUE),"") | F100: =IFERROR(D100-D87,"") | G100: =IFERROR(B100/AVERAGE(B61:B100)-1,"") | H100: =IF(B100="","",IFERROR(AVERAGE(B61:B100)/AVERAGE(B48:B87)-1,"")) | I100: =IFERROR(VLOOKUP(A100,'Sahm Rule'!$A:$B,2,TRUE),"") | J100: =IFERROR((B100/B87)^4-1-D100/100,"")
...

Sheet Sahm Rule
A1: observation_date | B1: SAHMREALTIME | D1: FRED Graph Observations
A2: 21885 | B2: 0.77 | D2: Federal Reserve Economic Data, Federal Reserve Bank of St. Louis
A3: 21916 | B3: 0.5 | D3: Link: https://fred.stlouisfed.org
A4: 21947 | B4: 0.13 | D4: Help: https://fredhelp.stlouisfed.org
A5: 21976 | B5: 0.1 | D5: This data may be copyrighted. Please refer to the Terms of Use: https://fred.stlouisfed.org/legal#fred-terms-faq
A6: 22007 | B6: 0.03 | D6: File Created: 2026-04-12 11:21 pm CDT
A7: 22037 | B7: 0.07
A8: 22068 | B8: 0.1 | D8: SAHMREALTIME | E8: Real-time Sahm Rule Recession Indicator, Percentage Points, Monthly, Seasonally Adjusted | F8: Data Updated: 2026-04-03
A9: 22098 | B9: 0.23
A10: 22129 | B10: 0.53
A11: 22160 | B11: 0.6
A12: 22190 | B12: 0.93
A13: 22221 | B13: 1.07
A14: 22251 | B14: 1.3
A15: 22282 | B15: 1.4
A16: 22313 | B16: 1.6
A17: 22341 | B17: 1.63
A18: 22372 | B18: 1.7
A19: 22402 | B19: 1.67
A20: 22433 | B20: 1.63
... A791: 45901 | B791: 0.23
A792: 45931
A793: 45962 | B793: 0.43
A794: 45992 | B794: 0.35
A795: 46023 | B795: 0.3
A796: 46054 | B796: 0.27
A797: 46082 | B797: 0.2

Sheet 10Y2Y
A1: observation_date | B1: T10Y2Y | D1: FRED Graph Observations
A2: 27912 | B2: 0.68 | D2: Federal Reserve Economic Data, Federal Reserve Bank of St. Louis
A3: 27913 | B3: 0.71 | D3: Link: https://fred.stlouisfed.org
A4: 27914 | B4: 0.7 | D4: Help: https://fredhelp.stlouisfed.org
A5: 27915 | B5: 0.77 | D5: This data may be copyrighted. Please refer to the Terms of Use: https://fred.stlouisfed.org/legal#fred-terms-faq
A6: 27918 | B6: 0.79 | D6: File Created: 2026-04-13 10:08 pm CDT
A7: 27919 | B7: 0.79
A8: 27920 | B8: 0.82 | D8: T10Y2Y | E8: 10-Year Treasury Constant Maturity Minus 2-Year Treasury Constant Maturity, Percent, Daily, Not Seasonally Adjusted | F8: Data Updated: 2026-04-13
A9: 27921 | B9: 0.86
A10: 27922 | B10: 0.83
A11: 27925 | B11: 0.83
A12: 27926 | B12: 0.83
A13: 27927 | B13: 0.81
A14: 27928 | B14: 0.79
A15: 27929 | B15: 0.82
A16: 27932 | B16: 0.85
A17: 27933 | B17: 0.8
A18: 27934 | B18: 0.8
A19: 27935 | B19: 0.82
A20: 27936 | B20: 0.81
... A25: 27943 | B25: 0.85
A26: 27946
A27: 27947 | B27: 0.86
A28: 27948 | B28: 0.85
A29: 27949 | B29: 0.9
A30: 27950 | B30: 1.01
A31: 27953 | B31: 1.04
A32: 27954 | B32: 1.03
A33: 27955 | B33: 1.03
A34: 27956 | B34: 1.05
A35: 27957 | B35: 0.98
A36: 27960 | B36: 0.97
A37: 27961 | B37: 0.96
A38: 27962 | B38: 0.96
... A70: 28006 | B70: 1.13
A71: 28009
A72: 28010 | B72: 1.18
A73: 28011 | B73: 1.2
A74: 28012 | B74: 1.17
A75: 28013 | B75: 1.18
A76: 28016 | B76: 1.17
A77: 28017 | B77: 1.15
A78: 28018 | B78: 1.17
A79: 28019 | B79: 1.19
A80: 28020 | B80: 1.23
A81: 28023 | B81: 1.18
A82: 28024 | B82: 1.21
A83: 28025 | B83: 1.17
... A95: 28041 | B95: 1.51
A96: 28044
A97: 28045 | B97: 1.55
A98: 28046 | B98: 1.53
A99: 28047 | B99: 1.53
A100: 28048 | B100: 1.56
A101: 28051 | B101: 1.54
A102: 28052 | B102: 1.5
A103: 28053 | B103: 1.43
A104: 28054 | B104: 1.41
A105: 28055 | B105: 1.41
A106: 28058 | B106: 1.42
A107: 28059 | B107: 1.43
A108: 28060 | B108: 1.44
... A111: 28065 | B111: 1.35
A112: 28066
A113: 28067 | B113: 1.37
A114: 28068 | B114: 1.43
A115: 28069 | B115: 1.4
A116: 28072 | B116: 1.42
A117: 28073 | B117: 1.39
A118: 28074 | B118: 1.42
A119: 28075
A120: 28076 | B120: 1.42
A121: 28079 | B121: 1.41
A122: 28080 | B122: 1.47
A123: 28081 | B123: 1.5
A124: 28082 | B124: 1.5
A125: 28083 | B125: 1.57
A126: 28086 | B126: 1.61
A127: 28087 | B127: 1.57
A128: 28088 | B128: 1.58
A129: 28089
A130: 28090 | B130: 1.58
A131: 28093 | B131: 1.56
A132: 28094 | B132: 1.59
A133: 28095 | B133: 1.57
A134: 28096 | B134: 1.58
A135: 28097 | B135: 1.55
A136: 28100 | B136: 1.5
A137: 28101 | B137: 1.47
A138: 28102 | B138: 1.48
A139: 28103 | B139: 1.48
A140: 28104 | B140: 1.51
A141: 28107 | B141: 1.47
... A149: 28117 | B149: 1.48
A150: 28118
A151: 28121 | B151: 1.47
A152: 28122 | B152: 1.47
A153: 28123 | B153: 1.45
A154: 28124 | B154: 1.42
A155: 28125 | B155: 1.47
...

Sheet 高收益利差
A1: observation_date | B1: BAMLH0A0HYM2 | D1: FRED Graph Observations
A2: 35430 | B2: 3.13 | D2: Federal Reserve Economic Data, Federal Reserve Bank of St. Louis
A3: 35431 | D3: Link: https://fred.stlouisfed.org
A4: 35432 | B4: 3.06 | D4: Help: https://fredhelp.stlouisfed.org
A5: 35433 | B5: 3.09 | D5: This data may be copyrighted. Please refer to the Terms of Use: https://fred.stlouisfed.org/legal#fred-terms-faq
A6: 35436 | B6: 3.1 | D6: File Created: 2026-04-08 8:24 pm CDT
A7: 35437 | B7: 3.1
A8: 35438 | B8: 3.07 | D8: BAMLH0A0HYM2 | E8: ICE BofA US High Yield Index Option-Adjusted Spread, Percent, Daily, Not Seasonally Adjusted | F8: Data Updated: 2026-04-08
A9: 35439 | B9: 3.13
A10: 35440 | B10: 3.16
A11: 35443 | B11: 3.04
A12: 35444 | B12: 3.09
A13: 35445 | B13: 3.07
A14: 35446 | B14: 3.02
A15: 35447 | B15: 3.04
A16: 35450 | B16: 3.03
A17: 35451 | B17: 3.05
A18: 35452 | B18: 2.99
A19: 35453 | B19: 2.97
A20: 35454 | B20: 2.94
... A35: 35475 | B35: 3.05
A36: 35478
A37: 35479 | B37: 3.01
A38: 35480 | B38: 2.98
A39: 35481 | B39: 2.89
A40: 35482 | B40: 2.89
A41: 35485 | B41: 2.85
A42: 35486 | B42: 2.83
A43: 35487 | B43: 2.71
A44: 35488 | B44: 2.71
A45: 35489 | B45: 2.73
A46: 35492 | B46: 2.71
A47: 35493 | B47: 2.67
A48: 35494 | B48: 2.71
... A64: 35516 | B64: 2.67
A65: 35517
A66: 35520 | B66: 2.84
A67: 35521 | B67: 2.9
A68: 35522 | B68: 2.94
A69: 35523 | B69: 2.95
A70: 35524 | B70: 2.92
A71: 35527 | B71: 2.95
A72: 35528 | B72: 2.93
A73: 35529 | B73: 2.91
A74: 35530 | B74: 2.92
A75: 35531 | B75: 2.87
A76: 35534 | B76: 2.88
A77: 35535 | B77: 2.93
... A105: 35573 | B105: 2.64
A106: 35576
A107: 35577 | B107: 2.6
A108: 35578 | B108: 2.61
A109: 35579 | B109: 2.61
A110: 35580 | B110: 2.65
A111: 35581 | B111: 2.68
A112: 35583 | B112: 2.66
A113: 35584 | B113: 2.68
A114: 35585 | B114: 2.65
A115: 35586 | B115: 2.6
A116: 35587 | B116: 2.7
A117: 35590 | B117: 2.59
A118: 35591 | B118: 2.56
... A135: 35614 | B135: 2.79
A136: 35615
A137: 35618 | B137: 2.82
A138: 35619 | B138: 2.8
A139: 35620 | B139: 2.8
A140: 35621 | B140: 2.78
A141: 35622 | B141: 2.76
A142: 35625 | B142: 2.71
A143: 35626 | B143: 2.69
A144: 35627 | B144: 2.71
A145: 35628 | B145: 2.7
A146: 35629 | B146: 2.67
A147: 35632 | B147: 2.66
A148: 35633 | B148: 2.72
... A177: 35673 | B177: 2.59
A178: 35674
A179: 35675 | B179: 2.62
A180: 35676 | B180: 2.6
A181: 35677 | B181: 2.61
A182: 35678 | B182: 2.6
A183: 35681 | B183: 2.6
A184: 35682 | B184: 2.59
A185: 35683 | B185: 2.55
A186: 35684 | B186: 2.55
A187: 35685 | B187: 2.62
A188: 35688 | B188: 2.61
A189: 35689 | B189: 2.69
A190: 35690 | B190: 2.65
... A261: 35788 | B261: 2.94
A262: 35789
A263: 35790 | B263: 2.93
A264: 35793 | B264: 2.92
A265: 35794 | B265: 2.91
A266: 35795 | B266: 2.96
A267: 35796
A268: 35797 | B268: 3.02
A269: 35800 | B269: 3.09
A270: 35801 | B270: 3.1
...

Sheet SP500相关数据
B2: Wind
B3: 国家 | C3: 美国 | D3: 美国 | E3: 美国
B4: 指标名称 | C4: 美国:标准普尔500指数 | D4: 标普500偏离200日均线偏离度 | E4: 标准普尔500波动率指数(VIX)
B5: 频率 | C5: 日 | D5: 日 | E5: 日
B6: 单位 | C6: 点
B7: 指标ID | C7: G0001672 | D7: s4 | E7: G0003892
B8: 时间区间 | C8: 1928-01-03:2026-04-08 | D8: 1928-10-17:2026-04-08 | E8: 1990-01-02:2026-04-08
B9: 来源 | C9: 标准普尔 | D9: 标准普尔 | E9: 芝加哥期权交易所
B10: 更新时间 | C10: 2026-04-09 | D10: 2026-04-09 | E10: 2026-04-09
B11: 10230 | C11: 17.76
B12: 10231 | C12: 17.72
B13: 10232 | C13: 17.55
B14: 10233 | C14: 17.66
B15: 10236 | C15: 17.5
B16: 10237 | C16: 17.37
B17: 10238 | C17: 17.35
B18: 10239 | C18: 17.47
B19: 10240 | C19: 17.58
B20: 10243 | C20: 17.29
B21: 10244 | C21: 17.3
B22: 10245 | C22: 17.26
... B209: 10517 | C209: 21.72
B210: 10518 | C210: 21.79 | D210: 0.126312
B211: 10519 | C211: 21.84 | D211: 0.127542
B212: 10520 | C212: 21.96 | D212: 0.131919
B213: 10523 | C213: 21.81 | D213: 0.123959
B214: 10524 | C214: 21.95 | D214: 0.129245
B215: 10525 | C215: 21.99 | D215: 0.129903
B216: 10526 | C216: 21.91 | D216: 0.125083
B217: 10527 | C217: 21.65 | D217: 0.112034
B218: 10530 | C218: 22 | D218: 0.126901
B219: 10531 | C219: 21.76 | D219: 0.114854
B220: 10532 | C220: 21.68 | D220: 0.11004
B221: 10533 | C221: 21.99 | D221: 0.123031
... B15563: 32871 | C15563: 353.4 | D15563: 0.063904
B15564: 32875 | C15564: 359.69 | D15564: 0.080536 | E15564: 17.24
B15565: 32876 | C15565: 358.76 | D15565: 0.07691 | E15565: 18.19
B15566: 32877 | C15566: 355.67 | D15566: 0.067292 | E15566: 19.22
B15567: 32878 | C15567: 352.2 | D15567: 0.05656 | E15567: 20.11
B15568: 32881 | C15568: 353.79 | D15568: 0.060092 | E15568: 20.26
B15569: 32882 | C15569: 349.62 | D15569: 0.047349 | E15569: 22.2
B15570: 32883 | C15570: 347.31 | D15570: 0.039885 | E15570: 22.44
B15571: 32884 | C15571: 348.53 | D15571: 0.04255 | E15571: 20.05
B15572: 32885 | C15572: 339.93 | D15572: 0.016856 | E15572: 24.64
B15573: 32888 | C15573: 337 | D15573: 0.007569 | E15573: 26.34
B15574: 32889 | C15574: 340.75 | D15574: 0.017972 | E15574: 24.18
B15575: 32890 | C15575: 337.4 | D15575: 0.007464 | E15575: 24.16
... B15857: 33297 | C15857: 367.07 | D15857: 0.091916 | E15857: 21.23
B15858: 33298 | C15858: 370.47 | D15858: 0.10089
B15859: 33301 | C15859: 369.33 | D15859: 0.097587 | E15859: 20.86
B15860: 33302 | C15860: 376.72 | D15860: 0.117069 | E15860: 20.45
B15861: 33303 | C15861: 376.17 | D15861: 0.115337 | E15861: 20.55
B15862: 33304 | C15862: 375.91 | D15862: 0.114385 | E15862: 21.05
B15863: 33305 | C15863: 374.95 | D15863: 0.111594 | E15863: 20.81
B15864: 33308 | C15864: 372.96 | D15864: 0.106056 | E15864: 20.88
B15865: 33309 | C15865: 370.03 | D15865: 0.097938 | E15865: 18.82
B15866: 33310 | C15866: 374.57 | D15866: 0.109925 | E15866: 16.09
B15867: 33311 | C15867: 373.5 | D15867: 0.106876 | E15867: 14.94
B15868: 33312 | C15868: 373.59 | D15868: 0.106933 | E15868: 14.9
B15869: 33315 | C15869: 372.11 | D15869: 0.102831 | E15869: 15.79
B15870: 33316 | C15870: 366.59 | D15870: 0.087897 | E15870: 16.11
... B17355: 35460 | C17355: 784.17 | D17355: 0.124014 | E17355: 19.47
B17356: 35461 | C17356: 786.16 | D17356: 0.12552
B17357: 35464 | C17357: 786.73 | D17357: 0.125224 | E17357: 19.58
B17358: 35465 | C17358: 789.26 | D17358: 0.127417 | E17358: 19.43
B17359: 35466 | C17359: 778.28 | D17359: 0.112496 | E17359: 21.06
B17360: 35467 | C17360: 780.15 | D17360: 0.113962 | E17360: 20.16
B17361: 35468 | C17361: 789.56 | D17361: 0.12497 | E17361: 18.9
B17362: 35471 | C17362: 785.43 | D17362: 0.118779 | E17362: 20.65
B17363: 35472 | C17363: 789.59 | D17363: 0.123091 | E17363: 19.97
B17364: 35473 | C17364: 802.77 | D17364: 0.138582 | E17364: 19.48
B17365: 35474 | C17365: 811.82 | D17365: 0.148668 | E17365: 19.23
B17366: 35475 | C17366: 808.48 | D17366: 0.143366 | E17366: 19.18
B17367: 35479 | C17367: 816.29 | D17367: 0.151734 | E17367: 19.7
B17368: 35480 | C17368: 812.49 | D17368: 0.145845 | E17368: 20.61
... B17563: 35759 | C17563: 950.82 | D17563: 0.080006 | E17563: 28.95
B17564: 35760 | C17564: 951.64 | D17564: 0.080021
B17565: 35762 | C17565: 955.4 | D17565: 0.083147 | E17565: 27.43
B17566: 35765 | C17566: 974.78 | D17566: 0.102283 | E17566: 26.01
B17567: 35766 | C17567: 971.68 | D17567: 0.098216 | E17567: 25.66
B17568: 35767 | C17568: 976.77 | D17568: 0.102508 | E17568: 23.92
B17569: 35768 | C17569: 973.1 | D17569: 0.097778 | E17569: 23.84
B17570: 35769 | C17570: 983.79 | D17570: 0.107673 | E17570: 22.65
B17571: 35772 | C17571: 982.37 | D17571: 0.105255 | E17571: 23.22
B17572: 35773 | C17572: 975.78 | D17572: 0.097599 | E17572: 23.36
B17573: 35774 | C17573: 969.79 | D17573: 0.090515 | E17573: 24.55
B17574: 35775 | C17574: 954.94 | D17574: 0.074182 | E17574: 27.63
B17575: 35776 | C17575: 953.39 | D17575: 0.071641 | E17575: 27.92
B17576: 35779 | C17576: 963.39 | D17576: 0.081129 | E17576: 27.37
... B22853: 43438 | C22853: 2700.06 | D22853: -0.022713 | E22853: 20.74
B22854: 43439 | E22854: 20.74
B22855: 43440 | C22855: 2695.95 | D22855: -0.024227 | E22855: 21.19
B22856: 43441 | C22856: 2633.08 | D22856: -0.047695 | E22856: 23.23
B22857: 43444 | C22857: 2637.72 | D22857: -0.045736 | E22857: 22.64
B22858: 43445 | C22858: 2636.78 | D22858: -0.045834 | E22858: 21.76
B22859: 43446 | C22859: 2651.07 | D22859: -0.04026 | E22859: 21.46
B22860: 43447 | C22860: 2650.54 | D22860: -0.040345 | E22860: 20.65
B22861: 43448 | C22861: 2599.95 | D22861: -0.059476 | E22861: 21.63
B22862: 43451 | C22862: 2545.94 | D22862: -0.080205 | E22862: 24.52
B22863: 43452 | C22863: 2546.16 | D22863: -0.079801 | E22863: 25.58
...

Sheet _图表数据
A1: 日期 | B1: SP500 | C1: 简单模式 | D1: 普通模式 | E1: 困难模式 | F1: 噩梦模式 | G1: 地狱模式 | H1: 炼狱模式
